Icarus-Verliog-testing/Constants/constants.vh
//DEFINE CONSTANTS
// `define KEY_WIDTH 16 // width of the key. In multiples of 4.
// `define KEY_QSPI_COUNT `KEY_WIDTH/4 // number of QSPI transactions per key sent in LSB. 
// `define KEY_QSPI_COUNT_REG $clog2(`KEY_QSPI_COUNT+1) // register size required to count the current QSPI transaction of the key + 1. log2(`KEY_QSPI_COUNT+1)

`define ENCRYPTER_WIDTH 32 // width of the bus between the Paralellizer and Encrypter, and the Encrypter and Collector. In multiples of 4.
`define ENCRYPTER_WIDTH_COUNT_REG $clog2(`ENCRYPTER_WIDTH+1) // register size required to count the current bit of the encrypter bus + 1. log2(`ENCRYPTER_WIDTH+1). (Verilog doesn't like me so i need a for loop)
`define ENCRYPTER_QSPI_COUNT `ENCRYPTER_WIDTH/4 // number of QSPI transactions per Encrypter.
`define ENCRYPTER_QSPI_COUNT_REG $clog2(`ENCRYPTER_QSPI_COUNT+1) // register size required to count the current QSPI transaction of the Encrypter + 1. log2(`ENCRYPTER_QSPI_COUNT+1)

`define KEY_ROTATION_WIDTH $clog2(`ENCRYPTER_WIDTH) // width of the key rotation bus between Paralellizer and Encrypter. log2(`KEY_WIDTH)
`define KEY_ROTATION_WIDTH_COUNT_REG $clog2(`KEY_ROTATION_WIDTH+1) // register size required to count the current bit of the key rotation bus + 1. log2(`KEY_ROTATION_WIDTH+1). (Verilog doesn't like me so i need a for loop)

// `define KEY_ENCRYPTER_COUNT `KEY_WIDTH/`ENCRYPTER_WIDTH // number of Encrypters transactions per key. `KEY_WIDTH/`ENCRYPTER_WIDTH
// `define KEY_ENCRYPTER_COUNT_REG $clog2(`KEY_ENCRYPTER_COUNT+1) // register size required to count the current Encrypter transaction of the key + 1. log2(`KEY_ENCRYPTER_COUNT+1)

`define NUM_ENCRYPTERS 2 // number of Encrypters
`define NUM_ENCRYPTERS_REG $clog2(`NUM_ENCRYPTERS+1) // register size required to count the current Encrypter + 1. log2(`NUM_ENCRYPTERS+1)

Icarus-Verliog-testing/Paralellizer/paralellizer.sv
`include "./Constants/constants.vh"

`define STATE_IDLE 3'b000
`define STATE_PROGRAMMING 3'b001
`define STATE_RECEIVING_KEY 3'b010
`define STATE_PROGRAMMING_ENCRYPTERS 3'b011
`define STATE_WAITING_FOR_READY_ENCRYPTERS 3'b100
`define STATE_ENCRYPTING 3'b101

module Paralellizer (
    input wire clk,
    input wire reset,
    //QSPI
    input wire [3:0] qspi_data,
    input wire qspi_sending,
    output reg qspi_ready,
    //Program
    input wire prog,
    //To encrypters
    output reg [`ENCRYPTER_WIDTH-1:0] encrypters_data  [`NUM_ENCRYPTERS-1:0],
    output reg [`KEY_ROTATION_WIDTH-1:0] encrypters_key_rotation [`NUM_ENCRYPTERS-1],
    output reg [`NUM_ENCRYPTERS-1:0] encrypters_program,
    output reg [`NUM_ENCRYPTERS-1:0] encrypters_data_ready,
    input wire [`NUM_ENCRYPTERS-1:0] encrypters_ready,
    //Watchers
    output reg [2:0] state_out,
    output reg [`KEY_WIDTH-1:0] key_out,
    output reg [`KEY_ROTATION_WIDTH-1:0] key_rotation_out,
    output reg [`KEY_QSPI_COUNT_REG-1:0] key_index_out,
    output reg [`KEY_ENCRYPTER_COUNT_REG-1:0] key_encrypter_index_out,
    output reg [`ENCRYPTER_WIDTH-1:0] encrypter_data_packet_out,
    output reg [`ENCRYPTER_QSPI_COUNT_REG-1:0] encrypter_data_index_out,
    output reg [`NUM_ENCRYPTERS_REG-1:0] encrypter_index_out
);

reg [2:0] state = `STATE_IDLE;
reg [`KEY_WIDTH-1:0] key;
reg [`KEY_QSPI_COUNT_REG-1:0] key_index;
reg [`KEY_ROTATION_WIDTH-1:0] key_rotation;
reg [`KEY_ROTATION_WIDTH_COUNT_REG-1:0] key_rotation_index;

reg [`KEY_ENCRYPTER_COUNT_REG-1:0] key_encrypter_index;

reg [`ENCRYPTER_WIDTH-1:0] encrypter_data_packet;
reg [`ENCRYPTER_WIDTH_COUNT_REG-1:0] encrypter_data_subindex;

reg [`ENCRYPTER_QSPI_COUNT_REG-1:0] encrypter_data_index;
reg [`NUM_ENCRYPTERS_REG-1:0] encrypter_index;
integer i;

initial begin
    assign state_out = state;
    assign key_out = key;
    assign key_rotation_out = key_rotation;
    assign key_index_out = key_index;
    assign encrypter_data_packet_out = encrypter_data_packet;
    assign encrypter_data_index_out = encrypter_data_index;
    assign encrypter_index_out = encrypter_index;

    qspi_ready = 1'b0;
    encrypters_program = 0;
    key = 0;
    key_index = 0;
end

always @(posedge reset) begin
    state <= `STATE_IDLE;
    qspi_ready = 1'b1;
end

always @(posedge prog) begin
    if (state == `STATE_IDLE) begin
        state <= `STATE_PROGRAMMING;
        qspi_ready = 1'b1;
        key_index = 0;
    end
end

always @(posedge qspi_sending) begin
    case (state)

        `STATE_IDLE: begin
            state <= `STATE_ENCRYPTING;
            encrypter_index = 0;
            encrypter_data_index = 0;
            encrypters_data_ready = 0;
            key_rotation = 0;
        end

        `STATE_PROGRAMMING: state <= `STATE_RECEIVING_KEY;

        default:;

    endcase
end

always @(negedge qspi_sending) begin
    case (state)
        `STATE_ENCRYPTING: state = `STATE_IDLE;
        `STATE_RECEIVING_KEY: state = `STATE_IDLE;
        default:;
    endcase
end

//read on positive
always @(posedge clk) begin
    case (state)

        `STATE_RECEIVING_KEY: begin 
            key[key_index*4] = qspi_data[0];
            key[key_index*4+1] = qspi_data[1];
            key[key_index*4+2] = qspi_data[2];
            key[key_index*4+3] = qspi_data[3];
            key_index = key_index + 1;
            if (key_index == `KEY_QSPI_COUNT) begin
                state = `STATE_PROGRAMMING_ENCRYPTERS;
                key_encrypter_index = 0;
                qspi_ready = 1'b0;
            end
        end

        `STATE_WAITING_FOR_READY_ENCRYPTERS: begin
            state = `STATE_IDLE;
            for (encrypter_index = 0; encrypter_index < `NUM_ENCRYPTERS; encrypter_index++) begin
                if (~encrypters_ready[encrypter_index]) begin
                    state = `STATE_WAITING_FOR_READY_ENCRYPTERS;
                end
            end
            if (state == `STATE_IDLE) begin
                qspi_ready = 1'b1;
                encrypters_program = 0;
            end
        end

        `STATE_ENCRYPTING: begin
            //read spi data
            encrypter_data_packet[encrypter_data_index*4] = qspi_data[0];
            encrypter_data_packet[encrypter_data_index*4+1] = qspi_data[1];
            encrypter_data_packet[encrypter_data_index*4+2] = qspi_data[2];
            encrypter_data_packet[encrypter_data_index*4+3] = qspi_data[3];
            encrypter_data_index = encrypter_data_index + 1;
        end

        default:;

    endcase
end

//write on negative
always @(negedge clk) begin
    case (state)

        `STATE_PROGRAMMING_ENCRYPTERS: begin
            for (encrypter_index = 0; encrypter_index < `NUM_ENCRYPTERS; encrypter_index = encrypter_index + 1) begin
                for (encrypter_data_subindex = 0; encrypter_data_subindex < `ENCRYPTER_WIDTH; encrypter_data_subindex = encrypter_data_subindex + 1) begin
                    encrypters_data[encrypter_index][encrypter_data_subindex] = key[key_encrypter_index * `ENCRYPTER_WIDTH + encrypter_data_subindex];
                end
                encrypters_program[encrypter_index] = 1'b1;
            end

            key_encrypter_index = key_encrypter_index + 1;
            if (key_encrypter_index == `KEY_ENCRYPTER_COUNT) state = `STATE_WAITING_FOR_READY_ENCRYPTERS;
        end

        `STATE_ENCRYPTING: begin
            //keep ecrypter data index high for only 1 posedge clock cycle
            if (encrypter_index == 0) begin
                if (encrypters_data_ready[`NUM_ENCRYPTERS-1]) encrypters_data_ready[`NUM_ENCRYPTERS-1] = 0;
            end else begin
                if (encrypters_data_ready[encrypter_index-1]) encrypters_data_ready[encrypter_index-1] = 0;
            end

            if (encrypter_data_index == `ENCRYPTER_QSPI_COUNT) begin
                //when packet full, send to encrypters
                encrypter_data_index = 0;
                
                //check if encrypter is ready for new data
                if (encrypters_ready[encrypter_index]) begin
                    //put packet on encrypter bus
                    for (encrypter_data_subindex = 0; encrypter_data_subindex < `ENCRYPTER_WIDTH; encrypter_data_subindex = encrypter_data_subindex + 1) begin
                        encrypters_data[encrypter_index][encrypter_data_subindex] = encrypter_data_packet[encrypter_data_subindex];
                    end
                    //put key rot on encrypter bus
                    for (key_rotation_index = 0; key_rotation_index < `KEY_ROTATION_WIDTH; key_rotation_index = key_rotation_index + 1) begin
                        encrypters_key_rotation[encrypter_index][key_rotation_index] = key_rotation[key_rotation_index];
                    end

                    //signal data is ready
                    encrypters_data_ready[encrypter_index] = 1'b1;

                    //move to next encrypter
                    encrypter_index = encrypter_index + 1;
                    if (encrypter_index == `NUM_ENCRYPTERS) encrypter_index = 0;

                    //move to next key rotation
                    key_rotation = key_rotation + 1;
                    if (key_rotation == `KEY_WIDTH) key_rotation = 0;

                    //ready for more data as current data has been written
                    qspi_ready = 1'b1;
                end else begin
                    //if encrypter is not ready, wait for it
                    qspi_ready = 1'b0;
                end
            end
        end

        default:;

    endcase
end

endmodule

Icarus-Verliog-testing/Paralellizer/paralellizer_tb.sv
`timescale 1ns / 1ns
`include "./Constants/constants.vh"
`include "./Paralellizer/paralellizer.sv"

module Paralellizer_tb;

    reg clk; 
    reg reset;
    //QSPI
    reg [3:0] qspi_data;
    reg qspi_sending;
    wire qspi_ready;
    //Program
    reg prog;
    //To encrypters
    wire[`ENCRYPTER_WIDTH-1:0] encrypters_data [`NUM_ENCRYPTERS-1:0];
    wire [`KEY_ROTATION_WIDTH-1:0] encrypters_key_rotation [`NUM_ENCRYPTERS-1];
    wire [`NUM_ENCRYPTERS-1:0] encrypters_program;
    wire [`NUM_ENCRYPTERS-1:0] encrypters_data_ready;
    reg [`NUM_ENCRYPTERS-1:0] encrypters_ready;
    //Watchers
    wire [2:0] state_out;
    wire [`KEY_WIDTH-1:0] key_out;
    wire [`KEY_ROTATION_WIDTH-1:0] key_rotation_out;
    wire [`KEY_QSPI_COUNT_REG-1:0] key_index_out;
    wire [`KEY_ENCRYPTER_COUNT_REG-1:0] key_encrypter_index_out;
    wire [`ENCRYPTER_WIDTH-1:0] encrypter_data_packet_out;
    wire [`ENCRYPTER_QSPI_COUNT_REG-1:0] encrypter_data_index_out;
    wire [`NUM_ENCRYPTERS_REG-1:0] encrypter_index_out;
    reg [`ENCRYPTER_WIDTH-1:0] encrypters_data_slice;

    Paralellizer uut(
        .clk(clk),
        .reset(reset),
        .qspi_data(qspi_data),
        .qspi_sending(qspi_sending),
        .qspi_ready(qspi_ready),
        .prog(prog),
        .encrypters_data(encrypters_data),
        .encrypters_key_rotation(encrypters_key_rotation),
        .encrypters_program(encrypters_program),
        .encrypters_data_ready(encrypters_data_ready),
        .encrypters_ready(encrypters_ready),
        .state_out(state_out),
        .key_out(key_out),
        .key_rotation_out(key_rotation_out),
        .key_index_out(key_index_out),
        .key_encrypter_index_out(key_encrypter_index_out),
        .encrypter_data_packet_out(encrypter_data_packet_out),
        .encrypter_data_index_out(encrypter_data_index_out),
        .encrypter_index_out(encrypter_index_out)
    );
    
    reg [3:0] spi_data_values[256:0];
    reg [3:0] encrypters_delays [`NUM_ENCRYPTERS-1:0];
    integer fd, i, j;

    initial begin
        //fill spi_data_values with data from file
        fd = $fopen("./Constants/qspi_data.csv", "r");
        if (fd == -1) begin
            $display("Error opening file!");
            $finish;  // Exit simulation on error
        end
        for (i = 0; i < 256; i++) begin
            j = $fscanf(fd, "%h", spi_data_values[i]);
        end
        $fclose(fd);
        $display(spi_data_values[0]);

        for (j = 0; j < `NUM_ENCRYPTERS-1; j = j + 1) begin
            encrypters_delays[j] = 0;
        end
    end

    initial begin
        $dumpfile("Paralellizer/paralellizer_tb.vcd");
        $dumpvars(0, Paralellizer_tb);
        $display("Starting paralellizer testbench");
        clk = 0;
        reset = 0;
        qspi_data = 0;
        qspi_sending = 0;
        prog = 0;
        encrypters_ready = 0;


        //expected use
        //set data on neg edge, read on the rising
        #2 reset = 1; #2 reset = 0;
        #2 prog = 1; #2 prog = 0;
        //send key
        #2 qspi_sending = 1;
        for (i = 0; i < `KEY_QSPI_COUNT; i = i + 1) begin
            qspi_data = spi_data_values[i];
            $display("Setting qspi_data to 0x%h", spi_data_values[i]);
            #2;
        end
        qspi_sending = 0;

        #10;
        //simulate encrypters receiving key after paralellizer send it out
        for (i = 0; i < `NUM_ENCRYPTERS; i = i + 1) begin
            encrypters_ready[i] = 1;
            #1;
        end

        //start encrypting data. can only be started from idle state
        #4 qspi_sending = 1;
        for (i = `KEY_QSPI_COUNT; i < 200; i = i + 1) begin
            qspi_data = spi_data_values[i];
            $display("Setting qspi_data to 0x%h", spi_data_values[i]);
            #2;
        end
        #2 qspi_sending = 0;
        #10
        $display("Ending paralellizer testbench");
        $finish;
    end

    always begin
        #1 clk = ~clk;
        //update slice of encrypters data to be seen on gktwave
        encrypters_data_slice[`ENCRYPTER_WIDTH-1:0] = encrypters_data[0][`ENCRYPTER_WIDTH-1:0];
        if (clk)
            for (j = 0; j < `NUM_ENCRYPTERS-1; j = j + 1) begin
                if (encrypters_ready[j] && encrypters_data_ready[j]) begin
                    encrypters_ready[j] = 0;
                end
                if (encrypters_data_ready[j]) encrypters_delays[j] = 4;
                if (encrypters_delays[j]) begin
                    if (encrypters_delays[j] == 1) encrypters_ready[j] = 1;
                    encrypters_delays[j] = encrypters_delays[j] - 1;
                end
            end
    end

endmodule

Icarus-Verliog-testing/Paralellizer/paralellizer_tb.vcd
$date
	Tue May  7 10:24:50 2024
$end
$version
	Icarus Verilog
$end
$timescale
	1ns
$end
$scope module Paralellizer_tb $end
$var wire 3 ! state_out [2:0] $end
$var wire 1 " qspi_ready $end
$var wire 4 # key_rotation_out [3:0] $end
$var wire 16 $ key_out [15:0] $end
$var wire 3 % key_index_out [2:0] $end
$var wire 1 & key_encrypter_index_out $end
$var wire 4 ' encrypters_program [3:0] $end
$var wire 4 ( encrypters_data_ready [3:0] $end
$var wire 3 ) encrypter_index_out [2:0] $end
$var wire 16 * encrypter_data_packet_out [15:0] $end
$var wire 3 + encrypter_data_index_out [2:0] $end
$var reg 1 , clk $end
$var reg 16 - encrypters_data_slice [15:0] $end
$var reg 4 . encrypters_ready [3:0] $end
$var reg 1 / prog $end
$var reg 4 0 qspi_data [3:0] $end
$var reg 1 1 qspi_sending $end
$var reg 1 2 reset $end
$var integer 32 3 fd [31:0] $end
$var integer 32 4 i [31:0] $end
$var integer 32 5 j [31:0] $end
$scope module uut $end
$var wire 1 , clk $end
$var wire 4 6 encrypters_ready [3:0] $end
$var wire 1 / prog $end
$var wire 4 7 qspi_data [3:0] $end
$var wire 1 1 qspi_sending $end
$var wire 1 2 reset $end
$var reg 3 8 encrypter_data_index [2:0] $end
$var reg 3 9 encrypter_data_index_out [2:0] $end
$var reg 16 : encrypter_data_packet [15:0] $end
$var reg 16 ; encrypter_data_packet_out [15:0] $end
$var reg 5 < encrypter_data_subindex [4:0] $end
$var reg 3 = encrypter_index [2:0] $end
$var reg 3 > encrypter_index_out [2:0] $end
$var reg 4 ? encrypters_data_ready [3:0] $end
$var reg 4 @ encrypters_program [3:0] $end
$var reg 16 A key [15:0] $end
$var reg 1 B key_encrypter_index $end
$var reg 1 & key_encrypter_index_out $end
$var reg 3 C key_index [2:0] $end
$var reg 3 D key_index_out [2:0] $end
$var reg 16 E key_out [15:0] $end
$var reg 4 F key_rotation [3:0] $end
$var reg 3 G key_rotation_index [2:0] $end
$var reg 4 H key_rotation_out [3:0] $end
$var reg 1 " qspi_ready $end
$var reg 3 I state [2:0] $end
$var reg 3 J state_out [2:0] $end
$upscope $end
$upscope $end
$enddefinitions $end
$comment Show the parameter values. $end
$dumpall
$end
#0
$dumpvars
b0 J
b0 I
bx H
bx G
bx F
b0 E
b0 D
b0 C
xB
b0 A
b0 @
bx ?
bx >
bx =
bx <
bx ;
bx :
bx 9
bx 8
b0 7
b0 6
b11 5
b100000000 4
b10000000000000000000000000000011 3
02
01
b0 0
0/
b0 .
bx -
0,
bx +
bx *
bx )
bx (
b0 '
x&
b0 %
b0 $
bx #
0"
b0 !
$end
#1
b11 5
1,
#2
1"
0,
12
#3
b11 5
1,
#4
0,
02
#5
b11 5
1,
#6
b1 !
b1 J
b1 I
0,
1/
#7
b11 5
1,
#8
0,
0/
#9
b11 5
1,
#10
b10 !
b10 J
b10 I
0,
b1101 0
b1101 7
b0 4
11
#11
b1 %
b1 D
b1 C
b1101 $
b1101 E
b1101 A
b11 5
1,
#12
0,
b1 0
b1 7
b1 4
#13
b10 %
b10 D
b10 C
b11101 $
b11101 E
b11101 A
b11 5
1,
#14
0,
b1010 0
b1010 7
b10 4
#15
b11 %
b11 D
b11 C
b101000011101 $
b101000011101 E
b101000011101 A
b11 5
1,
#16
0,
b11 4
#17
0"
0B
b11 !
b11 J
b11 I
b100 %
b100 D
b100 C
b1010101000011101 $
b1010101000011101 E
b1010101000011101 A
b11 5
1,
#18
b100 !
b100 J
b100 I
1B
b1111 '
b1111 @
b10000 <
b100 )
b100 >
b100 =
0,
01
b100 4
#19
b100 )
b100 >
b100 =
b100 !
b100 J
b100 I
b11 5
b1010101000011101 -
1,
#20
0,
#21
b100 )
b100 >
b100 =
b100 !
b100 J
b100 I
b11 5
1,
#22
0,
#23
b100 )
b100 >
b100 =
b100 !
b100 J
b100 I
b11 5
1,
#24
0,
#25
b100 )
b100 >
b100 =
b100 !
b100 J
b100 I
b11 5
1,
#26
0,
#27
b100 )
b100 >
b100 =
b100 !
b100 J
b100 I
b11 5
1,
#28
0,
b1 .
b1 6
b0 4
#29
b100 )
b100 >
b100 =
b100 !
b100 J
b100 I
b11 5
1,
b11 .
b11 6
b1 4
#30
0,
b111 .
b111 6
b10 4
#31
b0 '
b0 @
1"
b100 )
b100 >
b100 =
b0 !
b0 J
b0 I
b11 5
1,
b1111 .
b1111 6
b11 4
#32
0,
b100 4
#33
b11 5
1,
#34
0,
#35
b11 5
1,
#36
b101 !
b101 J
b101 I
b0 #
b0 H
b0 F
b0 (
b0 ?
b0 +
b0 9
b0 8
b0 )
b0 >
b0 =
0,
b11 0
b11 7
11
#37
b1 +
b1 9
b1 8
bx0011 *
bx0011 ;
bx0011 :
b11 5
1,
#38
0,
b10 0
b10 7
b101 4
#39
b10 +
b10 9
b10 8
bx00100011 *
bx00100011 ;
bx00100011 :
b11 5
1,
#40
0,
b1011 0
b1011 7
b110 4
#41
b11 +
b11 9
b11 8
bx101100100011 *
bx101100100011 ;
bx101100100011 :
b11 5
1,
#42
0,
b1 0
b1 7
b111 4
#43
b100 +
b100 9
b100 8
b1101100100011 *
b1101100100011 ;
b1101100100011 :
b11 5
1,
#44
b1 #
b1 H
b1 F
b1 )
b1 >
b1 =
b1 (
b1 ?
b100 G
b10000 <
b0 +
b0 9
b0 8
0,
b1100 0
b1100 7
b1000 4
#45
b1 +
b1 9
b1 8
b1101100101100 *
b1101100101100 ;
b1101100101100 :
b1110 .
b1110 6
b11 5
b1101100100011 -
1,
#46
b0 (
b0 ?
0,
b1000 0
b1000 7
b1001 4
#47
b10 +
b10 9
b10 8
b1101110001100 *
b1101110001100 ;
b1101110001100 :
b11 5
1,
#48
0,
b111 0
b111 7
b1010 4
#49
b11 +
b11 9
b11 8
b1011110001100 *
b1011110001100 ;
b1011110001100 :
b11 5
1,
#50
0,
b1101 0
b1101 7
b1011 4
#51
b100 +
b100 9
b100 8
b1101011110001100 *
b1101011110001100 ;
b1101011110001100 :
b1111 .
b1111 6
b11 5
1,
#52
b10 #
b10 H
b10 F
b10 )
b10 >
b10 =
b10 (
b10 ?
b100 G
b10000 <
b0 +
b0 9
b0 8
0,
b1001 0
b1001 7
b1100 4
#53
b1 +
b1 9
b1 8
b1101011110001001 *
b1101011110001001 ;
b1101011110001001 :
b1101 .
b1101 6
b11 5
1,
#54
b0 (
b0 ?
0,
b110 0
b110 7
b1101 4
#55
b10 +
b10 9
b10 8
b1101011101101001 *
b1101011101101001 ;
b1101011101101001 :
b11 5
1,
#56
0,
b1001 0
b1001 7
b1110 4
#57
b11 +
b11 9
b11 8
b1101100101101001 *
b1101100101101001 ;
b1101100101101001 :
b11 5
1,
#58
0,
b10 0
b10 7
b1111 4
#59
b100 +
b100 9
b100 8
b10100101101001 *
b10100101101001 ;
b10100101101001 :
b1111 .
b1111 6
b11 5
1,
#60
b11 #
b11 H
b11 F
b11 )
b11 >
b11 =
b100 (
b100 ?
b100 G
b10000 <
b0 +
b0 9
b0 8
0,
b111 0
b111 7
b10000 4
#61
b1 +
b1 9
b1 8
b10100101100111 *
b10100101100111 ;
b10100101100111 :
b1011 .
b1011 6
b11 5
1,
#62
b0 (
b0 ?
0,
b1011 0
b1011 7
b10001 4
#63
b10 +
b10 9
b10 8
b10100110110111 *
b10100110110111 ;
b10100110110111 :
b11 5
1,
#64
0,
b0 0
b0 7
b10010 4
#65
b11 +
b11 9
b11 8
b10000010110111 *
b10000010110111 ;
b10000010110111 :
b11 5
1,
#66
0,
b110 0
b110 7
b10011 4
#67
b100 +
b100 9
b100 8
b110000010110111 *
b110000010110111 ;
b110000010110111 :
b1111 .
b1111 6
b11 5
1,
#68
b100 #
b100 H
b100 F
b0 )
b0 >
b0 =
b1000 (
b1000 ?
b100 G
b10000 <
b0 +
b0 9
b0 8
0,
b11 0
b11 7
b10100 4
#69
b1 +
b1 9
b1 8
b110000010110011 *
b110000010110011 ;
b110000010110011 :
b11 5
1,
#70
b0 (
b0 ?
0,
b111 0
b111 7
b10101 4
#71
b10 +
b10 9
b10 8
b110000001110011 *
b110000001110011 ;
b110000001110011 :
b11 5
1,
#72
0,
b101 0
b101 7
b10110 4
#73
b11 +
b11 9
b11 8
b110010101110011 *
b110010101110011 ;
b110010101110011 :
b11 5
1,
#74
0,
b1010 0
b1010 7
b10111 4
#75
b100 +
b100 9
b100 8
b1010010101110011 *
b1010010101110011 ;
b1010010101110011 :
b11 5
1,
#76
b101 #
b101 H
b101 F
b1 )
b1 >
b1 =
b1 (
b1 ?
b100 G
b10000 <
b0 +
b0 9
b0 8
0,
b100 0
b100 7
b11000 4
#77
b1 +
b1 9
b1 8
b1010010101110100 *
b1010010101110100 ;
b1010010101110100 :
b1110 .
b1110 6
b11 5
b1010010101110011 -
1,
#78
b0 (
b0 ?
0,
b10 0
b10 7
b11001 4
#79
b10 +
b10 9
b10 8
b1010010100100100 *
b1010010100100100 ;
b1010010100100100 :
b11 5
1,
#80
0,
b100 0
b100 7
b11010 4
#81
b11 +
b11 9
b11 8
b1010010000100100 *
b1010010000100100 ;
b1010010000100100 :
b11 5
1,
#82
0,
b110 0
b110 7
b11011 4
#83
b100 +
b100 9
b100 8
b110010000100100 *
b110010000100100 ;
b110010000100100 :
b1111 .
b1111 6
b11 5
1,
#84
b110 #
b110 H
b110 F
b10 )
b10 >
b10 =
b10 (
b10 ?
b100 G
b10000 <
b0 +
b0 9
b0 8
0,
b0 0
b0 7
b11100 4
#85
b1 +
b1 9
b1 8
b110010000100000 *
b110010000100000 ;
b110010000100000 :
b1101 .
b1101 6
b11 5
1,
#86
b0 (
b0 ?
0,
b1110 0
b1110 7
b11101 4
#87
b10 +
b10 9
b10 8
b110010011100000 *
b110010011100000 ;
b110010011100000 :
b11 5
1,
#88
0,
b0 0
b0 7
b11110 4
#89
b11 +
b11 9
b11 8
b110000011100000 *
b110000011100000 ;
b110000011100000 :
b11 5
1,
#90
0,
b1110 0
b1110 7
b11111 4
#91
b100 +
b100 9
b100 8
b1110000011100000 *
b1110000011100000 ;
b1110000011100000 :
b1111 .
b1111 6
b11 5
1,
#92
b111 #
b111 H
b111 F
b11 )
b11 >
b11 =
b100 (
b100 ?
b100 G
b10000 <
b0 +
b0 9
b0 8
0,
b0 0
b0 7
b100000 4
#93
b1 +
b1 9
b1 8
b1011 .
b1011 6
b11 5
1,
#94
b0 (
b0 ?
0,
b1111 0
b1111 7
b100001 4
#95
b10 +
b10 9
b10 8
b1110000011110000 *
b1110000011110000 ;
b1110000011110000 :
b11 5
1,
#96
0,
b101 0
b101 7
b100010 4
#97
b11 +
b11 9
b11 8
b1110010111110000 *
b1110010111110000 ;
b1110010111110000 :
b11 5
1,
#98
0,
b0 0
b0 7
b100011 4
#99
b100 +
b100 9
b100 8
b10111110000 *
b10111110000 ;
b10111110000 :
b1111 .
b1111 6
b11 5
1,
#100
b1000 #
b1000 H
b1000 F
b0 )
b0 >
b0 =
b1000 (
b1000 ?
b100 G
b10000 <
b0 +
b0 9
b0 8
0,
b101 0
b101 7
b100100 4
#101
b1 +
b1 9
b1 8
b10111110101 *
b10111110101 ;
b10111110101 :
b11 5
1,
#102
b0 (
b0 ?
0,
b111 0
b111 7
b100101 4
#103
b10 +
b10 9
b10 8
b10101110101 *
b10101110101 ;
b10101110101 :
b11 5
1,
#104
0,
b1111 0
b1111 7
b100110 4
#105
b11 +
b11 9
b11 8
b111101110101 *
b111101110101 ;
b111101110101 :
b11 5
1,
#106
0,
b11 0
b11 7
b100111 4
#107
b100 +
b100 9
b100 8
b11111101110101 *
b11111101110101 ;
b11111101110101 :
b11 5
1,
#108
b1001 #
b1001 H
b1001 F
b1 )
b1 >
b1 =
b1 (
b1 ?
b100 G
b10000 <
b0 +
b0 9
b0 8
0,
b1101 0
b1101 7
b101000 4
#109
b1 +
b1 9
b1 8
b11111101111101 *
b11111101111101 ;
b11111101111101 :
b1110 .
b1110 6
b11 5
b11111101110101 -
1,
#110
b0 (
b0 ?
0,
b110 0
b110 7
b101001 4
#111
b10 +
b10 9
b10 8
b11111101101101 *
b11111101101101 ;
b11111101101101 :
b11 5
1,
#112
0,
b101 0
b101 7
b101010 4
#113
b11 +
b11 9
b11 8
b11010101101101 *
b11010101101101 ;
b11010101101101 :
b11 5
1,
#114
0,
b1011 0
b1011 7
b101011 4
#115
b100 +
b100 9
b100 8
b1011010101101101 *
b1011010101101101 ;
b1011010101101101 :
b1111 .
b1111 6
b11 5
1,
#116
b1010 #
b1010 H
b1010 F
b10 )
b10 >
b10 =
b10 (
b10 ?
b100 G
b10000 <
b0 +
b0 9
b0 8
0,
b101 0
b101 7
b101100 4
#117
b1 +
b1 9
b1 8
b1011010101100101 *
b1011010101100101 ;
b1011010101100101 :
b1101 .
b1101 6
b11 5
1,
#118
b0 (
b0 ?
0,
b1111 0
b1111 7
b101101 4
#119
b10 +
b10 9
b10 8
b1011010111110101 *
b1011010111110101 ;
b1011010111110101 :
b11 5
1,
#120
0,
b1101 0
b1101 7
b101110 4
#121
b11 +
b11 9
b11 8
b1011110111110101 *
b1011110111110101 ;
b1011110111110101 :
b11 5
1,
#122
0,
b1111 0
b1111 7
b101111 4
#123
b100 +
b100 9
b100 8
b1111110111110101 *
b1111110111110101 ;
b1111110111110101 :
b1111 .
b1111 6
b11 5
1,
#124
b1011 #
b1011 H
b1011 F
b11 )
b11 >
b11 =
b100 (
b100 ?
b100 G
b10000 <
b0 +
b0 9
b0 8
0,
b1010 0
b1010 7
b110000 4
#125
b1 +
b1 9
b1 8
b1111110111111010 *
b1111110111111010 ;
b1111110111111010 :
b1011 .
b1011 6
b11 5
1,
#126
b0 (
b0 ?
0,
b1 0
b1 7
b110001 4
#127
b10 +
b10 9
b10 8
b1111110100011010 *
b1111110100011010 ;
b1111110100011010 :
b11 5
1,
#128
0,
b10 0
b10 7
b110010 4
#129
b11 +
b11 9
b11 8
b1111001000011010 *
b1111001000011010 ;
b1111001000011010 :
b11 5
1,
#130
0,
b1011 0
b1011 7
b110011 4
#131
b100 +
b100 9
b100 8
b1011001000011010 *
b1011001000011010 ;
b1011001000011010 :
b1111 .
b1111 6
b11 5
1,
#132
b1100 #
b1100 H
b1100 F
b0 )
b0 >
b0 =
b1000 (
b1000 ?
b100 G
b10000 <
b0 +
b0 9
b0 8
0,
b1 0
b1 7
b110100 4
#133
b1 +
b1 9
b1 8
b1011001000010001 *
b1011001000010001 ;
b1011001000010001 :
b11 5
1,
#134
b0 (
b0 ?
0,
b1101 0
b1101 7
b110101 4
#135
b10 +
b10 9
b10 8
b1011001011010001 *
b1011001011010001 ;
b1011001011010001 :
b11 5
1,
#136
0,
b0 0
b0 7
b110110 4
#137
b11 +
b11 9
b11 8
b1011000011010001 *
b1011000011010001 ;
b1011000011010001 :
b11 5
1,
#138
0,
b10 0
b10 7
b110111 4
#139
b100 +
b100 9
b100 8
b10000011010001 *
b10000011010001 ;
b10000011010001 :
b11 5
1,
#140
b1101 #
b1101 H
b1101 F
b1 )
b1 >
b1 =
b1 (
b1 ?
b100 G
b10000 <
b0 +
b0 9
b0 8
0,
b11 0
b11 7
b111000 4
#141
b1 +
b1 9
b1 8
b10000011010011 *
b10000011010011 ;
b10000011010011 :
b1110 .
b1110 6
b11 5
b10000011010001 -
1,
#142
b0 (
b0 ?
0,
b100 0
b100 7
b111001 4
#143
b10 +
b10 9
b10 8
b10000001000011 *
b10000001000011 ;
b10000001000011 :
b11 5
1,
#144
0,
b111010 4
#145
b11 +
b11 9
b11 8
b10010001000011 *
b10010001000011 ;
b10010001000011 :
b11 5
1,
#146
0,
b1 0
b1 7
b111011 4
#147
b100 +
b100 9
b100 8
b1010001000011 *
b1010001000011 ;
b1010001000011 :
b1111 .
b1111 6
b11 5
1,
#148
b1110 #
b1110 H
b1110 F
b10 )
b10 >
b10 =
b10 (
b10 ?
b100 G
b10000 <
b0 +
b0 9
b0 8
0,
b1001 0
b1001 7
b111100 4
#149
b1 +
b1 9
b1 8
b1010001001001 *
b1010001001001 ;
b1010001001001 :
b1101 .
b1101 6
b11 5
1,
#150
b0 (
b0 ?
0,
b111101 4
#151
b10 +
b10 9
b10 8
b1010010011001 *
b1010010011001 ;
b1010010011001 :
b11 5
1,
#152
0,
b1 0
b1 7
b111110 4
#153
b11 +
b11 9
b11 8
b1000110011001 *
b1000110011001 ;
b1000110011001 :
b11 5
1,
#154
0,
b1001 0
b1001 7
b111111 4
