Icarus-Verliog-testing/Constants/constants.vh
//DEFINE CONSTANTS
// `define KEY_WIDTH 16 // width of the key. In multiples of 4.
// `define KEY_QSPI_COUNT `KEY_WIDTH/4 // number of QSPI transactions per key sent in LSB. 
// `define KEY_QSPI_COUNT_REG $clog2(`KEY_QSPI_COUNT+1) // register size required to count the current QSPI transaction of the key + 1. log2(`KEY_QSPI_COUNT+1)

`define ENCRYPTER_WIDTH 32 // width of the bus between the Paralellizer and Encrypter, and the Encrypter and Collector. In multiples of 4.
`define ENCRYPTER_WIDTH_COUNT_REG $clog2(`ENCRYPTER_WIDTH+1) // register size required to count the current bit of the encrypter bus + 1. log2(`ENCRYPTER_WIDTH+1). (Verilog doesn't like me so i need a for loop)
`define ENCRYPTER_QSPI_COUNT `ENCRYPTER_WIDTH/4 // number of QSPI transactions per Encrypter.
`define ENCRYPTER_QSPI_COUNT_REG $clog2(`ENCRYPTER_QSPI_COUNT+1) // register size required to count the current QSPI transaction of the Encrypter + 1. log2(`ENCRYPTER_QSPI_COUNT+1)

`define KEY_ROTATION_WIDTH $clog2(`ENCRYPTER_WIDTH) // width of the key rotation bus between Paralellizer and Encrypter. log2(`KEY_WIDTH)
`define KEY_ROTATION_WIDTH_COUNT_REG $clog2(`KEY_ROTATION_WIDTH+1) // register size required to count the current bit of the key rotation bus + 1. log2(`KEY_ROTATION_WIDTH+1). (Verilog doesn't like me so i need a for loop)

// `define KEY_ENCRYPTER_COUNT `KEY_WIDTH/`ENCRYPTER_WIDTH // number of Encrypters transactions per key. `KEY_WIDTH/`ENCRYPTER_WIDTH
// `define KEY_ENCRYPTER_COUNT_REG $clog2(`KEY_ENCRYPTER_COUNT+1) // register size required to count the current Encrypter transaction of the key + 1. log2(`KEY_ENCRYPTER_COUNT+1)

`define NUM_ENCRYPTERS 2 // number of Encrypters
`define NUM_ENCRYPTERS_REG $clog2(`NUM_ENCRYPTERS+1) // register size required to count the current Encrypter + 1. log2(`NUM_ENCRYPTERS+1)

Icarus-Verliog-testing/Collector/collector.sv
`include "./Constants/constants.vh"
`define IDLE 2'b00
`define WAITING 2'b01
`define CAPTURING 2'b10
`define SENDING 2'b11


module Collector(
    input wire clk,
    input wire reset,
    //QSPI
    
    output reg [3:0] qspi_data,
    output reg qspi_sending = 0,
    input wire qspi_ready,
    
    //To encrypters
    input wire [`ENCRYPTER_WIDTH-1:0] encrypters_data [`NUM_ENCRYPTERS-1:0],
    input wire [`NUM_ENCRYPTERS-1:0] encrypters_data_ready,
    output reg [`NUM_ENCRYPTERS-1:0] encrypters_capture

    //Watchers
    // output reg [1:0] state_out,
    // output reg [`ENCRYPTER_WIDTH-1:0] encrypter_data_packe_out,
    
    // output reg [`ENCRYPTER_WIDTH_COUNT_REG-1:0] encrypter_data_subindex_out,
    // output reg [`NUM_ENCRYPTERS_REG-1:0] encrypter_index_out,
    // output reg [`ENCRYPTER_QSPI_COUNT_REG-1:0] encrypter_data_index_out    
);

    reg [1:0] state = `IDLE;

    reg [`ENCRYPTER_WIDTH-1:0] encrypter_data_packet;
    reg [`ENCRYPTER_WIDTH_COUNT_REG-1:0] encrypter_data_subindex;

    reg [`NUM_ENCRYPTERS_REG-1:0] encrypter_index;

    reg [`ENCRYPTER_QSPI_COUNT_REG-1:0] encrypter_data_index;

    initial begin
        encrypters_capture = 0;
        // assign state_out = state;
        // assign encrypter_data_packe_out = encrypter_data_packet;
        // assign encrypter_data_subindex_out = encrypter_data_subindex;
        // assign encrypter_index_out = encrypter_index;
        // assign encrypter_data_index_out = encrypter_data_index;
    end

    always @(posedge clk) begin

        if (reset) begin
            state <= `WAITING;
            encrypter_index <= 0;
        end

        if (state == `WAITING) begin
            if(encrypters_data_ready[encrypter_index]) begin
                encrypter_data_packet = encrypters_data[encrypter_index];
                state <= `CAPTURING;
                encrypter_data_index = 0;
            end else begin
                qspi_sending = 0;
            end
        end

    end

    always @(negedge clk) begin
        encrypters_capture <= 0;

        if (state == `CAPTURING) begin
            encrypters_capture[encrypter_index] <= 1;
            state = `SENDING;
        end

        if (state == `SENDING) begin
            if(qspi_ready) begin
                qspi_sending = 1;
                qspi_data[0] = encrypter_data_packet[encrypter_data_index*4];
                qspi_data[1] = encrypter_data_packet[encrypter_data_index*4+1]; 
                qspi_data[2] = encrypter_data_packet[encrypter_data_index*4+2];
                qspi_data[3] = encrypter_data_packet[encrypter_data_index*4+3];  
                encrypter_data_index = encrypter_data_index + 1;   
                if(encrypter_data_index == `ENCRYPTER_QSPI_COUNT) begin
                        encrypter_index = encrypter_index + 1;
                        if (encrypter_index == `NUM_ENCRYPTERS) begin
                            encrypter_index = 0;
                        end
                    state <= `WAITING; 
                end           
            end else qspi_sending = 0;   
        end     
    end 


endmodule

Icarus-Verliog-testing/Encrypter/encrypter.sv
`include "./Constants/constants.vh"

`define IDLE 3'b000
`define READING_KEY 3'b001
`define WAITING_RDY_DATA_IN 3'b010
`define READING_DATA_ENCRYPTING 3'b011
`define SENDING_DATA 3'b100
`define ACKNOWLEDGING_CAPTURE 3'b101

module Encrypter (
    input wire clk,
    input wire reset,

    // Parallelizer <-> Encrypter signals
    input wire [`ENCRYPTER_WIDTH-1:0] data_in_p,
    input wire [`KEY_ROTATION_WIDTH-1:0] key_rotation_p,
    input wire prog_p,
    input wire data_ready_in_p,
    output reg ready_p,

    // Encrypter <-> Collector signals
    output reg [`ENCRYPTER_WIDTH-1:0] data_out_c,
    output reg data_ready_out_c,
    input wire capture_c
);

    reg [2:0] state;
    reg [`ENCRYPTER_WIDTH-1:0] keyRotated;
    reg [`ENCRYPTER_WIDTH-1:0] data_in_store;
    reg [`ENCRYPTER_WIDTH-1:0] keyOrigin;
    reg [`KEY_ROTATION_WIDTH:0] offset;

    initial begin
        state <= `IDLE;
        ready_p = 0;
        data_ready_out_c = 0;
        data_out_c = 0;
        data_in_store = 0;
        keyOrigin = 0;
        keyRotated = 0;
        offset = 0;
    end

    always @(posedge clk) begin
        if (reset) begin
            state <= `IDLE;
            ready_p = 0;
            data_ready_out_c = 0;
            data_out_c = 0;
            data_in_store = 0;
            keyOrigin = 0;
            keyRotated = 0;
            offset = 0;
        end
        
        case (state)

            `IDLE: begin
                if (prog_p) state <= `READING_KEY;
            end

            `WAITING_RDY_DATA_IN: begin
                if (data_ready_in_p) state <= `READING_DATA_ENCRYPTING;
            end

            `READING_KEY: begin
                keyOrigin = data_in_p;
                state = `WAITING_RDY_DATA_IN;
            end

            `READING_DATA_ENCRYPTING: begin
                data_in_store = data_in_p;
                offset = key_rotation_p;
                ready_p = 0;
                keyRotated = (keyOrigin << offset) | (keyOrigin >> (`ENCRYPTER_WIDTH-offset));
                #20;
                state = `SENDING_DATA;
            end

            `SENDING_DATA: begin
                if (capture_c)
                state <= `ACKNOWLEDGING_CAPTURE;
            end

        endcase
    end

    always @(negedge clk) begin
        case (state)
            `SENDING_DATA: begin
                data_out_c = data_in_store ^ keyRotated;
                data_ready_out_c = 1;
            end

            `WAITING_RDY_DATA_IN: begin
                if (~ready_p) ready_p = 1;
            end

            `ACKNOWLEDGING_CAPTURE: begin
                state <= `WAITING_RDY_DATA_IN;
                data_ready_out_c = 0;
                ready_p = 1;
            end
        endcase
    end
endmodule

Icarus-Verliog-testing/Parallelizer/parallelizer.sv
`include "./Constants/constants.vh"

`define STATE_IDLE 3'b000
`define STATE_PROGRAMMING 3'b001
`define STATE_RECEIVING_KEY 3'b010
`define STATE_PROGRAMMING_ENCRYPTERS 3'b011
`define STATE_WAITING_FOR_READY_ENCRYPTERS 3'b100
`define STATE_ENCRYPTING 3'b101

module Parallelizer (
    input wire clk,
    input wire reset,
    //QSPI
    input wire [3:0] qspi_data,
    input wire qspi_sending,
    output reg qspi_ready,
    //Program
    input wire prog,
    //To encrypters
    output reg [`ENCRYPTER_WIDTH-1:0] encrypters_data,
    output reg [`KEY_ROTATION_WIDTH-1:0] encrypters_key_rotation,
    output reg [`NUM_ENCRYPTERS-1:0] encrypters_program,
    output reg [`NUM_ENCRYPTERS-1:0] encrypters_data_ready,
    input wire [`NUM_ENCRYPTERS-1:0] encrypters_ready,
    //Watchers
    // output reg [2:0] state_out,
    output reg [`ENCRYPTER_WIDTH-1:0] key_out
    // output reg [`KEY_ROTATION_WIDTH-1:0] key_rotation_out,
    // output reg [`ENCRYPTER_QSPI_COUNT_REG-1:0] key_index_out,
    // output reg [`ENCRYPTER_WIDTH-1:0] encrypter_data_packet_out,
    // output reg [`ENCRYPTER_QSPI_COUNT_REG-1:0] encrypter_data_index_out,
    // output reg [`NUM_ENCRYPTERS_REG-1:0] encrypter_index_out
);

reg [2:0] state = `STATE_IDLE;
reg [`ENCRYPTER_WIDTH-1:0] key;
reg [`ENCRYPTER_QSPI_COUNT_REG-1:0] key_index;
reg [`KEY_ROTATION_WIDTH-1:0] key_rotation;

reg [`ENCRYPTER_WIDTH-1:0] encrypter_data_packet;

reg [`ENCRYPTER_QSPI_COUNT_REG-1:0] encrypter_data_index;
reg [`NUM_ENCRYPTERS_REG-1:0] encrypter_index;
integer i;

initial begin
    // assign state_out = state;
    assign key_out = key;
    // assign key_rotation_out = key_rotation;
    // assign key_index_out = key_index;
    // assign encrypter_data_packet_out = encrypter_data_packet;
    // assign encrypter_data_index_out = encrypter_data_index;
    // assign encrypter_index_out = encrypter_index;

    qspi_ready = 1'b0;
    encrypters_program = 0;
    key = 0;
    key_index = 0;
end

//read on positive
always @(posedge clk) begin

    if (reset) begin
        state <= `STATE_IDLE;
        qspi_ready = 1'b1;
    end

    case (state)

        `STATE_IDLE: begin 
            if (qspi_sending) begin
                state <= `STATE_ENCRYPTING;
                encrypter_index = 0;
                encrypter_data_index = 0;
                encrypters_data_ready = 0;
                key_rotation = 0;
            end
            if (prog) begin
                state <= `STATE_PROGRAMMING;
                qspi_ready = 1'b1;
                key_index = 0;
            end
        end

        `STATE_PROGRAMMING: if (qspi_sending) state <= `STATE_RECEIVING_KEY;

        `STATE_RECEIVING_KEY: begin 
            if (~qspi_sending) begin
                state = `STATE_IDLE;
            end else begin
                key[key_index*4] = qspi_data[0];
                key[key_index*4+1] = qspi_data[1];
                key[key_index*4+2] = qspi_data[2];
                key[key_index*4+3] = qspi_data[3];
                key_index = key_index + 1;
                if (key_index == `ENCRYPTER_QSPI_COUNT) begin
                    state = `STATE_PROGRAMMING_ENCRYPTERS;
                    qspi_ready = 1'b0;
                end
            end
        end

        `STATE_WAITING_FOR_READY_ENCRYPTERS: begin
            if (& encrypters_ready) begin
                state = `STATE_IDLE;
                qspi_ready = 1'b1;
                encrypters_program = 0;
                encrypter_index = 0;
            end
        end

        `STATE_ENCRYPTING: begin
            if (~qspi_sending) begin
                state = `STATE_IDLE;
            end else begin
            //read spi data
                encrypter_data_packet[encrypter_data_index*4] = qspi_data[0];
                encrypter_data_packet[encrypter_data_index*4+1] = qspi_data[1];
                encrypter_data_packet[encrypter_data_index*4+2] = qspi_data[2];
                encrypter_data_packet[encrypter_data_index*4+3] = qspi_data[3];
                encrypter_data_index = encrypter_data_index + 1;
            end
        end

        default:;

    endcase
end

//write on negative
always @(negedge clk) begin
    case (state)

        `STATE_PROGRAMMING_ENCRYPTERS: begin
            encrypters_data = key;
            for (encrypter_index = 0; encrypter_index < `NUM_ENCRYPTERS; encrypter_index = encrypter_index + 1) begin
                encrypters_program[encrypter_index] = 1'b1;
            end
            state = `STATE_WAITING_FOR_READY_ENCRYPTERS;
        end

        `STATE_ENCRYPTING: begin
            //keep ecrypter data index high for only 1 posedge clock cycle
            if (encrypter_index == 0) begin
                if (encrypters_data_ready[`NUM_ENCRYPTERS-1]) encrypters_data_ready[`NUM_ENCRYPTERS-1] = 0;
            end else begin
                if (encrypters_data_ready[encrypter_index-1]) encrypters_data_ready[encrypter_index-1] = 0;
            end

            if (encrypter_data_index == `ENCRYPTER_QSPI_COUNT) begin
                //when packet full, send to encrypters
                encrypter_data_index = 0;
                
                //check if encrypter is ready for new data
                if (encrypters_ready[encrypter_index]) begin
                    //put packet on encrypter bus
                    encrypters_data = encrypter_data_packet;
                    //put key rot on encrypter bus
                    encrypters_key_rotation = key_rotation;

                    //signal data is ready
                    encrypters_data_ready[encrypter_index] = 1'b1;

                    //move to next encrypter
                    encrypter_index = encrypter_index + 1;
                    if (encrypter_index == `NUM_ENCRYPTERS) encrypter_index = 0;

                    //move to next key rotation
                    key_rotation = key_rotation + 1;
                    if (key_rotation == `ENCRYPTER_WIDTH) key_rotation = 0;

                    //ready for more data as current data has been written
                    qspi_ready = 1'b1;
                end else begin
                    //if encrypter is not ready, wait for it
                    qspi_ready = 1'b0;
                end
            end
        end

        default:;

    endcase
end

endmodule

Icarus-Verliog-testing/TopLevel/top_level.sv
`timescale 10ns/10ns
`include "./Constants/constants.vh"
`include "./Parallelizer/parallelizer.sv"
`include "./Encrypter/encrypter.sv"
`include "./Collector/collector.sv"

module TopLevel();

    // Toplevel signals
    reg clk = 0;
    reg reset = 0;

    // Toplevel <-> Parallelizer signals
    reg [3:0] qspi_data_tp = 0;
    reg qspi_sending_tp = 0;
    wire qspi_ready_tp;
    reg prog_tp = 0;

    // Parallelizer <-> Encrypter signals
    wire [`ENCRYPTER_WIDTH-1:0] encrypters_data_pe;
    wire [`KEY_ROTATION_WIDTH-1:0] encrypters_key_rotation_pe;
    wire [`NUM_ENCRYPTERS-1:0] encrypters_program_pe;
    wire [`NUM_ENCRYPTERS-1:0] encrypters_data_ready_pe;
    wire [`NUM_ENCRYPTERS-1:0] encrypters_ready_pe;

    // Encrypter <-> Collector signals
    wire [`ENCRYPTER_WIDTH-1:0] encrypters_data_ec [`NUM_ENCRYPTERS-1:0];
    wire [`NUM_ENCRYPTERS-1:0] encrypters_data_ready_ec;
    wire [`NUM_ENCRYPTERS-1:0] encrypters_capture_ec;

    // Collector <-> Toplevel signals
    wire [3:0] qspi_data_ct;
    wire qspi_sending_ct;
    reg qspi_ready_ct = 1;

    // Watchers
    // wire [2:0] state_out_p;
    wire [`ENCRYPTER_WIDTH-1:0] key_out;
    wire [`ENCRYPTER_WIDTH-1:0] encrypters_data_ec1;
    wire [`ENCRYPTER_WIDTH-1:0] encrypters_data_ec2;

    assign encrypters_data_ec1 = encrypters_data_ec[0];
    assign encrypters_data_ec2 = encrypters_data_ec[1];

    Parallelizer p_inst(
        .clk(clk),
        .reset(reset),
        .qspi_data(qspi_data_tp),
        .qspi_sending(qspi_sending_tp),
        .qspi_ready(qspi_ready_tp),
        .prog(prog_tp),
        .encrypters_data(encrypters_data_pe),
        .encrypters_key_rotation(encrypters_key_rotation_pe),
        .encrypters_program(encrypters_program_pe),
        .encrypters_data_ready(encrypters_data_ready_pe),
        .encrypters_ready(encrypters_ready_pe),
        // .state_out(state_out_p),
        .key_out(key_out)
    );

    genvar e;
    generate
        for (e = 0; e < `NUM_ENCRYPTERS; e = e + 1) begin : encrypter_loop
            Encrypter e_inst (
                .clk(clk),
                .reset(reset),
                .data_in_p(encrypters_data_pe),
                .key_rotation_p(encrypters_key_rotation_pe),
                .prog_p(encrypters_program_pe[e]),
                .data_ready_in_p(encrypters_data_ready_pe[e]),
                .ready_p(encrypters_ready_pe[e]),
                .data_out_c(encrypters_data_ec[e]),
                .data_ready_out_c(encrypters_data_ready_ec[e]),
                .capture_c(encrypters_capture_ec[e])
            );
        end
    endgenerate

    Collector c_inst(
        .clk(clk),
        .reset(reset),
        .qspi_data(qspi_data_ct),
        .qspi_sending(qspi_sending_ct),
        .qspi_ready(qspi_ready_ct),
        .encrypters_data(encrypters_data_ec),
        .encrypters_data_ready(encrypters_data_ready_ec),
        .encrypters_capture(encrypters_capture_ec)
    );

    reg [3:0] spi_data_values[255:0];
    reg [3:0] encrypters_delays [`NUM_ENCRYPTERS-1:0];
    integer fd, i, j;

    initial begin
        //fill spi_data_values with data from file
        fd = $fopen("./Constants/qspi_data.csv", "r");
        if (fd == -1) begin
            $display("Error data file!");
            $finish;  // Exit simulation on error
        end
        for (i = 0; i < 256; i++) begin
            j = $fscanf(fd, "%h", spi_data_values[i]);
        end
        $fclose(fd);

        fd = $fopen("./TopLevel/encrypted_qspi_data.csv", "w");
        if (fd == -1) begin
            $display("Error encrypted data file!");
            $finish;  // Exit simulation on error
        end

        for (j = 0; j < `NUM_ENCRYPTERS-1; j = j + 1) begin
            encrypters_delays[j] = 0;
        end
    end

    initial begin
        $dumpfile("TopLevel/top_level.vcd");
        $dumpvars(0, TopLevel);
        $display("Starting simulation");

        //set data on neg edge, read on the rising
        #2 reset = 1; #2 reset = 0;
        #2 prog_tp = 1; #2 prog_tp = 0;

        //send key
        while (!qspi_ready_tp) #2;
        #2 qspi_sending_tp = 1; #2
        for (i = 0; i < `ENCRYPTER_QSPI_COUNT; i = i + 1) begin
            qspi_data_tp = spi_data_values[i];
            $display("[KEY] qspi_data_tp <= 0x%h", spi_data_values[i]);
            #2;
        end
        qspi_sending_tp = 0;

        //send data
        while (!qspi_ready_tp) #2;
        #2 qspi_sending_tp = 1; #2
        for (i = `ENCRYPTER_QSPI_COUNT; i < 256; i = i + 1) begin
            if (!qspi_ready_tp) begin
                i = i - 1;
                #2;
            end else begin
                qspi_data_tp = spi_data_values[i];
                $display("[DATA] qspi_data_tp <= 0x%h", spi_data_values[i]);
                #2;
            end
        end
        #2 qspi_sending_tp = 0;

        #4 $fclose(fd); $finish;
    end

    always begin
        #1 clk = ~clk;
        if (clk) begin
            if (qspi_sending_ct) begin
                $fwrite(fd, "0x%x\n", qspi_data_ct);
                $display("[COL] qspi_data_ct >= 0x%h", qspi_data_ct);
            end
        end
    end

endmodule

Icarus-Verliog-testing/TopLevel/top_level.vcd
$date
	Fri May 17 14:39:15 2024
$end
$version
	Icarus Verilog
$end
$timescale
	10ns
$end
$scope module TopLevel $end
$var wire 16 ! encrypters_data_ec1 [15:0] $end
$var wire 16 " encrypters_data_ec2 [15:0] $end
$var wire 1 # qspi_sending_ct $end
$var wire 1 $ qspi_ready_tp $end
$var wire 4 % qspi_data_ct [3:0] $end
$var wire 16 & key_out [15:0] $end
$var wire 2 ' encrypters_ready_pe [1:0] $end
$var wire 2 ( encrypters_program_pe [1:0] $end
$var wire 4 ) encrypters_key_rotation_pe [3:0] $end
$var wire 2 * encrypters_data_ready_pe [1:0] $end
$var wire 2 + encrypters_data_ready_ec [1:0] $end
$var wire 16 , encrypters_data_pe [15:0] $end
$var wire 2 - encrypters_capture_ec [1:0] $end
$var reg 1 . clk $end
$var reg 1 / prog_tp $end
$var reg 4 0 qspi_data_tp [3:0] $end
$var reg 1 1 qspi_ready_ct $end
$var reg 1 2 qspi_sending_tp $end
$var reg 1 3 reset $end
$var integer 32 4 fd [31:0] $end
$var integer 32 5 i [31:0] $end
$var integer 32 6 j [31:0] $end
$scope begin encrypter_loop[0] $end
$var parameter 2 7 e $end
$scope module e_inst $end
$var wire 1 8 capture_c $end
$var wire 1 . clk $end
$var wire 1 9 data_ready_in_p $end
$var wire 1 : prog_p $end
$var wire 1 3 reset $end
$var wire 4 ; key_rotation_p [3:0] $end
$var wire 16 < data_in_p [15:0] $end
$var reg 16 = data_in_store [15:0] $end
$var reg 16 > data_out_c [15:0] $end
$var reg 1 ? data_ready_out_c $end
$var reg 16 @ keyOrigin [15:0] $end
$var reg 16 A keyRotated [15:0] $end
$var reg 5 B offset [4:0] $end
$var reg 1 C ready_p $end
$var reg 3 D state [2:0] $end
$upscope $end
$upscope $end
$scope begin encrypter_loop[1] $end
$var parameter 2 E e $end
$scope module e_inst $end
$var wire 1 F capture_c $end
$var wire 1 . clk $end
$var wire 1 G data_ready_in_p $end
$var wire 1 H prog_p $end
$var wire 1 3 reset $end
$var wire 4 I key_rotation_p [3:0] $end
$var wire 16 J data_in_p [15:0] $end
$var reg 16 K data_in_store [15:0] $end
$var reg 16 L data_out_c [15:0] $end
$var reg 1 M data_ready_out_c $end
$var reg 16 N keyOrigin [15:0] $end
$var reg 16 O keyRotated [15:0] $end
$var reg 5 P offset [4:0] $end
$var reg 1 Q ready_p $end
$var reg 3 R state [2:0] $end
$upscope $end
$upscope $end
$scope module c_inst $end
$var wire 1 . clk $end
$var wire 2 S encrypters_data_ready [1:0] $end
$var wire 1 1 qspi_ready $end
$var wire 1 3 reset $end
$var reg 3 T encrypter_data_index [2:0] $end
$var reg 16 U encrypter_data_packet [15:0] $end
$var reg 2 V encrypter_index [1:0] $end
$var reg 2 W encrypters_capture [1:0] $end
$var reg 4 X qspi_data [3:0] $end
$var reg 1 # qspi_sending $end
$var reg 2 Y state [1:0] $end
$upscope $end
$scope module p_inst $end
$var wire 1 . clk $end
$var wire 2 Z encrypters_ready [1:0] $end
$var wire 1 / prog $end
$var wire 4 [ qspi_data [3:0] $end
$var wire 1 2 qspi_sending $end
$var wire 1 3 reset $end
$var reg 3 \ encrypter_data_index [2:0] $end
$var reg 16 ] encrypter_data_packet [15:0] $end
$var reg 2 ^ encrypter_index [1:0] $end
$var reg 16 _ encrypters_data [15:0] $end
$var reg 2 ` encrypters_data_ready [1:0] $end
$var reg 4 a encrypters_key_rotation [3:0] $end
$var reg 2 b encrypters_program [1:0] $end
$var reg 16 c key [15:0] $end
$var reg 3 d key_index [2:0] $end
$var reg 16 e key_out [15:0] $end
$var reg 4 f key_rotation [3:0] $end
$var reg 1 $ qspi_ready $end
$var reg 3 g state [2:0] $end
$upscope $end
$upscope $end
$enddefinitions $end
$comment Show the parameter values. $end
$dumpall
b1 E
b0 7
$end
#0
$dumpvars
b0 g
bx f
b0 e
b0 d
b0 c
b0 b
bx a
bx `
bx _
bx ^
bx ]
bx \
b0 [
b0 Z
b0 Y
bx X
b0 W
bx V
bx U
bx T
b0 S
b0 R
0Q
b0 P
b0 O
b0 N
0M
b0 L
b0 K
bx J
bx I
0H
xG
0F
b0 D
0C
b0 B
b0 A
b0 @
0?
b0 >
b0 =
bx <
bx ;
0:
x9
08
b1 6
b100000000 5
b10000000000000000000000000000011 4
03
02
11
b0 0
0/
0.
b0 -
bx ,
b0 +
bx *
bx )
b0 (
b0 '
b0 &
bx %
0$
0#
b0 "
b0 !
$end
#1
1.
#2
0.
13
#3
b0 V
b1 Y
1$
1.
#4
0.
03
#5
1.
#6
0.
1/
#7
b1 g
1.
#8
0.
0/
#9
1.
#10
0.
12
#11
b10 g
1.
#12
0.
b1101 0
b1101 [
b0 5
#13
b1 d
b1101 &
b1101 e
b1101 c
1.
#14
0.
b1 0
b1 [
b1 5
#15
b10 d
b11101 &
b11101 e
b11101 c
1.
#16
0.
b1010 0
b1010 [
b10 5
#17
b11 d
b101000011101 &
b101000011101 e
b101000011101 c
1.
#18
0.
b11 5
#19
0$
b11 g
b100 d
b1010101000011101 &
b1010101000011101 e
b1010101000011101 c
1.
#20
1H
1:
b100 g
b11 (
b11 b
b10 ^
b1010101000011101 ,
b1010101000011101 <
b1010101000011101 J
b1010101000011101 _
0.
02
b100 5
#21
b1 D
b1 R
1.
#22
0.
#23
b10 R
b1010101000011101 N
b10 D
b1010101000011101 @
1.
#24
1Q
b11 '
b11 Z
1C
0.
#25
0H
0:
b0 ^
b0 (
b0 b
1$
b0 g
1.
#26
0.
#27
1.
#28
0.
12
#29
b101 g
0G
09
b0 f
b0 *
b0 `
b0 \
1.
#30
0.
b11 0
b11 [
#31
b1 \
bx0011 ]
1.
#32
0.
b10 0
b10 [
b101 5
#33
b10 \
bx00100011 ]
1.
#34
0.
b1011 0
b1011 [
b110 5
#35
b11 \
bx101100100011 ]
1.
#36
0.
b1 0
b1 [
b111 5
#37
b100 \
b1101100100011 ]
1.
#38
19
b1 f
b1 ^
b1 *
b1 `
b0 )
b0 ;
b0 I
b0 a
b1101100100011 ,
b1101100100011 <
b1101100100011 J
b1101100100011 _
b0 \
0.
b1100 0
b1100 [
b1000 5
#39
b11 D
b1 \
b1101100101100 ]
1.
#40
09
b0 *
b0 `
0.
b1000 0
b1000 [
b1001 5
#41
b1010101000011101 A
b10 '
b10 Z
0C
b1101100100011 =
b10 \
b1101110001100 ]
1.
#42
0.
b111 0
b111 [
b1010 5
#43
b11 \
b1011110001100 ]
1.
#44
0.
b1101 0
b1101 [
b1011 5
#45
b100 \
b1101011110001100 ]
1.
#46
1G
b10 f
b0 ^
b10 *
b10 `
b1 )
b1 ;
b1 I
b1 a
b1101011110001100 ,
b1101011110001100 <
b1101011110001100 J
b1101011110001100 _
b0 \
0.
b1001 0
b1001 [
b1100 5
#47
b11 R
b1 \
b1101011110001001 ]
1.
#48
0G
b0 *
b0 `
0.
b110 0
b110 [
b1101 5
#49
b101010000111011 O
b0 '
b0 Z
0Q
b1 P
b1101011110001100 K
b10 \
b1101011101101001 ]
1.
#50
0.
b1001 0
b1001 [
b1110 5
#51
b11 \
b1101100101101001 ]
1.
#52
0.
b10 0
b10 [
b1111 5
#53
b100 \
b10100101101001 ]
1.
#54
0$
b0 \
0.
b111 0
b111 [
b10000 5
#55
b1 \
b10100101100111 ]
1.
#56
0.
b10000 5
#57
b10 \
b10100101110111 ]
1.
#58
0.
b10000 5
#59
b11 \
b10011101110111 ]
1.
#60
0.
b10000 5
#61
b100 \
b111011101110111 ]
1.
b100 D
#62
b1 +
b1 S
1?
b1011000100111110 !
b1011000100111110 >
b0 \
0.
b10000 5
#63
b10 Y
b0 T
b1011000100111110 U
b1 \
1.
#64
18
b1 -
b1 W
b1 T
b1110 %
b1110 X
1#
b11 Y
0.
b10000 5
#65
b101 D
b10 \
1.
#66
08
b10 D
b0 -
b0 W
b1 '
b1 Z
1C
b0 +
b0 S
0?
b10 T
b11 %
b11 X
0.
b10000 5
#67
b11 \
1.
#68
b11 T
b1 %
b1 X
0.
b10000 5
#69
b100 \
1.
b100 R
#70
b1 Y
19
b10 +
b10 S
1M
b1000001110110111 "
b1000001110110111 L
1$
b11 f
b1 ^
b1 *
b1 `
b10 )
b10 ;
b10 I
b10 a
b111011101110111 ,
b111011101110111 <
b111011101110111 J
b111011101110111 _
b0 \
b1 V
b100 T
b1011 %
b1011 X
0.
b10000 5
#71
b11 D
b10 Y
b0 T
b1000001110110111 U
b1 \
1.
#72
1F
b10 -
b10 W
09
b1 T
b111 %
b111 X
b11 Y
b0 *
b0 `
0.
b1011 0
b1011 [
b10001 5
#73
b101 R
b10 \
b111011110110111 ]
b1010100001110110 A
b0 '
b0 Z
0C
b10 B
b111011101110111 =
1.
#74
0F
b10 R
b0 -
b0 W
b10 '
b10 Z
1Q
b0 +
b0 S
0M
b10 T
b1011 %
b1011 X
0.
b0 0
b0 [
b10010 5
#75
b11 \
b111000010110111 ]
1.
#76
b11 T
b11 %
b11 X
0.
b110 0
b110 [
b10011 5
#77
b100 \
b110000010110111 ]
1.
#78
b1 Y
1G
b100 f
b0 ^
b10 *
b10 `
b11 )
b11 ;
b11 I
b11 a
b110000010110111 ,
b110000010110111 <
b110000010110111 J
b110000010110111 _
b0 \
b0 V
b100 T
b1000 %
b1000 X
0.
b11 0
b11 [
b10100 5
#79
b11 R
0#
b1 \
b110000010110011 ]
1.
#80
0G
b0 *
b0 `
0.
b111 0
b111 [
b10101 5
#81
b10 \
b110000001110011 ]
b101000011101101 O
b0 '
b0 Z
0Q
b11 P
b110000010110111 K
1.
#82
0.
b101 0
b101 [
b10110 5
#83
b11 \
b110010101110011 ]
1.
#84
0.
b1010 0
b1010 [
b10111 5
#85
b100 \
b1010010101110011 ]
1.
#86
0$
b0 \
0.
b100 0
b100 [
b11000 5
#87
b1 \
b1010010101110100 ]
1.
#88
0.
b11000 5
#89
b10 \
b1010010101000100 ]
1.
#90
0.
b11000 5
#91
b11 \
b1010010001000100 ]
1.
#92
0.
b11000 5
#93
b100 \
b100010001000100 ]
1.
b100 D
#94
b1 +
b1 S
1?
b1101111100000001 !
b1101111100000001 >
b0 \
0.
b11000 5
#95
b10 Y
b0 T
b1101111100000001 U
b1 \
1.
#96
18
b1 -
b1 W
b1 T
b1 %
b1 X
1#
b11 Y
0.
b11000 5
#97
b101 D
b10 \
1.
#98
08
b10 D
b0 -
b0 W
b1 '
b1 Z
1C
b0 +
b0 S
0?
b10 T
b0 %
b0 X
0.
b11000 5
#99
b11 \
1.
#100
b11 T
b1111 %
b1111 X
0.
b11000 5
#101
b100 \
1.
b100 R
#102
b1 Y
19
b10 +
b10 S
1M
b11000001011010 "
b11000001011010 L
1$
b101 f
b1 ^
b1 *
b1 `
b100 )
b100 ;
b100 I
b100 a
b100010001000100 ,
b100010001000100 <
b100010001000100 J
b100010001000100 _
b0 \
b1 V
b100 T
b1101 %
b1101 X
0.
b11000 5
#103
b11 D
b10 Y
b0 T
b11000001011010 U
b1 \
1.
#104
1F
b10 -
b10 W
09
b1 T
b1010 %
b1010 X
b11 Y
b0 *
b0 `
0.
b10 0
b10 [
b11001 5
#105
b101 R
b10 \
b100010000100100 ]
b1010000111011010 A
b0 '
b0 Z
0C
b100 B
b100010001000100 =
1.
#106
0F
b10 R
b0 -
b0 W
b10 '
b10 Z
1Q
b0 +
b0 S
0M
b10 T
b101 %
b101 X
0.
b100 0
b100 [
b11010 5
#107
b11 \
1.
#108
b11 T
b0 %
b0 X
0.
b110 0
b110 [
b11011 5
#109
b100 \
b110010000100100 ]
1.
#110
b1 Y
1G
b110 f
b0 ^
b10 *
b10 `
b101 )
b101 ;
b101 I
b101 a
b110010000100100 ,
b110010000100100 <
b110010000100100 J
b110010000100100 _
b0 \
b0 V
b100 T
b11 %
b11 X
0.
b0 0
b0 [
b11100 5
#111
b11 R
0#
b1 \
b110010000100000 ]
1.
#112
0G
b0 *
b0 `
0.
b1110 0
b1110 [
b11101 5
#113
b10 \
b110010011100000 ]
b100001110110101 O
b0 '
b0 Z
0Q
b101 P
b110010000100100 K
1.
#114
0.
b0 0
b0 [
b11110 5
