Icarus-Verliog-testing/Collector/collector.sv
`include "./Constants/constants.vh"
`define IDLE 2'b00
`define WAITING 2'b01
`define SENDING 2'b10


module Collector(
    input wire clk,
    input wire reset,
    //QSPI
    
    output reg [3:0] qspi_data,
    output reg qspi_sending = 0,
    input wire qspi_ready,
    
    //To encrypters
    input wire [`ENCRYPTER_WIDTH-1:0] encrypters_data,
    input wire [`NUM_ENCRYPTERS-1:0] encrypters_data_ready,
    output reg [`NUM_ENCRYPTERS-1:0] encrypters_capture

    //Watchers
    // output reg [1:0] state_out,
    // output reg [`ENCRYPTER_WIDTH-1:0] encrypter_data_packe_out,
    
    // output reg [`ENCRYPTER_WIDTH_COUNT_REG-1:0] encrypter_data_subindex_out,
    // output reg [`NUM_ENCRYPTERS_REG-1:0] encrypter_index_out,
    // output reg [`ENCRYPTER_QSPI_COUNT_REG-1:0] encrypter_data_index_out    
); // 4-bit collector

    reg [1:0] state = `IDLE;

    reg [`ENCRYPTER_WIDTH-1:0] encrypter_data_packet;
    reg [`ENCRYPTER_WIDTH_COUNT_REG-1:0] encrypter_data_subindex;

    reg [`NUM_ENCRYPTERS_REG-1:0] encrypter_index;

    reg [`ENCRYPTER_QSPI_COUNT_REG-1:0] encrypter_data_index;

    
    // assign state_out = state;
    // assign encrypter_data_packe_out = encrypter_data_packet;
    // assign encrypter_data_subindex_out = encrypter_data_subindex;
    // assign encrypter_index_out = encrypter_index;
    // assign encrypter_data_index_out = encrypter_data_index;


    

    always @(posedge reset) begin
        state <= `WAITING;
        encrypter_index <= 0;
    end  


    always @(posedge clk) begin
        if (state == `WAITING) begin
            if(encrypters_data_ready[encrypter_index]) begin
                encrypter_data_packet = encrypters_data;
                // for (encrypter_data_subindex = 0; encrypter_data_subindex < `ENCRYPTER_WIDTH; encrypter_data_subindex = encrypter_data_subindex + 1) begin
                //     encrypter_data_packet[encrypter_data_subindex] = encrypters_data[encrypter_index][encrypter_data_subindex];
                // end
                state <= `SENDING;
                encrypter_data_index = 0;
            end
        end
    end 

    always @(negedge clk) begin 
        if (encrypters_capture[encrypter_index]) encrypters_capture[encrypter_index] <= 0;

        if (state == `SENDING) begin  encrypters_capture[encrypter_index] <= 1;  
            if (encrypter_data_index == 0) encrypters_capture[encrypter_index] <= 1;  
                if(qspi_ready) begin
                    qspi_sending = 1;
                    qspi_data[0] = encrypter_data_packet[encrypter_data_index*4];
                    qspi_data[1] = encrypter_data_packet[encrypter_data_index*4+1]; 
                    qspi_data[2] = encrypter_data_packet[encrypter_data_index*4+2];
                    qspi_data[3] = encrypter_data_packet[encrypter_data_index*4+3];  
                    encrypter_data_index = encrypter_data_index + 1;   
                    if(encrypter_data_index == `ENCRYPTER_QSPI_COUNT) begin
                        qspi_sending = 0;
                            encrypter_index = encrypter_index + 1;
                            if (encrypter_index == `NUM_ENCRYPTERS) begin
                                encrypter_index = 0;
                            end
                        state <= `WAITING; 
                    end           
                end
            else qspi_sending = 0;   
        end     
    end 


endmodule

Icarus-Verliog-testing/Encrypter/encrypter.sv
`include "./Constants/constants.vh"

`define IDLE 3'b000
`define READING_KEY 3'b001
`define WAITING_RDY_DATA_IN 3'b010
`define READING_DATA 3'b011
`define ENCRYPTING 3'b100
`define SENDING_DATA 3'b101

module Encrypter (
    input wire clk,
    input wire reset,

    input wire [`ENCRYPTER_WIDTH-1:0] dataIn,
    input wire [`KEY_ROTATION_WIDTH-1:0] rot_offset,
    input wire rdyIn,
    input wire cap,
    input wire prog,

    output reg [`ENCRYPTER_WIDTH-1:0] dataOut,
    output reg reqIn,
    output reg reqOut,

    output reg [2:0] state,
    output reg [`KEY_WIDTH-1:0] key,
    output reg [`ENCRYPTER_WIDTH-1:0] data_in
);

    reg [`ENCRYPTER_WIDTH-1:0] data_out;
    reg [`KEY_WIDTH-1:0] keyTemp;
    reg [`KEY_ROTATION_WIDTH:0] offset;

    initial begin
        state <= `IDLE;
        reqIn = 0;
        reqOut = 0;
        dataOut = 0;
        data_in = 0;
        key = 0;
        offset = 0;
    end

    always @(posedge reset) begin
        state <= `IDLE;
        reqIn = 0;
        reqOut = 0;
        dataOut = 0;
        data_in = 0;
        key = 0;
        offset = 0;
    end

    always @(posedge prog) begin
        state <= `READING_KEY;
    end

    always @(posedge rdyIn) begin
        state <= `READING_DATA;
    end

    always @(posedge cap) begin
        state <= `WAITING_RDY_DATA_IN;
        reqOut = 0;
        reqIn = 1;
    end

    always @(posedge clk) begin
        case (state)
            `READING_KEY: begin
                keyTemp = dataIn;
                state = `WAITING_RDY_DATA_IN;
                reqIn = 1;
            end

            `READING_DATA: begin
                data_in = dataIn;
                offset = rot_offset;
                state = `ENCRYPTING;
                reqIn = 0;
            end

            `ENCRYPTING: begin
                key = (keyTemp << offset) | (keyTemp >> (`KEY_WIDTH-offset));
                data_out = data_in ^ key;
                state = `SENDING_DATA;
            end
        endcase
    end

    always @(negedge clk) begin
        case (state)
            `SENDING_DATA: begin
                dataOut = data_out;
                reqOut = 1;
            end
        endcase
    end
endmodule

Icarus-Verliog-testing/Constants/constants.vh
//DEFINE CONSTANTS
// `define KEY_WIDTH 16 // width of the key. In multiples of 4.
// `define KEY_QSPI_COUNT `KEY_WIDTH/4 // number of QSPI transactions per key sent in LSB. 
// `define KEY_QSPI_COUNT_REG $clog2(`KEY_QSPI_COUNT+1) // register size required to count the current QSPI transaction of the key + 1. log2(`KEY_QSPI_COUNT+1)

`define ENCRYPTER_WIDTH 32 // width of the bus between the Paralellizer and Encrypter, and the Encrypter and Collector. In multiples of 4.
`define ENCRYPTER_WIDTH_COUNT_REG $clog2(`ENCRYPTER_WIDTH+1) // register size required to count the current bit of the encrypter bus + 1. log2(`ENCRYPTER_WIDTH+1). (Verilog doesn't like me so i need a for loop)
`define ENCRYPTER_QSPI_COUNT `ENCRYPTER_WIDTH/4 // number of QSPI transactions per Encrypter.
`define ENCRYPTER_QSPI_COUNT_REG $clog2(`ENCRYPTER_QSPI_COUNT+1) // register size required to count the current QSPI transaction of the Encrypter + 1. log2(`ENCRYPTER_QSPI_COUNT+1)

`define KEY_ROTATION_WIDTH $clog2(`ENCRYPTER_WIDTH) // width of the key rotation bus between Paralellizer and Encrypter. log2(`KEY_WIDTH)
`define KEY_ROTATION_WIDTH_COUNT_REG $clog2(`KEY_ROTATION_WIDTH+1) // register size required to count the current bit of the key rotation bus + 1. log2(`KEY_ROTATION_WIDTH+1). (Verilog doesn't like me so i need a for loop)

// `define KEY_ENCRYPTER_COUNT `KEY_WIDTH/`ENCRYPTER_WIDTH // number of Encrypters transactions per key. `KEY_WIDTH/`ENCRYPTER_WIDTH
// `define KEY_ENCRYPTER_COUNT_REG $clog2(`KEY_ENCRYPTER_COUNT+1) // register size required to count the current Encrypter transaction of the key + 1. log2(`KEY_ENCRYPTER_COUNT+1)

`define NUM_ENCRYPTERS 2 // number of Encrypters
`define NUM_ENCRYPTERS_REG $clog2(`NUM_ENCRYPTERS+1) // register size required to count the current Encrypter + 1. log2(`NUM_ENCRYPTERS+1)

Icarus-Verliog-testing/Parallelizer/parallelizer.sv
`include "./Constants/constants.vh"

`define STATE_IDLE 3'b000
`define STATE_PROGRAMMING 3'b001
`define STATE_RECEIVING_KEY 3'b010
`define STATE_PROGRAMMING_ENCRYPTERS 3'b011
`define STATE_WAITING_FOR_READY_ENCRYPTERS 3'b100
`define STATE_ENCRYPTING 3'b101

module Parallelizer (
    input wire clk,
    input wire reset,
    //QSPI
    input wire [3:0] qspi_data,
    input wire qspi_sending,
    output reg qspi_ready,
    //Program
    input wire prog,
    //To encrypters
    output reg [`ENCRYPTER_WIDTH-1:0] encrypters_data,
    output reg [`KEY_ROTATION_WIDTH-1:0] encrypters_key_rotation,
    output reg [`NUM_ENCRYPTERS-1:0] encrypters_program,
    output reg [`NUM_ENCRYPTERS-1:0] encrypters_data_ready,
    input wire [`NUM_ENCRYPTERS-1:0] encrypters_ready,
    //Watchers
    output reg [2:0] state_out,
    output reg [`KEY_WIDTH-1:0] key_out
    // output reg [`KEY_ROTATION_WIDTH-1:0] key_rotation_out,
    // output reg [`KEY_QSPI_COUNT_REG-1:0] key_index_out,
    // output reg [`KEY_ENCRYPTER_COUNT_REG-1:0] key_encrypter_index_out,
    // output reg [`ENCRYPTER_WIDTH-1:0] encrypter_data_packet_out,
    // output reg [`ENCRYPTER_QSPI_COUNT_REG-1:0] encrypter_data_index_out,
    // output reg [`NUM_ENCRYPTERS_REG-1:0] encrypter_index_out
);

reg [2:0] state = `STATE_IDLE;
reg [`KEY_WIDTH-1:0] key;
reg [`KEY_QSPI_COUNT_REG-1:0] key_index;
reg [`KEY_ROTATION_WIDTH-1:0] key_rotation;

reg [`KEY_ENCRYPTER_COUNT_REG-1:0] key_encrypter_index;

reg [`ENCRYPTER_WIDTH-1:0] encrypter_data_packet;

reg [`ENCRYPTER_QSPI_COUNT_REG-1:0] encrypter_data_index;
reg [`NUM_ENCRYPTERS_REG-1:0] encrypter_index;
integer i;

initial begin
    assign state_out = state;
    assign key_out = key;
    // assign key_rotation_out = key_rotation;
    // assign key_index_out = key_index;
    // assign encrypter_data_packet_out = encrypter_data_packet;
    // assign encrypter_data_index_out = encrypter_data_index;
    // assign encrypter_index_out = encrypter_index;

    qspi_ready = 1'b0;
    encrypters_program = 0;
    key = 0;
    key_index = 0;
end

always @(posedge reset) begin
    state <= `STATE_IDLE;
    qspi_ready = 1'b1;
end

always @(posedge prog) begin
    if (state == `STATE_IDLE) begin
        state <= `STATE_PROGRAMMING;
        qspi_ready = 1'b1;
        key_index = 0;
    end
end

always @(posedge qspi_sending) begin
    case (state)

        `STATE_IDLE: begin
            state <= `STATE_ENCRYPTING;
            encrypter_index = 0;
            encrypter_data_index = 0;
            encrypters_data_ready = 0;
            key_rotation = 0;
            key_encrypter_index = 0;
        end

        `STATE_PROGRAMMING: state <= `STATE_RECEIVING_KEY;

        default:;

    endcase
end

always @(negedge qspi_sending) begin
    case (state)
        `STATE_ENCRYPTING: state = `STATE_IDLE;
        `STATE_RECEIVING_KEY: state = `STATE_IDLE;
        default:;
    endcase
end

//read on positive
always @(posedge clk) begin
    case (state)

        `STATE_RECEIVING_KEY: begin 
            key[key_index*4] = qspi_data[0];
            key[key_index*4+1] = qspi_data[1];
            key[key_index*4+2] = qspi_data[2];
            key[key_index*4+3] = qspi_data[3];
            key_index = key_index + 1;
            if (key_index == `KEY_QSPI_COUNT) begin
                state = `STATE_PROGRAMMING_ENCRYPTERS;
                key_encrypter_index = 0;
                qspi_ready = 1'b0;
            end
        end

        `STATE_WAITING_FOR_READY_ENCRYPTERS: begin
            state = `STATE_IDLE;
            for (encrypter_index = 0; encrypter_index < `NUM_ENCRYPTERS; encrypter_index++) begin
                if (~encrypters_ready[encrypter_index]) begin
                    state = `STATE_WAITING_FOR_READY_ENCRYPTERS;
                end
            end
            if (state == `STATE_IDLE) begin
                qspi_ready = 1'b1;
                encrypters_program = 0;
            end
        end

        `STATE_ENCRYPTING: begin
            //read spi data
            encrypter_data_packet[encrypter_data_index*4] = qspi_data[0];
            encrypter_data_packet[encrypter_data_index*4+1] = qspi_data[1];
            encrypter_data_packet[encrypter_data_index*4+2] = qspi_data[2];
            encrypter_data_packet[encrypter_data_index*4+3] = qspi_data[3];
            encrypter_data_index = encrypter_data_index + 1;
        end

        default:;

    endcase
end

//write on negative
always @(negedge clk) begin
    case (state)

        `STATE_PROGRAMMING_ENCRYPTERS: begin
            
            for (encrypter_index = 0; encrypter_index < `NUM_ENCRYPTERS; encrypter_index = encrypter_index + 1) begin
                encrypters_data = key[key_encrypter_index * `ENCRYPTER_WIDTH +: `ENCRYPTER_WIDTH];
                encrypters_program[encrypter_index] = 1'b1;
            end

            key_encrypter_index = key_encrypter_index + 1;
            if (key_encrypter_index == `KEY_ENCRYPTER_COUNT) state = `STATE_WAITING_FOR_READY_ENCRYPTERS;
        end

        `STATE_ENCRYPTING: begin
            //keep ecrypter data index high for only 1 posedge clock cycle
            if (encrypter_index == 0) begin
                if (encrypters_data_ready[`NUM_ENCRYPTERS-1]) encrypters_data_ready[`NUM_ENCRYPTERS-1] = 0;
            end else begin
                if (encrypters_data_ready[encrypter_index-1]) encrypters_data_ready[encrypter_index-1] = 0;
            end

            if (encrypter_data_index == `ENCRYPTER_QSPI_COUNT) begin
                //when packet full, send to encrypters
                encrypter_data_index = 0;
                
                //check if encrypter is ready for new data
                if (encrypters_ready[encrypter_index]) begin
                    //put packet on encrypter bus
                    encrypters_data = encrypter_data_packet;
                    //put key rot on encrypter bus
                    encrypters_key_rotation = key_rotation;

                    //signal data is ready
                    encrypters_data_ready[encrypter_index] = 1'b1;

                    //move to next encrypter
                    encrypter_index = encrypter_index + 1;
                    if (encrypter_index == `NUM_ENCRYPTERS) encrypter_index = 0;

                    //move to next key rotation
                    key_encrypter_index = key_encrypter_index + 1;
                    if (key_encrypter_index == `KEY_ENCRYPTER_COUNT) begin
                        key_encrypter_index = 0;
                        key_rotation = key_rotation + 1;
                        if (key_rotation == `KEY_WIDTH) key_rotation = 0;
                    end

                    //ready for more data as current data has been written
                    qspi_ready = 1'b1;
                end else begin
                    //if encrypter is not ready, wait for it
                    qspi_ready = 1'b0;
                end
            end
        end

        default:;

    endcase
end

endmodule

Icarus-Verliog-testing/TopLevel/top_level.sv
`include "./Constants/constants.vh"
`include "./Parallelizer/parallelizer.sv"
`include "./Encrypter/encrypter.sv"
`include "./Collector/collector.sv"

module TopLevel();

    // Toplevel signals
    reg clk = 0;
    reg reset = 0;

    // Toplevel <-> Parallelizer signals
    reg [3:0] qspi_data_tp = 0;
    reg qspi_sending_tp = 0;
    wire qspi_ready_tp;
    reg prog_tp = 0;

    // Parallelizer <-> Encrypter signals
    wire [`ENCRYPTER_WIDTH-1:0] encrypters_data_pe;
    wire [`KEY_ROTATION_WIDTH-1:0] encrypters_key_rotation_pe;
    wire [`NUM_ENCRYPTERS-1:0] encrypters_program_pe;
    wire [`NUM_ENCRYPTERS-1:0] encrypters_data_ready_pe;
    wire [`NUM_ENCRYPTERS-1:0] encrypters_ready_pe;

    // Encrypter <-> Collector signals
    wire [`ENCRYPTER_WIDTH-1:0] encrypters_data_ec;
    wire [`NUM_ENCRYPTERS-1:0] encrypters_data_ready_ec;
    wire [`NUM_ENCRYPTERS-1:0] encrypters_capture_ec;

    // Collector <-> Toplevel signals
    wire [3:0] qspi_data_ct;
    wire qspi_sending_ct;
    reg qspi_ready_ct = 0;

    // Watchers
    wire [2:0] state_out_p;
    wire [`KEY_WIDTH-1:0] key_out;

    Parallelizer p_inst(
        .clk(clk),
        .reset(reset),
        .qspi_data(qspi_data_tp),
        .qspi_sending(qspi_sending_tp),
        .qspi_ready(qspi_ready_tp),
        .prog(prog_tp),
        .encrypters_data(encrypters_data_pe),
        .encrypters_key_rotation(encrypters_key_rotation_pe),
        .encrypters_program(encrypters_program_pe),
        .encrypters_data_ready(encrypters_data_ready_pe),
        .encrypters_ready(encrypters_ready_pe),
        .state_out(state_out_p),
        .key_out(key_out)
    );

    // Encrypter e_inst0(
    //     .clk(clk),
    //     .reset(reset),
    //     .dataIn(encrypters_data_pe[0]),
    //     .rot_offset(encrypters_key_rotation_pe[0]),
    //     .dataRdyIn(encrypters_ready_pe[0]),
    //     .cap(encrypters_capture_ec[0]),
    // );

    reg [3:0] spi_data_values[255:0];
    reg [3:0] encrypters_delays [`NUM_ENCRYPTERS-1:0];
    integer fd, i, j;

    initial begin
        //fill spi_data_values with data from file
        fd = $fopen("./Constants/qspi_data.csv", "r");
        if (fd == -1) begin
            $display("Error opening file!");
            $finish;  // Exit simulation on error
        end
        for (i = 0; i < 256; i++) begin
            j = $fscanf(fd, "%h", spi_data_values[i]);
        end
        $fclose(fd);
        $display(spi_data_values[0]);

        for (j = 0; j < `NUM_ENCRYPTERS-1; j = j + 1) begin
            encrypters_delays[j] = 0;
        end
    end

    initial begin
        $dumpfile("TopLevel/top_level.vcd");
        $dumpvars(0, TopLevel);
        $display("Starting simulation");

        //set data on neg edge, read on the rising
        #2 reset = 1; #2 reset = 0;
        #2 prog_tp = 1; #2 prog_tp = 0;

        while (!qspi_ready_tp);

        #2 qspi_sending_tp = 1;
        for (i = 0; i < `KEY_QSPI_COUNT; i = i + 1) begin
            qspi_data_tp = spi_data_values[i];
            $display("Setting qspi_data to 0x%h", spi_data_values[i]);
            #2;
        end
        qspi_sending_tp = 0;

        #4 $finish;
    end

    always begin
        #1 clk = ~clk;
    end

endmodule

Icarus-Verliog-testing/TopLevel/top_level.vcd
$date
	Fri May 17 12:32:23 2024
$end
$version
	Icarus Verilog
$end
$timescale
	1s
$end
$scope module TopLevel $end
$var wire 2 ! encrypters_ready_pe [1:0] $end
$var wire 3 " state_out_p [2:0] $end
$var wire 1 # qspi_ready_tp $end
$var wire 32 $ key_out [31:0] $end
$var wire 2 % encrypters_program_pe [1:0] $end
$var wire 5 & encrypters_key_rotation_pe [4:0] $end
$var wire 2 ' encrypters_data_ready_pe [1:0] $end
$var wire 32 ( encrypters_data_pe [31:0] $end
$var reg 1 ) clk $end
$var reg 1 * prog_tp $end
$var reg 4 + qspi_data_tp [3:0] $end
$var reg 1 , qspi_ready_ct $end
$var reg 1 - qspi_sending_tp $end
$var reg 1 . reset $end
$var integer 32 / fd [31:0] $end
$var integer 32 0 i [31:0] $end
$var integer 32 1 j [31:0] $end
$scope module p_inst $end
$var wire 1 ) clk $end
$var wire 2 2 encrypters_ready [1:0] $end
$var wire 1 * prog $end
$var wire 4 3 qspi_data [3:0] $end
$var wire 1 - qspi_sending $end
$var wire 1 . reset $end
$var reg 4 4 encrypter_data_index [3:0] $end
$var reg 32 5 encrypter_data_packet [31:0] $end
$var reg 2 6 encrypter_index [1:0] $end
$var reg 32 7 encrypters_data [31:0] $end
$var reg 2 8 encrypters_data_ready [1:0] $end
$var reg 5 9 encrypters_key_rotation [4:0] $end
$var reg 2 : encrypters_program [1:0] $end
$var reg 32 ; key [31:0] $end
$var reg 1 < key_encrypter_index $end
$var reg 4 = key_index [3:0] $end
$var reg 32 > key_out [31:0] $end
$var reg 5 ? key_rotation [4:0] $end
$var reg 1 # qspi_ready $end
$var reg 3 @ state [2:0] $end
$var reg 3 A state_out [2:0] $end
$upscope $end
$upscope $end
$enddefinitions $end
$comment Show the parameter values. $end
$dumpall
$end
#0
$dumpvars
b0 A
b0 @
bx ?
b0 >
b0 =
x<
b0 ;
b0 :
bx 9
bx 8
bx 7
bx 6
bx 5
bx 4
b0 3
bz 2
b1 1
b100000000 0
b10000000000000000000000000000011 /
0.
0-
0,
b0 +
0*
0)
bx (
bx '
bx &
b0 %
b0 $
0#
b0 "
bz !
$end
#1
1)
#2
1#
0)
1.
#3
1)
#4
0)
0.
#5
1)
#6
b1 "
b1 A
b1 @
0)
1*
#7
1)
#8
0)
0*
#9
1)
#10
b10 "
b10 A
b10 @
0)
b1101 +
b1101 3
b0 0
1-
#11
b1 =
b1101 $
b1101 >
b1101 ;
1)
#12
0)
b1 +
b1 3
b1 0
#13
b10 =
b11101 $
b11101 >
b11101 ;
1)
#14
0)
b1010 +
b1010 3
b10 0
#15
b11 =
b101000011101 $
b101000011101 >
b101000011101 ;
1)
#16
0)
b11 0
#17
b100 =
b1010101000011101 $
b1010101000011101 >
b1010101000011101 ;
1)
#18
0)
b11 +
b11 3
b100 0
#19
b101 =
b111010101000011101 $
b111010101000011101 >
b111010101000011101 ;
1)
#20
0)
b10 +
b10 3
b101 0
#21
b110 =
b1000111010101000011101 $
b1000111010101000011101 >
b1000111010101000011101 ;
1)
#22
0)
b1011 +
b1011 3
b110 0
#23
b111 =
b1011001000111010101000011101 $
b1011001000111010101000011101 >
b1011001000111010101000011101 ;
1)
#24
0)
b1 +
b1 3
b111 0
#25
0#
0<
b11 "
b11 A
b11 @
b1000 =
b11011001000111010101000011101 $
b11011001000111010101000011101 >
b11011001000111010101000011101 ;
1)
#26
b100 "
b100 A
b100 @
1<
b11 %
b11 :
b11011001000111010101000011101 (
b11011001000111010101000011101 7
b10 6
0)
0-
b1000 0
#27
b0 %
b0 :
1#
b10 6
b0 "
b0 A
b0 @
1)
