Icarus-Verliog-testing/Constants/constants.vh
//DEFINE CONSTANTS
// `define KEY_WIDTH 16 // width of the key. In multiples of 4.
// `define KEY_QSPI_COUNT `KEY_WIDTH/4 // number of QSPI transactions per key sent in LSB. 
// `define KEY_QSPI_COUNT_REG $clog2(`KEY_QSPI_COUNT+1) // register size required to count the current QSPI transaction of the key + 1. log2(`KEY_QSPI_COUNT+1)

`define ENCRYPTER_WIDTH 32 // width of the bus between the Paralellizer and Encrypter, and the Encrypter and Collector. In multiples of 4.
`define ENCRYPTER_WIDTH_COUNT_REG $clog2(`ENCRYPTER_WIDTH+1) // register size required to count the current bit of the encrypter bus + 1. log2(`ENCRYPTER_WIDTH+1). (Verilog doesn't like me so i need a for loop)
`define ENCRYPTER_QSPI_COUNT `ENCRYPTER_WIDTH/4 // number of QSPI transactions per Encrypter.
`define ENCRYPTER_QSPI_COUNT_REG $clog2(`ENCRYPTER_QSPI_COUNT+1) // register size required to count the current QSPI transaction of the Encrypter + 1. log2(`ENCRYPTER_QSPI_COUNT+1)

`define KEY_ROTATION_WIDTH $clog2(`ENCRYPTER_WIDTH) // width of the key rotation bus between Paralellizer and Encrypter. log2(`KEY_WIDTH)
`define KEY_ROTATION_WIDTH_COUNT_REG $clog2(`KEY_ROTATION_WIDTH+1) // register size required to count the current bit of the key rotation bus + 1. log2(`KEY_ROTATION_WIDTH+1). (Verilog doesn't like me so i need a for loop)

// `define KEY_ENCRYPTER_COUNT `KEY_WIDTH/`ENCRYPTER_WIDTH // number of Encrypters transactions per key. `KEY_WIDTH/`ENCRYPTER_WIDTH
// `define KEY_ENCRYPTER_COUNT_REG $clog2(`KEY_ENCRYPTER_COUNT+1) // register size required to count the current Encrypter transaction of the key + 1. log2(`KEY_ENCRYPTER_COUNT+1)

`define NUM_ENCRYPTERS 2 // number of Encrypters
`define NUM_ENCRYPTERS_REG $clog2(`NUM_ENCRYPTERS+1) // register size required to count the current Encrypter + 1. log2(`NUM_ENCRYPTERS+1)

Icarus-Verliog-testing/Collector/collector.sv
`include "./Constants/constants.vh"
`define IDLE 2'b00
`define WAITING 2'b01
`define CAPTURING 2'b10
`define SENDING 2'b11


module Collector(
    input wire clk,
    input wire reset,
    //QSPI
    
    output reg [3:0] qspi_data,
    output reg qspi_sending = 0,
    input wire qspi_ready,
    
    //To encrypters
    input wire [`ENCRYPTER_WIDTH-1:0] encrypters_data [`NUM_ENCRYPTERS-1:0],
    input wire [`NUM_ENCRYPTERS-1:0] encrypters_data_ready,
    output reg [`NUM_ENCRYPTERS-1:0] encrypters_capture

    //Watchers
    // output reg [1:0] state_out,
    // output reg [`ENCRYPTER_WIDTH-1:0] encrypter_data_packe_out,
    
    // output reg [`ENCRYPTER_WIDTH_COUNT_REG-1:0] encrypter_data_subindex_out,
    // output reg [`NUM_ENCRYPTERS_REG-1:0] encrypter_index_out,
    // output reg [`ENCRYPTER_QSPI_COUNT_REG-1:0] encrypter_data_index_out    
);

    reg [1:0] state = `IDLE;

    reg [`ENCRYPTER_WIDTH-1:0] encrypter_data_packet;
    reg [`ENCRYPTER_WIDTH_COUNT_REG-1:0] encrypter_data_subindex;

    reg [`NUM_ENCRYPTERS_REG-1:0] encrypter_index;

    reg [`ENCRYPTER_QSPI_COUNT_REG-1:0] encrypter_data_index;

    initial begin
        encrypters_capture = 0;
        // assign state_out = state;
        // assign encrypter_data_packe_out = encrypter_data_packet;
        // assign encrypter_data_subindex_out = encrypter_data_subindex;
        // assign encrypter_index_out = encrypter_index;
        // assign encrypter_data_index_out = encrypter_data_index;
    end

    always @(posedge clk) begin

        if (reset) begin
            state <= `WAITING;
            encrypter_index <= 0;
        end

        if (state == `WAITING) begin
            if(encrypters_data_ready[encrypter_index]) begin
                encrypter_data_packet = encrypters_data[encrypter_index];
                state <= `CAPTURING;
                encrypter_data_index = 0;
            end else begin
                qspi_sending = 0;
            end
        end

    end

    always @(negedge clk) begin
        encrypters_capture <= 0;

        if (state == `CAPTURING) begin
            encrypters_capture[encrypter_index] <= 1;
            state = `SENDING;
        end

        if (state == `SENDING) begin
            if(qspi_ready) begin
                qspi_sending = 1;
                qspi_data[0] = encrypter_data_packet[encrypter_data_index*4];
                qspi_data[1] = encrypter_data_packet[encrypter_data_index*4+1]; 
                qspi_data[2] = encrypter_data_packet[encrypter_data_index*4+2];
                qspi_data[3] = encrypter_data_packet[encrypter_data_index*4+3];  
                encrypter_data_index = encrypter_data_index + 1;   
                if(encrypter_data_index == `ENCRYPTER_QSPI_COUNT) begin
                        encrypter_index = encrypter_index + 1;
                        if (encrypter_index == `NUM_ENCRYPTERS) begin
                            encrypter_index = 0;
                        end
                    state <= `WAITING; 
                end           
            end else qspi_sending = 0;   
        end     
    end 


endmodule

Icarus-Verliog-testing/Encrypter/encrypter.sv
`include "./Constants/constants.vh"

`define IDLE 3'b000
`define READING_KEY 3'b001
`define WAITING_RDY_DATA_IN 3'b010
`define READING_DATA_ENCRYPTING 3'b011
`define SENDING_DATA 3'b100
`define ACKNOWLEDGING_CAPTURE 3'b101

module Encrypter (
    input wire clk,
    input wire reset,

    // Parallelizer <-> Encrypter signals
    input wire [`ENCRYPTER_WIDTH-1:0] data_in_p,
    input wire [`KEY_ROTATION_WIDTH-1:0] key_rotation_p,
    input wire prog_p,
    input wire data_ready_in_p,
    output reg ready_p,

    // Encrypter <-> Collector signals
    output reg [`ENCRYPTER_WIDTH-1:0] data_out_c,
    output reg data_ready_out_c,
    input wire capture_c
);

    reg [2:0] state;
    reg [`ENCRYPTER_WIDTH-1:0] keyRotated;
    reg [`ENCRYPTER_WIDTH-1:0] data_in_store;
    reg [`ENCRYPTER_WIDTH-1:0] keyOrigin;
    reg [`KEY_ROTATION_WIDTH:0] offset;

    initial begin
        state <= `IDLE;
        ready_p = 0;
        data_ready_out_c = 0;
        data_out_c = 0;
        data_in_store = 0;
        keyOrigin = 0;
        keyRotated = 0;
        offset = 0;
    end

    always @(posedge clk) begin
        if (reset) begin
            state <= `IDLE;
            ready_p = 0;
            data_ready_out_c = 0;
            data_out_c = 0;
            data_in_store = 0;
            keyOrigin = 0;
            keyRotated = 0;
            offset = 0;
        end
        
        case (state)

            `IDLE: begin
                if (prog_p) state <= `READING_KEY;
            end

            `WAITING_RDY_DATA_IN: begin
                if (data_ready_in_p) state <= `READING_DATA_ENCRYPTING;
            end

            `READING_KEY: begin
                keyOrigin = data_in_p;
                state = `WAITING_RDY_DATA_IN;
            end

            `READING_DATA_ENCRYPTING: begin
                data_in_store = data_in_p;
                offset = key_rotation_p;
                ready_p = 0;
                keyRotated = (keyOrigin << offset) | (keyOrigin >> (`ENCRYPTER_WIDTH-offset));
                state = `SENDING_DATA;
            end

            `SENDING_DATA: begin
                if (capture_c)
                state <= `ACKNOWLEDGING_CAPTURE;
            end

        endcase
    end

    always @(negedge clk) begin
        case (state)
            `SENDING_DATA: begin
                data_out_c = data_in_store ^ keyRotated;
                data_ready_out_c = 1;
            end

            `WAITING_RDY_DATA_IN: begin
                if (~ready_p) ready_p = 1;
            end

            `ACKNOWLEDGING_CAPTURE: begin
                state <= `WAITING_RDY_DATA_IN;
                data_ready_out_c = 0;
                ready_p = 1;
            end
        endcase
    end
endmodule


module EncrypterADV (
    input wire clk,
    input wire reset,

    // Parallelizer <-> Encrypter signals
    input wire [`ENCRYPTER_WIDTH-1:0] data_in_p,
    input wire [`KEY_ROTATION_WIDTH-1:0] key_rotation_p,
    input wire prog_p,
    input wire data_ready_in_p,
    output reg ready_p,

    // Encrypter <-> Collector signals
    output reg [`ENCRYPTER_WIDTH-1:0] data_out_c,
    output reg data_ready_out_c,
    input wire capture_c
);

    reg [2:0] state;
    reg [`ENCRYPTER_WIDTH-1:0] keyRotated;
    reg [64-1:0] keySquared;
    reg [`ENCRYPTER_WIDTH-1:0] keyNew;
    reg [`ENCRYPTER_WIDTH-1:0] keyMod;
    reg [`ENCRYPTER_WIDTH-1:0] data_in_store;
    reg [`ENCRYPTER_WIDTH-1:0] keyOrigin;
    reg [`KEY_ROTATION_WIDTH:0] offset;
    reg [`ENCRYPTER_WIDTH-1:0] xorOffset;

    initial begin
        state <= `IDLE;
        ready_p = 0;
        data_ready_out_c = 0;
        data_out_c = 0;
        data_in_store = 0;
        keyNew = 0;
        keyRotated = 0;
        keyOrigin = 0;
        keySquared = 0;
        keyMod = 0;
        offset = 0;
    end

    always @(posedge clk) begin
        if (reset) begin
            state <= `IDLE;
            ready_p = 0;
            data_ready_out_c = 0;
            data_out_c = 0;
            data_in_store = 0;
            keyNew = 0;
            keyRotated = 0;
            keyOrigin = 0;
            keySquared = 0;
            keyMod = 0;
            offset = 0;
        end
        
        case (state)

            `IDLE: begin
                if (prog_p) state <= `READING_KEY;
            end

            `WAITING_RDY_DATA_IN: begin
                if (data_ready_in_p) state <= `READING_DATA_ENCRYPTING;
            end

            `READING_KEY: begin
                keyOrigin = data_in_p;
                state = `WAITING_RDY_DATA_IN;
            end

            `READING_DATA_ENCRYPTING: begin
                data_in_store = data_in_p;
                offset = key_rotation_p;
                ready_p = 0;
                xorOffset = (keyOrigin & 5'b11111)^offset;
                keyNew = keyOrigin^(xorOffset<<27);
                keyRotated = (keyNew << xorOffset) | (keyNew >> (`ENCRYPTER_WIDTH-xorOffset));
                keySquared = keyRotated*keyRotated;
                keyMod = keySquared%4294967311;
                state = `SENDING_DATA;
            end

            `SENDING_DATA: begin
                if (capture_c)
                state <= `ACKNOWLEDGING_CAPTURE;
            end

        endcase
    end

    always @(negedge clk) begin
        case (state)
            `SENDING_DATA: begin
                data_out_c = data_in_store ^ keyMod;
                data_ready_out_c = 1;
            end

            `WAITING_RDY_DATA_IN: begin
                if (~ready_p) ready_p = 1;
            end

            `ACKNOWLEDGING_CAPTURE: begin
                state <= `WAITING_RDY_DATA_IN;
                data_ready_out_c = 0;
                ready_p = 1;
            end
        endcase
    end
endmodule

Icarus-Verliog-testing/Parallelizer/parallelizer.sv
`include "./Constants/constants.vh"

`define STATE_IDLE 3'b000
`define STATE_PROGRAMMING 3'b001
`define STATE_RECEIVING_KEY 3'b010
`define STATE_PROGRAMMING_ENCRYPTERS 3'b011
`define STATE_WAITING_FOR_READY_ENCRYPTERS 3'b100
`define STATE_ENCRYPTING 3'b101

module Parallelizer (
    input wire clk,
    input wire reset,
    //QSPI
    input wire [3:0] qspi_data,
    input wire qspi_sending,
    output reg qspi_ready,
    //Program
    input wire prog,
    //To encrypters
    output reg [`ENCRYPTER_WIDTH-1:0] encrypters_data,
    output reg [`KEY_ROTATION_WIDTH-1:0] encrypters_key_rotation,
    output reg [`NUM_ENCRYPTERS-1:0] encrypters_program,
    output reg [`NUM_ENCRYPTERS-1:0] encrypters_data_ready,
    input wire [`NUM_ENCRYPTERS-1:0] encrypters_ready
    //Watchers
    // output reg [2:0] state_out,
    // output reg [`ENCRYPTER_WIDTH-1:0] key_out
    // output reg [`KEY_ROTATION_WIDTH-1:0] key_rotation_out,
    // output reg [`ENCRYPTER_QSPI_COUNT_REG-1:0] key_index_out,
    // output reg [`ENCRYPTER_WIDTH-1:0] encrypter_data_packet_out,
    // output reg [`ENCRYPTER_QSPI_COUNT_REG-1:0] encrypter_data_index_out,
    // output reg [`NUM_ENCRYPTERS_REG-1:0] encrypter_index_out
);

reg [2:0] state = `STATE_IDLE;
reg [`ENCRYPTER_QSPI_COUNT_REG-1:0] key_index;
reg [`KEY_ROTATION_WIDTH-1:0] key_rotation;

reg [`ENCRYPTER_WIDTH-1:0] encrypter_data_packet;

reg [`ENCRYPTER_QSPI_COUNT_REG-1:0] encrypter_data_index;
reg [`NUM_ENCRYPTERS_REG-1:0] encrypter_index;
integer i;

initial begin
    // assign state_out = state;
    // assign key_out = encrypter_data_packet;
    // assign key_rotation_out = key_rotation;
    // assign key_index_out = key_index;
    // assign encrypter_data_packet_out = encrypter_data_packet;
    // assign encrypter_data_index_out = encrypter_data_index;
    // assign encrypter_index_out = encrypter_index;

    qspi_ready = 1'b0;
    encrypters_program = 0;
    encrypter_data_packet = 0;
    key_index = `ENCRYPTER_QSPI_COUNT;
end

//read on positive
always @(posedge clk) begin

    if (reset) begin
        state <= `STATE_IDLE;
        qspi_ready = 1'b1;
    end

    case (state)

        `STATE_IDLE: begin 
            if (qspi_sending) begin
                state <= `STATE_ENCRYPTING;
                encrypter_index = 0;
                encrypter_data_index = `ENCRYPTER_QSPI_COUNT;
                encrypters_data_ready = 0;
                key_rotation = 0;
            end
            if (prog) begin
                state <= `STATE_PROGRAMMING;
                qspi_ready = 1'b1;
                key_index = `ENCRYPTER_QSPI_COUNT;
            end
        end

        `STATE_PROGRAMMING: if (qspi_sending) state <= `STATE_RECEIVING_KEY;

        `STATE_RECEIVING_KEY: begin 
            if (~qspi_sending) begin
                state = `STATE_IDLE;
            end else begin
                key_index = key_index - 1;
                encrypter_data_packet[key_index*4] = qspi_data[0];
                encrypter_data_packet[key_index*4+1] = qspi_data[1];
                encrypter_data_packet[key_index*4+2] = qspi_data[2];
                encrypter_data_packet[key_index*4+3] = qspi_data[3];
                if (key_index == 0) begin
                    state = `STATE_PROGRAMMING_ENCRYPTERS;
                    qspi_ready = 1'b0;
                end
            end
        end

        `STATE_WAITING_FOR_READY_ENCRYPTERS: begin
            if (& encrypters_ready) begin
                state = `STATE_IDLE;
                encrypter_index = 0;
            end
        end

        `STATE_ENCRYPTING: begin
            if (~qspi_sending) begin
                state = `STATE_IDLE;
            end else begin
                //read spi data
                encrypter_data_index = encrypter_data_index - 1;
                encrypter_data_packet[encrypter_data_index*4] = qspi_data[0];
                encrypter_data_packet[encrypter_data_index*4+1] = qspi_data[1];
                encrypter_data_packet[encrypter_data_index*4+2] = qspi_data[2];
                encrypter_data_packet[encrypter_data_index*4+3] = qspi_data[3];
            end
        end

        default:;

    endcase
end

//write on negative
always @(negedge clk) begin
    case (state)

        `STATE_IDLE: begin    
            qspi_ready = 1'b1;
            encrypters_program = 0;
        end

        `STATE_PROGRAMMING_ENCRYPTERS: begin
            encrypters_data = encrypter_data_packet;
            for (encrypter_index = 0; encrypter_index < `NUM_ENCRYPTERS; encrypter_index = encrypter_index + 1) begin
                encrypters_program[encrypter_index] = 1'b1;
            end
            state = `STATE_WAITING_FOR_READY_ENCRYPTERS;
        end

        `STATE_ENCRYPTING: begin
            //keep ecrypter data index high for only 1 posedge clock cycle
            if (encrypter_index == 0) begin
                if (encrypters_data_ready[`NUM_ENCRYPTERS-1]) encrypters_data_ready[`NUM_ENCRYPTERS-1] = 0;
            end else begin
                if (encrypters_data_ready[encrypter_index-1]) encrypters_data_ready[encrypter_index-1] = 0;
            end

            if (encrypter_data_index == 0) begin
                //when packet full, send to encrypters
                encrypter_data_index = `ENCRYPTER_QSPI_COUNT;
                
                //check if encrypter is ready for new data
                if (encrypters_ready[encrypter_index]) begin
                    //put packet on encrypter bus
                    encrypters_data = encrypter_data_packet;
                    //put key rot on encrypter bus
                    encrypters_key_rotation = key_rotation;

                    //signal data is ready
                    encrypters_data_ready[encrypter_index] = 1'b1;

                    //move to next encrypter
                    encrypter_index = encrypter_index + 1;
                    if (encrypter_index == `NUM_ENCRYPTERS) encrypter_index = 0;

                    //move to next key rotation
                    key_rotation = key_rotation + 1;
                    if (key_rotation == `ENCRYPTER_WIDTH) key_rotation = 0;

                    //ready for more data as current data has been written
                    qspi_ready = 1'b1;
                end else begin
                    //if encrypter is not ready, wait for it
                    qspi_ready = 1'b0;
                end
            end
        end

        default:;

    endcase
end

endmodule

Icarus-Verliog-testing/TopLevel/top_level.sv
`timescale 10ns / 10ns
`include "./Constants/constants.vh"
`include "./Parallelizer/parallelizer.sv"
`include "./Encrypter/encrypter.sv"
`include "./Collector/collector.sv"

`define ENCRYPT 1
`define MAX_BYTES 4*1


module TopLevel();

    // Toplevel signals
    reg clk = 0;
    reg reset = 0;

    // Toplevel <-> Parallelizer signals
    reg [3:0] qspi_data_tp = 0;
    reg qspi_sending_tp = 0;
    wire qspi_ready_tp;
    reg prog_tp = 0;

    // Parallelizer <-> Encrypter signals
    wire [`ENCRYPTER_WIDTH-1:0] encrypters_data_pe;
    wire [`KEY_ROTATION_WIDTH-1:0] encrypters_key_rotation_pe;
    wire [`NUM_ENCRYPTERS-1:0] encrypters_program_pe;
    wire [`NUM_ENCRYPTERS-1:0] encrypters_data_ready_pe;
    wire [`NUM_ENCRYPTERS-1:0] encrypters_ready_pe;

    // Encrypter <-> Collector signals
    wire [`ENCRYPTER_WIDTH-1:0] encrypters_data_ec [`NUM_ENCRYPTERS-1:0];
    wire [`NUM_ENCRYPTERS-1:0] encrypters_data_ready_ec;
    wire [`NUM_ENCRYPTERS-1:0] encrypters_capture_ec;

    // Collector <-> Toplevel signals
    wire [3:0] qspi_data_ct;
    wire qspi_sending_ct;
    reg qspi_ready_ct = 1;

    // Watchers
    // wire [2:0] state_out_p;
    wire [`ENCRYPTER_WIDTH-1:0] key_out;
    wire [`ENCRYPTER_WIDTH-1:0] encrypters_data_ec0;
    wire [`ENCRYPTER_WIDTH-1:0] encrypters_data_ec1;

    assign encrypters_data_ec0 = encrypters_data_ec[0];
    assign encrypters_data_ec1 = encrypters_data_ec[1];

    Parallelizer p_inst(
        .clk(clk),
        .reset(reset),
        .qspi_data(qspi_data_tp),
        .qspi_sending(qspi_sending_tp),
        .qspi_ready(qspi_ready_tp),
        .prog(prog_tp),
        .encrypters_data(encrypters_data_pe),
        .encrypters_key_rotation(encrypters_key_rotation_pe),
        .encrypters_program(encrypters_program_pe),
        .encrypters_data_ready(encrypters_data_ready_pe),
        .encrypters_ready(encrypters_ready_pe)
        // .state_out(state_out_p),
        // .key_out(key_out)
    );

    generate
        genvar e;
        for (e = 0; e < `NUM_ENCRYPTERS; e = e + 1) begin : encrypter_loop
            EncrypterADV e_inst (
                .clk(clk),
                .reset(reset),
                .data_in_p(encrypters_data_pe),
                .key_rotation_p(encrypters_key_rotation_pe),
                .prog_p(encrypters_program_pe[e]),
                .data_ready_in_p(encrypters_data_ready_pe[e]),
                .ready_p(encrypters_ready_pe[e]),
                .data_out_c(encrypters_data_ec[e]),
                .data_ready_out_c(encrypters_data_ready_ec[e]),
                .capture_c(encrypters_capture_ec[e])
            );
        end
    endgenerate

    Collector c_inst(
        .clk(clk),
        .reset(reset),
        .qspi_data(qspi_data_ct),
        .qspi_sending(qspi_sending_ct),
        .qspi_ready(qspi_ready_ct),
        .encrypters_data(encrypters_data_ec),
        .encrypters_data_ready(encrypters_data_ready_ec),
        .encrypters_capture(encrypters_capture_ec)
    );

    reg [31:0] key = 32'hB4352B93;
    integer fd_read, fd_write, fd_csv, i, j, bytes_sent = 0, packets;
    reg [7:0] char_read, char_write;
    logic char_write_progress = 0;

    initial begin
        fd_csv = $fopen("./TopLevel/encrypter_output.csv", "w");
        if (fd_csv == -1) begin
            $display("Error data file!");
            $finish;  // Exit simulation on error
        end
        $fwrite(fd_csv, "#Blocks,Test1\n");
    end

    initial begin
        $dumpfile("TopLevel/top_level.vcd");
        $dumpvars(0, TopLevel);

        for (packets = 1; packets <= 2**5; packets = packets * 2) begin
            $display("Starting simulation with %d packets", packets);

            //fill spi_data_values with data from file
            if (`ENCRYPT) begin
                fd_read = $fopen("../data/unencrypted/starwarsscript.txt", "r");
            end else begin
                fd_read = $fopen("./TopLevel/encrypted_message.enc", "r");
            end

            if (fd_read == -1) begin
                $display("Error data file!");
                $finish;  // Exit simulation on error
            end

            if (`ENCRYPT) begin
                fd_write = $fopen("./TopLevel/encrypted_message.enc", "w");
            end else begin
                fd_write = $fopen("./TopLevel/decrypted_message.txt", "w");
            end
            if (fd_write == -1) begin
                $display("Error encrypted data file!");
                $finish;  // Exit simulation on error
            end


            //set data on neg edge, read on the rising
            #2 reset = 1; #2 reset = 0;
            #2 prog_tp = 1; #2 prog_tp = 0;

            //send key
            while (!qspi_ready_tp) #2;
            #2 qspi_sending_tp = 1; #2
            for (i = `ENCRYPTER_QSPI_COUNT-1; i > -1; i = i - 1) begin
                qspi_data_tp[0] = key[i*4];
                qspi_data_tp[1] = key[i*4+1];
                qspi_data_tp[2] = key[i*4+2];
                qspi_data_tp[3] = key[i*4+3];
                #2;
                // $display("[KEY] 0x%x", qspi_data_tp);
            end
            qspi_sending_tp = 0;

            //send data
            bytes_sent = 0;
            while (!qspi_ready_tp) #2;
            #2 qspi_sending_tp = 1; #2
            while (!$feof(fd_read) && (bytes_sent < packets*4)) begin
                char_read = $fgetc(fd_read);
                // $display("[RAW] 0x%x", char_read);

                while (!qspi_ready_tp) #2;
                qspi_data_tp = char_read[7:4]; #2;
                // $display("[DAT] 0x%x", qspi_data_tp);

                while (!qspi_ready_tp) #2;
                qspi_data_tp = char_read[3:0]; #2;
                // $display("[DAT] 0x%x", qspi_data_tp);

                bytes_sent = bytes_sent + 1;
                // $display("Bytes sent: %d", bytes_sent);
            end
            #2 qspi_sending_tp = 0; #10;

            while (qspi_sending_ct) #2;
            $fclose(fd_read); $fclose(fd_write);
            $display("Simulation time: %.8f s", $time/(10.0**8));
            $fwrite(fd_csv, "%d,%.8f\n", packets, $time/(10.0**8));
        end
        $fclose(fd_csv); $finish;
    end

    always begin
        #1 clk = ~clk;
        if (clk) begin
            if (qspi_sending_ct) begin
                if (char_write_progress == 0) begin
                    char_write_progress = 1;
                    char_write[7:4] = qspi_data_ct;
                end else begin
                    char_write_progress = 0;
                    char_write[3:0] = qspi_data_ct;
                    // $display("[ENC] 0x%x", char_write);
                    j = $fputc(char_write, fd_write);
                end
            end
        end
    end

endmodule

Icarus-Verliog-testing/TopLevel/top_level.vcd
$date
	Sun May 19 20:56:49 2024
$end
$version
	Icarus Verilog
$end
$timescale
	10ns
$end
$scope module TopLevel $end
$var wire 32 ! encrypters_data_ec0 [31:0] $end
$var wire 32 " encrypters_data_ec1 [31:0] $end
$var wire 1 # qspi_sending_ct $end
$var wire 1 $ qspi_ready_tp $end
$var wire 4 % qspi_data_ct [3:0] $end
$var wire 2 & encrypters_ready_pe [1:0] $end
$var wire 2 ' encrypters_program_pe [1:0] $end
$var wire 5 ( encrypters_key_rotation_pe [4:0] $end
$var wire 2 ) encrypters_data_ready_pe [1:0] $end
$var wire 2 * encrypters_data_ready_ec [1:0] $end
$var wire 32 + encrypters_data_pe [31:0] $end
$var wire 2 , encrypters_capture_ec [1:0] $end
$var reg 8 - char_read [7:0] $end
$var reg 8 . char_write [7:0] $end
$var reg 1 / char_write_progress $end
$var reg 1 0 clk $end
$var reg 32 1 key [31:0] $end
$var reg 1 2 prog_tp $end
$var reg 4 3 qspi_data_tp [3:0] $end
$var reg 1 4 qspi_ready_ct $end
$var reg 1 5 qspi_sending_tp $end
$var reg 1 6 reset $end
$var integer 32 7 bytes_sent [31:0] $end
$var integer 32 8 fd_csv [31:0] $end
$var integer 32 9 fd_read [31:0] $end
$var integer 32 : fd_write [31:0] $end
$var integer 32 ; i [31:0] $end
$var integer 32 < j [31:0] $end
$var integer 32 = packets [31:0] $end
$scope begin encrypter_loop[0] $end
$var parameter 2 > e $end
$scope module e_inst $end
$var wire 1 ? capture_c $end
$var wire 1 0 clk $end
$var wire 1 @ data_ready_in_p $end
$var wire 1 A prog_p $end
$var wire 1 6 reset $end
$var wire 5 B key_rotation_p [4:0] $end
$var wire 32 C data_in_p [31:0] $end
$var reg 32 D data_in_store [31:0] $end
$var reg 32 E data_out_c [31:0] $end
$var reg 1 F data_ready_out_c $end
$var reg 32 G keyMod [31:0] $end
$var reg 32 H keyNew [31:0] $end
$var reg 32 I keyOrigin [31:0] $end
$var reg 32 J keyRotated [31:0] $end
$var reg 64 K keySquared [63:0] $end
$var reg 6 L offset [5:0] $end
$var reg 1 M ready_p $end
$var reg 3 N state [2:0] $end
$var reg 32 O xorOffset [31:0] $end
$upscope $end
$upscope $end
$scope begin encrypter_loop[1] $end
$var parameter 2 P e $end
$scope module e_inst $end
$var wire 1 Q capture_c $end
$var wire 1 0 clk $end
$var wire 1 R data_ready_in_p $end
$var wire 1 S prog_p $end
$var wire 1 6 reset $end
$var wire 5 T key_rotation_p [4:0] $end
$var wire 32 U data_in_p [31:0] $end
$var reg 32 V data_in_store [31:0] $end
$var reg 32 W data_out_c [31:0] $end
$var reg 1 X data_ready_out_c $end
$var reg 32 Y keyMod [31:0] $end
$var reg 32 Z keyNew [31:0] $end
$var reg 32 [ keyOrigin [31:0] $end
$var reg 32 \ keyRotated [31:0] $end
$var reg 64 ] keySquared [63:0] $end
$var reg 6 ^ offset [5:0] $end
$var reg 1 _ ready_p $end
$var reg 3 ` state [2:0] $end
$var reg 32 a xorOffset [31:0] $end
$upscope $end
$upscope $end
$scope module c_inst $end
$var wire 1 0 clk $end
$var wire 2 b encrypters_data_ready [1:0] $end
$var wire 1 4 qspi_ready $end
$var wire 1 6 reset $end
$var reg 4 c encrypter_data_index [3:0] $end
$var reg 32 d encrypter_data_packet [31:0] $end
$var reg 2 e encrypter_index [1:0] $end
$var reg 2 f encrypters_capture [1:0] $end
$var reg 4 g qspi_data [3:0] $end
$var reg 1 # qspi_sending $end
$var reg 2 h state [1:0] $end
$upscope $end
$scope module p_inst $end
$var wire 1 0 clk $end
$var wire 2 i encrypters_ready [1:0] $end
$var wire 1 2 prog $end
$var wire 4 j qspi_data [3:0] $end
$var wire 1 5 qspi_sending $end
$var wire 1 6 reset $end
$var reg 4 k encrypter_data_index [3:0] $end
$var reg 32 l encrypter_data_packet [31:0] $end
$var reg 2 m encrypter_index [1:0] $end
$var reg 32 n encrypters_data [31:0] $end
$var reg 2 o encrypters_data_ready [1:0] $end
$var reg 5 p encrypters_key_rotation [4:0] $end
$var reg 2 q encrypters_program [1:0] $end
$var reg 4 r key_index [3:0] $end
$var reg 5 s key_rotation [4:0] $end
$var reg 1 $ qspi_ready $end
$var reg 3 t state [2:0] $end
$upscope $end
$upscope $end
$enddefinitions $end
$comment Show the parameter values. $end
$dumpall
b1 P
b0 >
$end
#0
$dumpvars
b0 t
bx s
b1000 r
b0 q
bx p
bx o
bx n
bx m
b0 l
bx k
b0 j
b0 i
b0 h
bx g
b0 f
bx e
bx d
bx c
b0 b
bx a
b0 `
0_
b0 ^
b0 ]
b0 \
b0 [
b0 Z
b0 Y
0X
b0 W
b0 V
bx U
bx T
0S
xR
0Q
bx O
b0 N
0M
b0 L
b0 K
b0 J
b0 I
b0 H
b0 G
0F
b0 E
b0 D
bx C
bx B
0A
x@
0?
b1 =
bx <
bx ;
b10000000000000000000000000000101 :
b10000000000000000000000000000100 9
b10000000000000000000000000000011 8
b0 7
06
05
14
b0 3
02
b10110100001101010010101110010011 1
00
0/
bx .
bx -
b0 ,
bx +
b0 *
bx )
bx (
b0 '
b0 &
bx %
0$
0#
b0 "
b0 !
$end
#1
10
#2
1$
00
16
#3
b0 e
b1 h
10
#4
00
06
#5
10
#6
00
12
#7
b1 t
10
#8
00
02
#9
10
#10
00
15
#11
b10 t
10
#12
00
b1011 3
b1011 j
b111 ;
#13
b10110000000000000000000000000000 l
b111 r
10
#14
00
b100 3
b100 j
b110 ;
#15
b10110100000000000000000000000000 l
b110 r
10
#16
00
b11 3
b11 j
b101 ;
#17
b10110100001100000000000000000000 l
b101 r
10
#18
00
b101 3
b101 j
b100 ;
#19
b10110100001101010000000000000000 l
b100 r
10
#20
00
b10 3
b10 j
b11 ;
#21
b10110100001101010010000000000000 l
b11 r
10
#22
00
b1011 3
b1011 j
b10 ;
#23
b10110100001101010010101100000000 l
b10 r
10
#24
00
b1001 3
b1001 j
b1 ;
#25
b10110100001101010010101110010000 l
b1 r
10
#26
00
b11 3
b11 j
b0 ;
#27
0$
b11 t
b10110100001101010010101110010011 l
b0 r
10
#28
1S
1A
b100 t
b11 '
b11 q
b10 m
b10110100001101010010101110010011 +
b10110100001101010010101110010011 C
b10110100001101010010101110010011 U
b10110100001101010010101110010011 n
00
05
b11111111111111111111111111111111 ;
#29
b1 N
b1 `
10
#30
00
#31
b10 `
b10110100001101010010101110010011 [
b10 N
b10110100001101010010101110010011 I
10
#32
1_
b11 &
b11 i
1M
00
#33
b0 m
b0 t
10
#34
0S
0A
b0 '
b0 q
1$
00
#35
10
#36
00
#37
10
#38
00
15
#39
b101 t
0R
0@
b0 s
b0 )
b0 o
b1000 k
10
#40
00
b101 3
b101 j
b1010011 -
#41
b1010100001101010010101110010011 l
b111 k
10
#42
00
b11 3
b11 j
#43
b1010011001101010010101110010011 l
b110 k
10
#44
00
b101 3
b101 j
b1010100 -
b1 7
#45
b1010011010101010010101110010011 l
b101 k
10
#46
00
b100 3
b100 j
#47
b1010011010101000010101110010011 l
b100 k
10
#48
00
b1000001 -
b10 7
#49
b1010011010101000100101110010011 l
b11 k
10
#50
00
b1 3
b1 j
#51
b1010011010101000100000110010011 l
b10 k
10
#52
00
b101 3
b101 j
b1010010 -
b11 7
#53
b1010011010101000100000101010011 l
b1 k
10
#54
00
b10 3
b10 j
#55
b1010011010101000100000101010010 l
b0 k
10
#56
1@
b1 s
b1 m
b1 )
b1 o
b0 (
b0 B
b0 T
b0 p
b1010011010101000100000101010010 +
b1010011010101000100000101010010 C
b1010011010101000100000101010010 U
b1010011010101000100000101010010 n
b1000 k
00
b100 7
#57
b11 N
b100011010101000100000101010010 l
b111 k
10
#58
0@
b0 )
b0 o
00
05
#59
b0 t
b100 N
b1100010110110000111101001010110 G
b10000101111110100110100001011101011001010000111000000110010001 K
b1011100100110010110000110101001 J
b101100001101010010101110010011 H
b10011 O
b10 &
b10 i
0M
b1010011010101000100000101010010 D
10
#60
b1 *
b1 b
1F
b110001100011000011101100000100 !
b110001100011000011101100000100 E
00
#61
b10 h
b1000 c
b110001100011000011101100000100 d
10
#62
1?
b1 ,
b1 f
b11 %
b11 g
b111 c
1#
b11 h
00
