Icarus-Verliog-testing/Constants/constants.vh
//DEFINE CONSTANTS
// `define KEY_WIDTH 16 // width of the key. In multiples of 4.
// `define KEY_QSPI_COUNT `KEY_WIDTH/4 // number of QSPI transactions per key sent in LSB. 
// `define KEY_QSPI_COUNT_REG $clog2(`KEY_QSPI_COUNT+1) // register size required to count the current QSPI transaction of the key + 1. log2(`KEY_QSPI_COUNT+1)

`define ENCRYPTER_WIDTH 32 // width of the bus between the Paralellizer and Encrypter, and the Encrypter and Collector. In multiples of 4.
`define ENCRYPTER_WIDTH_COUNT_REG $clog2(`ENCRYPTER_WIDTH+1) // register size required to count the current bit of the encrypter bus + 1. log2(`ENCRYPTER_WIDTH+1). (Verilog doesn't like me so i need a for loop)
`define ENCRYPTER_QSPI_COUNT `ENCRYPTER_WIDTH/4 // number of QSPI transactions per Encrypter.
`define ENCRYPTER_QSPI_COUNT_REG $clog2(`ENCRYPTER_QSPI_COUNT+1) // register size required to count the current QSPI transaction of the Encrypter + 1. log2(`ENCRYPTER_QSPI_COUNT+1)

`define KEY_ROTATION_WIDTH $clog2(`ENCRYPTER_WIDTH) // width of the key rotation bus between Paralellizer and Encrypter. log2(`KEY_WIDTH)
`define KEY_ROTATION_WIDTH_COUNT_REG $clog2(`KEY_ROTATION_WIDTH+1) // register size required to count the current bit of the key rotation bus + 1. log2(`KEY_ROTATION_WIDTH+1). (Verilog doesn't like me so i need a for loop)

// `define KEY_ENCRYPTER_COUNT `KEY_WIDTH/`ENCRYPTER_WIDTH // number of Encrypters transactions per key. `KEY_WIDTH/`ENCRYPTER_WIDTH
// `define KEY_ENCRYPTER_COUNT_REG $clog2(`KEY_ENCRYPTER_COUNT+1) // register size required to count the current Encrypter transaction of the key + 1. log2(`KEY_ENCRYPTER_COUNT+1)

`define NUM_ENCRYPTERS 2 // number of Encrypters
`define NUM_ENCRYPTERS_REG $clog2(`NUM_ENCRYPTERS+1) // register size required to count the current Encrypter + 1. log2(`NUM_ENCRYPTERS+1)

Icarus-Verliog-testing/Collector/collector.sv
`include "./Constants/constants.vh"
`define IDLE 2'b00
`define WAITING 2'b01
`define CAPTURING 2'b10
`define SENDING 2'b11


module Collector(
    input wire clk,
    input wire reset,
    //QSPI
    
    output reg [3:0] qspi_data,
    output reg qspi_sending = 0,
    input wire qspi_ready,
    
    //To encrypters
    input wire [`ENCRYPTER_WIDTH-1:0] encrypters_data [`NUM_ENCRYPTERS-1:0],
    input wire [`NUM_ENCRYPTERS-1:0] encrypters_data_ready,
    output reg [`NUM_ENCRYPTERS-1:0] encrypters_capture

    //Watchers
    // output reg [1:0] state_out,
    // output reg [`ENCRYPTER_WIDTH-1:0] encrypter_data_packe_out,
    
    // output reg [`ENCRYPTER_WIDTH_COUNT_REG-1:0] encrypter_data_subindex_out,
    // output reg [`NUM_ENCRYPTERS_REG-1:0] encrypter_index_out,
    // output reg [`ENCRYPTER_QSPI_COUNT_REG-1:0] encrypter_data_index_out    
);

    reg [1:0] state = `IDLE;

    reg [`ENCRYPTER_WIDTH-1:0] encrypter_data_packet;
    reg [`ENCRYPTER_WIDTH_COUNT_REG-1:0] encrypter_data_subindex;

    reg [`NUM_ENCRYPTERS_REG-1:0] encrypter_index;

    reg [`ENCRYPTER_QSPI_COUNT_REG-1:0] encrypter_data_index;

    initial begin
        encrypters_capture = 0;
        // assign state_out = state;
        // assign encrypter_data_packe_out = encrypter_data_packet;
        // assign encrypter_data_subindex_out = encrypter_data_subindex;
        // assign encrypter_index_out = encrypter_index;
        // assign encrypter_data_index_out = encrypter_data_index;
    end

    always @(posedge clk) begin

        if (reset) begin
            state <= `WAITING;
            encrypter_index <= 0;
        end

        if (state == `WAITING) begin
            if(encrypters_data_ready[encrypter_index]) begin
                encrypter_data_packet = encrypters_data[encrypter_index];
                state <= `CAPTURING;
                encrypter_data_index = 0;
            end else begin
                qspi_sending = 0;
            end
        end

    end

    always @(negedge clk) begin
        encrypters_capture <= 0;

        if (state == `CAPTURING) begin
            encrypters_capture[encrypter_index] <= 1;
            state = `SENDING;
        end

        if (state == `SENDING) begin
            if(qspi_ready) begin
                qspi_sending = 1;
                qspi_data[0] = encrypter_data_packet[encrypter_data_index*4];
                qspi_data[1] = encrypter_data_packet[encrypter_data_index*4+1]; 
                qspi_data[2] = encrypter_data_packet[encrypter_data_index*4+2];
                qspi_data[3] = encrypter_data_packet[encrypter_data_index*4+3];  
                encrypter_data_index = encrypter_data_index + 1;   
                if(encrypter_data_index == `ENCRYPTER_QSPI_COUNT) begin
                        encrypter_index = encrypter_index + 1;
                        if (encrypter_index == `NUM_ENCRYPTERS) begin
                            encrypter_index = 0;
                        end
                    state <= `WAITING; 
                end           
            end else qspi_sending = 0;   
        end     
    end 


endmodule

Icarus-Verliog-testing/Encrypter/encrypter.sv
`include "./Constants/constants.vh"

`define IDLE 3'b000
`define READING_KEY 3'b001
`define WAITING_RDY_DATA_IN 3'b010
`define READING_DATA_ENCRYPTING 3'b011
`define SENDING_DATA 3'b100
`define ACKNOWLEDGING_CAPTURE 3'b101

module Encrypter (
    input wire clk,
    input wire reset,

    // Parallelizer <-> Encrypter signals
    input wire [`ENCRYPTER_WIDTH-1:0] data_in_p,
    input wire [`KEY_ROTATION_WIDTH-1:0] key_rotation_p,
    input wire prog_p,
    input wire data_ready_in_p,
    output reg ready_p,

    // Encrypter <-> Collector signals
    output reg [`ENCRYPTER_WIDTH-1:0] data_out_c,
    output reg data_ready_out_c,
    input wire capture_c
);

    reg [2:0] state;
    reg [`ENCRYPTER_WIDTH-1:0] keyRotated;
    reg [`ENCRYPTER_WIDTH-1:0] data_in_store;
    reg [`ENCRYPTER_WIDTH-1:0] keyOrigin;
    reg [`KEY_ROTATION_WIDTH:0] offset;

    initial begin
        state <= `IDLE;
        ready_p = 0;
        data_ready_out_c = 0;
        data_out_c = 0;
        data_in_store = 0;
        keyOrigin = 0;
        keyRotated = 0;
        offset = 0;
    end

    always @(posedge clk) begin
        if (reset) begin
            state <= `IDLE;
            ready_p = 0;
            data_ready_out_c = 0;
            data_out_c = 0;
            data_in_store = 0;
            keyOrigin = 0;
            keyRotated = 0;
            offset = 0;
        end
        
        case (state)

            `IDLE: begin
                if (prog_p) state <= `READING_KEY;
            end

            `WAITING_RDY_DATA_IN: begin
                if (data_ready_in_p) state <= `READING_DATA_ENCRYPTING;
            end

            `READING_KEY: begin
                keyOrigin = data_in_p;
                state = `WAITING_RDY_DATA_IN;
            end

            `READING_DATA_ENCRYPTING: begin
                data_in_store = data_in_p;
                offset = key_rotation_p;
                ready_p = 0;
                keyRotated = (keyOrigin << offset) | (keyOrigin >> (`ENCRYPTER_WIDTH-offset));
                #20;
                state = `SENDING_DATA;
            end

            `SENDING_DATA: begin
                if (capture_c)
                state <= `ACKNOWLEDGING_CAPTURE;
            end

        endcase
    end

    always @(negedge clk) begin
        case (state)
            `SENDING_DATA: begin
                data_out_c = data_in_store ^ keyRotated;
                data_ready_out_c = 1;
            end

            `WAITING_RDY_DATA_IN: begin
                if (~ready_p) ready_p = 1;
            end

            `ACKNOWLEDGING_CAPTURE: begin
                state <= `WAITING_RDY_DATA_IN;
                data_ready_out_c = 0;
                ready_p = 1;
            end
        endcase
    end
endmodule

Icarus-Verliog-testing/Parallelizer/parallelizer.sv
`include "./Constants/constants.vh"

`define STATE_IDLE 3'b000
`define STATE_PROGRAMMING 3'b001
`define STATE_RECEIVING_KEY 3'b010
`define STATE_PROGRAMMING_ENCRYPTERS 3'b011
`define STATE_WAITING_FOR_READY_ENCRYPTERS 3'b100
`define STATE_ENCRYPTING 3'b101

module Parallelizer (
    input wire clk,
    input wire reset,
    //QSPI
    input wire [3:0] qspi_data,
    input wire qspi_sending,
    output reg qspi_ready,
    //Program
    input wire prog,
    //To encrypters
    output reg [`ENCRYPTER_WIDTH-1:0] encrypters_data,
    output reg [`KEY_ROTATION_WIDTH-1:0] encrypters_key_rotation,
    output reg [`NUM_ENCRYPTERS-1:0] encrypters_program,
    output reg [`NUM_ENCRYPTERS-1:0] encrypters_data_ready,
    input wire [`NUM_ENCRYPTERS-1:0] encrypters_ready
    //Watchers
    // output reg [2:0] state_out,
    // output reg [`ENCRYPTER_WIDTH-1:0] key_out
    // output reg [`KEY_ROTATION_WIDTH-1:0] key_rotation_out,
    // output reg [`ENCRYPTER_QSPI_COUNT_REG-1:0] key_index_out,
    // output reg [`ENCRYPTER_WIDTH-1:0] encrypter_data_packet_out,
    // output reg [`ENCRYPTER_QSPI_COUNT_REG-1:0] encrypter_data_index_out,
    // output reg [`NUM_ENCRYPTERS_REG-1:0] encrypter_index_out
);

reg [2:0] state = `STATE_IDLE;
reg [`ENCRYPTER_WIDTH-1:0] key;
reg [`ENCRYPTER_QSPI_COUNT_REG-1:0] key_index;
reg [`KEY_ROTATION_WIDTH-1:0] key_rotation;

reg [`ENCRYPTER_WIDTH-1:0] encrypter_data_packet;

reg [`ENCRYPTER_QSPI_COUNT_REG-1:0] encrypter_data_index;
reg [`NUM_ENCRYPTERS_REG-1:0] encrypter_index;
integer i;

initial begin
    // assign state_out = state;
    // assign key_out = key;
    // assign key_rotation_out = key_rotation;
    // assign key_index_out = key_index;
    // assign encrypter_data_packet_out = encrypter_data_packet;
    // assign encrypter_data_index_out = encrypter_data_index;
    // assign encrypter_index_out = encrypter_index;

    qspi_ready = 1'b0;
    encrypters_program = 0;
    key = 0;
    key_index = `ENCRYPTER_QSPI_COUNT;
end

//read on positive
always @(posedge clk) begin

    if (reset) begin
        state <= `STATE_IDLE;
        qspi_ready = 1'b1;
    end

    case (state)

        `STATE_IDLE: begin 
            if (qspi_sending) begin
                state <= `STATE_ENCRYPTING;
                encrypter_index = 0;
                encrypter_data_index = `ENCRYPTER_QSPI_COUNT;
                encrypters_data_ready = 0;
                key_rotation = 0;
            end
            if (prog) begin
                state <= `STATE_PROGRAMMING;
                qspi_ready = 1'b1;
                key_index = `ENCRYPTER_QSPI_COUNT;
            end
        end

        `STATE_PROGRAMMING: if (qspi_sending) state <= `STATE_RECEIVING_KEY;

        `STATE_RECEIVING_KEY: begin 
            if (~qspi_sending) begin
                state = `STATE_IDLE;
            end else begin
                key_index = key_index - 1;
                key[key_index*4] = qspi_data[0];
                key[key_index*4+1] = qspi_data[1];
                key[key_index*4+2] = qspi_data[2];
                key[key_index*4+3] = qspi_data[3];
                if (key_index == 0) begin
                    state = `STATE_PROGRAMMING_ENCRYPTERS;
                    qspi_ready = 1'b0;
                end
            end
        end

        `STATE_WAITING_FOR_READY_ENCRYPTERS: begin
            if (& encrypters_ready) begin
                state = `STATE_IDLE;
                encrypter_index = 0;
            end
        end

        `STATE_ENCRYPTING: begin
            if (~qspi_sending) begin
                state = `STATE_IDLE;
            end else begin
                //read spi data
                encrypter_data_index = encrypter_data_index - 1;
                encrypter_data_packet[encrypter_data_index*4] = qspi_data[0];
                encrypter_data_packet[encrypter_data_index*4+1] = qspi_data[1];
                encrypter_data_packet[encrypter_data_index*4+2] = qspi_data[2];
                encrypter_data_packet[encrypter_data_index*4+3] = qspi_data[3];
            end
        end

        default:;

    endcase
end

//write on negative
always @(negedge clk) begin
    case (state)

        `STATE_IDLE: begin    
            qspi_ready = 1'b1;
            encrypters_program = 0;
        end

        `STATE_PROGRAMMING_ENCRYPTERS: begin
            encrypters_data = key;
            for (encrypter_index = 0; encrypter_index < `NUM_ENCRYPTERS; encrypter_index = encrypter_index + 1) begin
                encrypters_program[encrypter_index] = 1'b1;
            end
            state = `STATE_WAITING_FOR_READY_ENCRYPTERS;
        end

        `STATE_ENCRYPTING: begin
            //keep ecrypter data index high for only 1 posedge clock cycle
            if (encrypter_index == 0) begin
                if (encrypters_data_ready[`NUM_ENCRYPTERS-1]) encrypters_data_ready[`NUM_ENCRYPTERS-1] = 0;
            end else begin
                if (encrypters_data_ready[encrypter_index-1]) encrypters_data_ready[encrypter_index-1] = 0;
            end

            if (encrypter_data_index == 0) begin
                //when packet full, send to encrypters
                encrypter_data_index = `ENCRYPTER_QSPI_COUNT;
                
                //check if encrypter is ready for new data
                if (encrypters_ready[encrypter_index]) begin
                    //put packet on encrypter bus
                    encrypters_data = encrypter_data_packet;
                    //put key rot on encrypter bus
                    encrypters_key_rotation = key_rotation;

                    //signal data is ready
                    encrypters_data_ready[encrypter_index] = 1'b1;

                    //move to next encrypter
                    encrypter_index = encrypter_index + 1;
                    if (encrypter_index == `NUM_ENCRYPTERS) encrypter_index = 0;

                    //move to next key rotation
                    key_rotation = key_rotation + 1;
                    if (key_rotation == `ENCRYPTER_WIDTH) key_rotation = 0;

                    //ready for more data as current data has been written
                    qspi_ready = 1'b1;
                end else begin
                    //if encrypter is not ready, wait for it
                    qspi_ready = 1'b0;
                end
            end
        end

        default:;

    endcase
end

endmodule

Icarus-Verliog-testing/TopLevel/top_level.sv
`timescale 10ns/10ns
`include "./Constants/constants.vh"
`include "./Parallelizer/parallelizer.sv"
`include "./Encrypter/encrypter.sv"
`include "./Collector/collector.sv"

`define ENCRYPT 1

module TopLevel();

    // Toplevel signals
    reg clk = 0;
    reg reset = 0;

    // Toplevel <-> Parallelizer signals
    reg [3:0] qspi_data_tp = 0;
    reg qspi_sending_tp = 0;
    wire qspi_ready_tp;
    reg prog_tp = 0;

    // Parallelizer <-> Encrypter signals
    wire [`ENCRYPTER_WIDTH-1:0] encrypters_data_pe;
    wire [`KEY_ROTATION_WIDTH-1:0] encrypters_key_rotation_pe;
    wire [`NUM_ENCRYPTERS-1:0] encrypters_program_pe;
    wire [`NUM_ENCRYPTERS-1:0] encrypters_data_ready_pe;
    wire [`NUM_ENCRYPTERS-1:0] encrypters_ready_pe;

    // Encrypter <-> Collector signals
    wire [`ENCRYPTER_WIDTH-1:0] encrypters_data_ec [`NUM_ENCRYPTERS-1:0];
    wire [`NUM_ENCRYPTERS-1:0] encrypters_data_ready_ec;
    wire [`NUM_ENCRYPTERS-1:0] encrypters_capture_ec;

    // Collector <-> Toplevel signals
    wire [3:0] qspi_data_ct;
    wire qspi_sending_ct;
    reg qspi_ready_ct = 1;

    // Watchers
    // wire [2:0] state_out_p;
    wire [`ENCRYPTER_WIDTH-1:0] key_out;
    wire [`ENCRYPTER_WIDTH-1:0] encrypters_data_ec1;
    wire [`ENCRYPTER_WIDTH-1:0] encrypters_data_ec2;

    assign encrypters_data_ec1 = encrypters_data_ec[0];
    assign encrypters_data_ec2 = encrypters_data_ec[1];

    Parallelizer p_inst(
        .clk(clk),
        .reset(reset),
        .qspi_data(qspi_data_tp),
        .qspi_sending(qspi_sending_tp),
        .qspi_ready(qspi_ready_tp),
        .prog(prog_tp),
        .encrypters_data(encrypters_data_pe),
        .encrypters_key_rotation(encrypters_key_rotation_pe),
        .encrypters_program(encrypters_program_pe),
        .encrypters_data_ready(encrypters_data_ready_pe),
        .encrypters_ready(encrypters_ready_pe)
        // .state_out(state_out_p),
        // .key_out(key_out)
    );

    genvar e;
    generate
        for (e = 0; e < `NUM_ENCRYPTERS; e = e + 1) begin : encrypter_loop
            Encrypter e_inst (
                .clk(clk),
                .reset(reset),
                .data_in_p(encrypters_data_pe),
                .key_rotation_p(encrypters_key_rotation_pe),
                .prog_p(encrypters_program_pe[e]),
                .data_ready_in_p(encrypters_data_ready_pe[e]),
                .ready_p(encrypters_ready_pe[e]),
                .data_out_c(encrypters_data_ec[e]),
                .data_ready_out_c(encrypters_data_ready_ec[e]),
                .capture_c(encrypters_capture_ec[e])
            );
        end
    endgenerate

    Collector c_inst(
        .clk(clk),
        .reset(reset),
        .qspi_data(qspi_data_ct),
        .qspi_sending(qspi_sending_ct),
        .qspi_ready(qspi_ready_ct),
        .encrypters_data(encrypters_data_ec),
        .encrypters_data_ready(encrypters_data_ready_ec),
        .encrypters_capture(encrypters_capture_ec)
    );

    reg [31:0] key = 32'hB4352B93;
    reg [3:0] encrypters_delays [`NUM_ENCRYPTERS-1:0];
    integer fd_read, fd_write, i, j;
    reg [7:0] char_read, char_write;
    logic char_write_progress = 0;

    initial begin
        //fill spi_data_values with data from file
        if (`ENCRYPT) begin
            fd_read = $fopen("./TopLevel/message.txt", "r");
        end else begin
            fd_read = $fopen("./TopLevel/encrypted_message.enc", "r");
        end

        if (fd_read == -1) begin
            $display("Error data file!");
            $finish;  // Exit simulation on error
        end

        if (`ENCRYPT) begin
            fd_write = $fopen("./TopLevel/encrypted_message.enc", "w");
        end else begin
            fd_write = $fopen("./TopLevel/decrypted_message.txt", "w");
        end
        if (fd_write == -1) begin
            $display("Error encrypted data file!");
            $finish;  // Exit simulation on error
        end

        for (j = 0; j < `NUM_ENCRYPTERS-1; j = j + 1) begin
            encrypters_delays[j] = 0;
        end
    end

    initial begin
        $dumpfile("TopLevel/top_level.vcd");
        $dumpvars(0, TopLevel);
        $display("Starting simulation");

        //set data on neg edge, read on the rising
        #2 reset = 1; #2 reset = 0;
        #2 prog_tp = 1; #2 prog_tp = 0;

        //send key
        while (!qspi_ready_tp) #2;
        #2 qspi_sending_tp = 1; #2
        for (i = 0; i < `ENCRYPTER_QSPI_COUNT; i = i + 1) begin
            qspi_data_tp[0] = key[i*4];
            qspi_data_tp[1] = key[i*4+1];
            qspi_data_tp[2] = key[i*4+2];
            qspi_data_tp[3] = key[i*4+3];
            #2;
            // $display("[KEY] 0x%x", qspi_data_tp);
        end
        qspi_sending_tp = 0;

        //send data
        while (!qspi_ready_tp) #2;
        #2 qspi_sending_tp = 1; #2
        while (!$feof(fd_read)) begin
            char_read = $fgetc(fd_read);
            $display("[RAW] 0x%x", char_read);

            while (!qspi_ready_tp) #2;
            qspi_data_tp = char_read[7:4]; #2;
            // $display("[DAT] 0x%x", qspi_data_tp);

            while (!qspi_ready_tp) #2;
            qspi_data_tp = char_read[3:0]; #2;
            // $display("[DAT] 0x%x", qspi_data_tp);
        end
        #2 qspi_sending_tp = 0;

        while (!qspi_sending_ct) #2;
        #4 $fclose(fd_read); $fclose(fd_write); $finish;
    end

    always begin
        #1 clk = ~clk;
        if (clk) begin
            if (qspi_sending_ct) begin
                if (char_write_progress == 0) begin
                    char_write_progress = 1;
                    char_write[7:4] = qspi_data_ct;
                end else begin
                    char_write_progress = 0;
                    char_write[3:0] = qspi_data_ct;
                    $display("[ENC] 0x%x", char_write);
                    $fputc(char_write, fd_write);
                end
            end
        end
    end

endmodule

Icarus-Verliog-testing/TopLevel/top_level.vcd
$date
	Sun May 19 16:18:55 2024
$end
$version
	Icarus Verilog
$end
$timescale
	10ns
$end
$scope module TopLevel $end
$var wire 32 ! encrypters_data_ec1 [31:0] $end
$var wire 32 " encrypters_data_ec2 [31:0] $end
$var wire 1 # qspi_sending_ct $end
$var wire 1 $ qspi_ready_tp $end
$var wire 4 % qspi_data_ct [3:0] $end
$var wire 2 & encrypters_ready_pe [1:0] $end
$var wire 2 ' encrypters_program_pe [1:0] $end
$var wire 5 ( encrypters_key_rotation_pe [4:0] $end
$var wire 2 ) encrypters_data_ready_pe [1:0] $end
$var wire 2 * encrypters_data_ready_ec [1:0] $end
$var wire 32 + encrypters_data_pe [31:0] $end
$var wire 2 , encrypters_capture_ec [1:0] $end
$var reg 8 - char_read [7:0] $end
$var reg 8 . char_write [7:0] $end
$var reg 1 / char_write_progress $end
$var reg 1 0 clk $end
$var reg 32 1 key [31:0] $end
$var reg 1 2 prog_tp $end
$var reg 4 3 qspi_data_tp [3:0] $end
$var reg 1 4 qspi_ready_ct $end
$var reg 1 5 qspi_sending_tp $end
$var reg 1 6 reset $end
$var integer 32 7 fd_read [31:0] $end
$var integer 32 8 fd_write [31:0] $end
$var integer 32 9 i [31:0] $end
$var integer 32 : j [31:0] $end
$scope begin encrypter_loop[0] $end
$var parameter 2 ; e $end
$scope module e_inst $end
$var wire 1 < capture_c $end
$var wire 1 0 clk $end
$var wire 1 = data_ready_in_p $end
$var wire 1 > prog_p $end
$var wire 1 6 reset $end
$var wire 5 ? key_rotation_p [4:0] $end
$var wire 32 @ data_in_p [31:0] $end
$var reg 32 A data_in_store [31:0] $end
$var reg 32 B data_out_c [31:0] $end
$var reg 1 C data_ready_out_c $end
$var reg 32 D keyOrigin [31:0] $end
$var reg 32 E keyRotated [31:0] $end
$var reg 6 F offset [5:0] $end
$var reg 1 G ready_p $end
$var reg 3 H state [2:0] $end
$upscope $end
$upscope $end
$scope begin encrypter_loop[1] $end
$var parameter 2 I e $end
$scope module e_inst $end
$var wire 1 J capture_c $end
$var wire 1 0 clk $end
$var wire 1 K data_ready_in_p $end
$var wire 1 L prog_p $end
$var wire 1 6 reset $end
$var wire 5 M key_rotation_p [4:0] $end
$var wire 32 N data_in_p [31:0] $end
$var reg 32 O data_in_store [31:0] $end
$var reg 32 P data_out_c [31:0] $end
$var reg 1 Q data_ready_out_c $end
$var reg 32 R keyOrigin [31:0] $end
$var reg 32 S keyRotated [31:0] $end
$var reg 6 T offset [5:0] $end
$var reg 1 U ready_p $end
$var reg 3 V state [2:0] $end
$upscope $end
$upscope $end
$scope module c_inst $end
$var wire 1 0 clk $end
$var wire 2 W encrypters_data_ready [1:0] $end
$var wire 1 4 qspi_ready $end
$var wire 1 6 reset $end
$var reg 4 X encrypter_data_index [3:0] $end
$var reg 32 Y encrypter_data_packet [31:0] $end
$var reg 2 Z encrypter_index [1:0] $end
$var reg 2 [ encrypters_capture [1:0] $end
$var reg 4 \ qspi_data [3:0] $end
$var reg 1 # qspi_sending $end
$var reg 2 ] state [1:0] $end
$upscope $end
$scope module p_inst $end
$var wire 1 0 clk $end
$var wire 2 ^ encrypters_ready [1:0] $end
$var wire 1 2 prog $end
$var wire 4 _ qspi_data [3:0] $end
$var wire 1 5 qspi_sending $end
$var wire 1 6 reset $end
$var reg 4 ` encrypter_data_index [3:0] $end
$var reg 32 a encrypter_data_packet [31:0] $end
$var reg 2 b encrypter_index [1:0] $end
$var reg 32 c encrypters_data [31:0] $end
$var reg 2 d encrypters_data_ready [1:0] $end
$var reg 5 e encrypters_key_rotation [4:0] $end
$var reg 2 f encrypters_program [1:0] $end
$var reg 32 g key [31:0] $end
$var reg 4 h key_index [3:0] $end
$var reg 5 i key_rotation [4:0] $end
$var reg 1 $ qspi_ready $end
$var reg 3 j state [2:0] $end
$upscope $end
$upscope $end
$enddefinitions $end
$comment Show the parameter values. $end
$dumpall
b1 I
b0 ;
$end
#0
$dumpvars
b0 j
bx i
b0 h
b0 g
b0 f
bx e
bx d
bx c
bx b
bx a
bx `
b0 _
b0 ^
b0 ]
bx \
b0 [
bx Z
bx Y
bx X
b0 W
b0 V
0U
b0 T
b0 S
b0 R
0Q
b0 P
b0 O
bx N
bx M
0L
xK
0J
b0 H
0G
b0 F
b0 E
b0 D
0C
b0 B
b0 A
bx @
bx ?
0>
x=
0<
b1 :
bx 9
b10000000000000000000000000000100 8
b10000000000000000000000000000011 7
06
05
14
b0 3
02
b10110100001101010010101110010011 1
00
0/
bx .
bx -
b0 ,
bx +
b0 *
bx )
bx (
b0 '
b0 &
bx %
0$
0#
b0 "
b0 !
$end
#1
10
#2
1$
00
16
#3
b0 Z
b1 ]
10
#4
00
06
#5
10
#6
00
12
#7
b1 j
10
#8
00
02
#9
10
#10
00
15
#11
b10 j
10
#12
00
b11 3
b11 _
b0 9
#13
b1 h
b11 g
10
#14
00
b1001 3
b1001 _
b1 9
#15
b10 h
b10010011 g
10
#16
00
b1011 3
b1011 _
b10 9
#17
b11 h
b101110010011 g
10
#18
00
b10 3
b10 _
b11 9
#19
b100 h
b10101110010011 g
10
#20
00
b101 3
b101 _
b100 9
#21
b101 h
b1010010101110010011 g
10
#22
00
b11 3
b11 _
b101 9
#23
b110 h
b1101010010101110010011 g
10
#24
00
b100 3
b100 _
b110 9
#25
b111 h
b100001101010010101110010011 g
10
#26
00
b1011 3
b1011 _
b111 9
#27
0$
b11 j
b1000 h
b10110100001101010010101110010011 g
10
#28
1L
1>
b100 j
b11 '
b11 f
b10 b
b10110100001101010010101110010011 +
b10110100001101010010101110010011 @
b10110100001101010010101110010011 N
b10110100001101010010101110010011 c
00
05
b1000 9
#29
b1 H
b1 V
10
#30
00
#31
b10 V
b10110100001101010010101110010011 R
b10 H
b10110100001101010010101110010011 D
10
#32
1U
b11 &
b11 ^
1G
00
#33
b0 b
b0 j
10
#34
0L
0>
b0 '
b0 f
1$
00
#35
10
#36
00
#37
10
#38
00
15
#39
b101 j
0K
0=
b0 i
b0 )
b0 d
b0 `
10
#40
00
b101 3
b101 _
b1011001 -
#41
b1 `
bx0101 a
10
#42
00
b1001 3
b1001 _
#43
b10 `
bx10010101 a
10
#44
00
b110 3
b110 _
b1101111 -
#45
b11 `
bx011010010101 a
10
#46
00
b1111 3
b1111 _
#47
b100 `
bx1111011010010101 a
10
#48
00
b110 3
b110 _
b1100100 -
#49
b101 `
bx01101111011010010101 a
10
#50
00
b100 3
b100 _
#51
b110 `
bx010001101111011010010101 a
10
#52
00
b110 3
b110 _
b1100001 -
#53
b111 `
bx0110010001101111011010010101 a
10
#54
00
b1 3
b1 _
#55
b1000 `
b10110010001101111011010010101 a
10
#56
1=
b1 i
b1 b
b1 )
b1 d
b0 (
b0 ?
b0 M
b0 e
b10110010001101111011010010101 +
b10110010001101111011010010101 @
b10110010001101111011010010101 N
b10110010001101111011010010101 c
b0 `
00
b10 3
b10 _
b101100 -
#57
b11 H
b1 `
b10110010001101111011010010010 a
10
#58
0=
b0 )
b0 d
00
b1100 3
b1100 _
#59
b10 `
b10110010001101111011011000010 a
b100 H
b10110100001101010010101110010011 E
b10 &
b10 ^
0G
b10110010001101111011010010101 A
10
#60
b1 *
b1 W
1C
b10100010011100111101110100000110 !
b10100010011100111101110100000110 B
00
b10 3
b10 _
b100000 -
#61
b10 ]
b11 `
b10110010001101111001011000010 a
b0 X
b10100010011100111101110100000110 Y
10
#62
1<
b1 ,
b1 [
b1 X
b110 %
b110 \
1#
b11 ]
00
b0 3
b0 _
#63
b101 H
b100 `
b10110010001100000001011000010 a
b110xxxx .
1/
10
#64
0<
b0 ,
b0 [
b10 H
b10 X
b0 %
b0 \
b11 &
b11 ^
1G
b0 *
b0 W
0C
00
b100 3
b100 _
b1001001 -
#65
b101 `
b10110010001000000001011000010 a
b1100000 .
0/
10
#66
b11 X
b1101 %
b1101 \
00
b1001 3
b1001 _
#67
b110 `
b10110100101000000001011000010 a
b11010000 .
1/
10
#68
b100 X
00
b10 3
b10 _
b100000 -
#69
b111 `
b10010100101000000001011000010 a
b11011101 .
0/
10
#70
b101 X
b11 %
b11 \
00
b0 3
b0 _
#71
b1000 `
b10100101000000001011000010 a
b111101 .
1/
10
#72
1K
b110 X
b111 %
b111 \
b10 i
b0 b
b10 )
b10 d
b1 (
b1 ?
b1 M
b1 e
b10100101000000001011000010 +
b10100101000000001011000010 @
b10100101000000001011000010 N
b10100101000000001011000010 c
b0 `
00
b110 3
b110 _
b1100001 -
#73
b11 V
b1 `
b10100101000000001011000110 a
b110111 .
0/
10
#74
0K
b0 )
b0 d
b111 X
b10 %
b10 \
00
b1 3
b1 _
#75
b10 `
b10100101000000001000010110 a
b100 V
b1101000011010100101011100100111 S
b1 &
b1 ^
0U
b1 T
b10100101000000001011000010 O
b100111 .
1/
10
#76
b1 ]
b1 Z
b1000 X
b1010 %
b1010 \
b10 *
b10 W
1Q
b1101010111111100101010111100101 "
b1101010111111100101010111100101 P
00
b110 3
b110 _
b1101101 -
#77
b10 ]
b11 `
b10100101000000011000010110 a
b0 X
b1101010111111100101010111100101 Y
b101010 .
0/
10
#78
1J
b10 ,
b10 [
b1 X
b101 %
b101 \
b11 ]
00
b1101 3
b1101 _
#79
b101 V
b100 `
b10100101001101011000010110 a
b1011010 .
1/
10
#80
0J
b0 ,
b0 [
b10 V
b10 X
b1110 %
b1110 \
b11 &
b11 ^
1U
b0 *
b0 W
0Q
00
b10 3
b10 _
b101110 -
#81
b101 `
b10100100101101011000010110 a
b1011110 .
0/
10
#82
b11 X
b101 %
b101 \
00
b1110 3
b1110 _
#83
b110 `
b10111000101101011000010110 a
1/
10
#84
b100 X
00
b10 3
b10 _
b100000 -
#85
b111 `
b1010101 .
0/
10
#86
b101 X
b1110 %
b1110 \
00
b0 3
b0 _
#87
b1000 `
b11100101 .
1/
10
#88
1=
b110 X
b1111 %
b1111 \
b11 i
b1 b
b1 )
b1 d
b10 (
b10 ?
b10 M
b10 e
b10111000101101011000010110 +
b10111000101101011000010110 @
b10111000101101011000010110 N
b10111000101101011000010110 c
b0 `
00
b101 3
b101 _
b1011001 -
#89
b11 H
b1 `
b10111000101101011000010101 a
b11101111 .
0/
10
#90
0=
b0 )
b0 d
b111 X
b1010 %
b1010 \
00
b1001 3
b1001 _
#91
b10 `
b10111000101101011010010101 a
b100 H
b11010000110101001010111001001110 E
b10 &
b10 ^
0G
b10 F
b10111000101101011000010110 A
b10101111 .
1/
10
#92
b1 ]
b0 Z
b1000 X
b110 %
b110 \
b1 *
b1 W
1C
b11010010001101100111100001011000 !
b11010010001101100111100001011000 B
00
b110 3
b110 _
b1101111 -
#93
b10 ]
b11 `
b0 X
b11010010001101100111100001011000 Y
b10100110 .
0/
10
#94
1<
b1 ,
b1 [
b1 X
b1000 %
b1000 \
b11 ]
00
b1111 3
b1111 _
#95
b101 H
b100 `
b10111000101111011010010101 a
b10000110 .
1/
10
#96
0<
b0 ,
b0 [
b10 H
b10 X
b101 %
b101 \
b11 &
b11 ^
1G
b0 *
b0 W
0C
00
b110 3
b110 _
b1100100 -
#97
b101 `
b10111001101111011010010101 a
b10000101 .
0/
10
#98
b11 X
b1000 %
b1000 \
00
b100 3
b100 _
#99
b110 `
b10010001101111011010010101 a
1/
10
#100
b100 X
b111 %
b111 \
00
b110 3
b110 _
b1100001 -
#101
b111 `
b110010001101111011010010101 a
b10000111 .
0/
10
