Icarus-Verliog-testing/Constants/constants.vh
//DEFINE CONSTANTS
// `define KEY_WIDTH 16 // width of the key. In multiples of 4.
// `define KEY_QSPI_COUNT `KEY_WIDTH/4 // number of QSPI transactions per key sent in LSB. 
// `define KEY_QSPI_COUNT_REG $clog2(`KEY_QSPI_COUNT+1) // register size required to count the current QSPI transaction of the key + 1. log2(`KEY_QSPI_COUNT+1)

`define ENCRYPTER_WIDTH 32 // width of the bus between the Paralellizer and Encrypter, and the Encrypter and Collector. In multiples of 4.
`define ENCRYPTER_WIDTH_COUNT_REG $clog2(`ENCRYPTER_WIDTH+1) // register size required to count the current bit of the encrypter bus + 1. log2(`ENCRYPTER_WIDTH+1). (Verilog doesn't like me so i need a for loop)
`define ENCRYPTER_QSPI_COUNT `ENCRYPTER_WIDTH/4 // number of QSPI transactions per Encrypter.
`define ENCRYPTER_QSPI_COUNT_REG $clog2(`ENCRYPTER_QSPI_COUNT+1) // register size required to count the current QSPI transaction of the Encrypter + 1. log2(`ENCRYPTER_QSPI_COUNT+1)

`define KEY_ROTATION_WIDTH $clog2(`ENCRYPTER_WIDTH) // width of the key rotation bus between Paralellizer and Encrypter. log2(`KEY_WIDTH)
`define KEY_ROTATION_WIDTH_COUNT_REG $clog2(`KEY_ROTATION_WIDTH+1) // register size required to count the current bit of the key rotation bus + 1. log2(`KEY_ROTATION_WIDTH+1). (Verilog doesn't like me so i need a for loop)

// `define KEY_ENCRYPTER_COUNT `KEY_WIDTH/`ENCRYPTER_WIDTH // number of Encrypters transactions per key. `KEY_WIDTH/`ENCRYPTER_WIDTH
// `define KEY_ENCRYPTER_COUNT_REG $clog2(`KEY_ENCRYPTER_COUNT+1) // register size required to count the current Encrypter transaction of the key + 1. log2(`KEY_ENCRYPTER_COUNT+1)

`define NUM_ENCRYPTERS 2 // number of Encrypters
`define NUM_ENCRYPTERS_REG $clog2(`NUM_ENCRYPTERS+1) // register size required to count the current Encrypter + 1. log2(`NUM_ENCRYPTERS+1)

Icarus-Verliog-testing/Collector/collector.sv
`include "./Constants/constants.vh"
`define IDLE 2'b00
`define WAITING 2'b01
`define CAPTURING 2'b10
`define SENDING 2'b11


module Collector(
    input wire clk,
    input wire reset,
    //QSPI
    
    output reg [3:0] qspi_data,
    output reg qspi_sending = 0,
    input wire qspi_ready,
    
    //To encrypters
    input wire [`ENCRYPTER_WIDTH-1:0] encrypters_data [`NUM_ENCRYPTERS-1:0],
    input wire [`NUM_ENCRYPTERS-1:0] encrypters_data_ready,
    output reg [`NUM_ENCRYPTERS-1:0] encrypters_capture

    //Watchers
    // output reg [1:0] state_out,
    // output reg [`ENCRYPTER_WIDTH-1:0] encrypter_data_packe_out,
    
    // output reg [`ENCRYPTER_WIDTH_COUNT_REG-1:0] encrypter_data_subindex_out,
    // output reg [`NUM_ENCRYPTERS_REG-1:0] encrypter_index_out,
    // output reg [`ENCRYPTER_QSPI_COUNT_REG-1:0] encrypter_data_index_out    
);

    reg [1:0] state = `IDLE;

    reg [`ENCRYPTER_WIDTH-1:0] encrypter_data_packet;
    reg [`ENCRYPTER_WIDTH_COUNT_REG-1:0] encrypter_data_subindex;

    reg [`NUM_ENCRYPTERS_REG-1:0] encrypter_index;

    reg [`ENCRYPTER_QSPI_COUNT_REG-1:0] encrypter_data_index;

    initial begin
        encrypters_capture = 0;
        // assign state_out = state;
        // assign encrypter_data_packe_out = encrypter_data_packet;
        // assign encrypter_data_subindex_out = encrypter_data_subindex;
        // assign encrypter_index_out = encrypter_index;
        // assign encrypter_data_index_out = encrypter_data_index;
    end

    always @(posedge clk) begin

        if (reset) begin
            state <= `WAITING;
            encrypter_index <= 0;
        end

        if (state == `WAITING) begin
            if(encrypters_data_ready[encrypter_index]) begin
                encrypter_data_packet = encrypters_data[encrypter_index];
                state <= `CAPTURING;
                encrypter_data_index = 0;
            end else begin
                qspi_sending = 0;
            end
        end

    end

    always @(negedge clk) begin
        encrypters_capture <= 0;

        if (state == `CAPTURING) begin
            encrypters_capture[encrypter_index] <= 1;
            state = `SENDING;
        end

        if (state == `SENDING) begin
            if(qspi_ready) begin
                qspi_sending = 1;
                qspi_data[0] = encrypter_data_packet[encrypter_data_index*4];
                qspi_data[1] = encrypter_data_packet[encrypter_data_index*4+1]; 
                qspi_data[2] = encrypter_data_packet[encrypter_data_index*4+2];
                qspi_data[3] = encrypter_data_packet[encrypter_data_index*4+3];  
                encrypter_data_index = encrypter_data_index + 1;   
                if(encrypter_data_index == `ENCRYPTER_QSPI_COUNT) begin
                        encrypter_index = encrypter_index + 1;
                        if (encrypter_index == `NUM_ENCRYPTERS) begin
                            encrypter_index = 0;
                        end
                    state <= `WAITING; 
                end           
            end else qspi_sending = 0;   
        end     
    end 


endmodule

Icarus-Verliog-testing/Encrypter/encrypter.sv
`include "./Constants/constants.vh"

`define IDLE 3'b000
`define READING_KEY 3'b001
`define WAITING_RDY_DATA_IN 3'b010
`define READING_DATA_ENCRYPTING 3'b011
`define SENDING_DATA 3'b100
`define ACKNOWLEDGING_CAPTURE 3'b101

module Encrypter (
    input wire clk,
    input wire reset,

    // Parallelizer <-> Encrypter signals
    input wire [`ENCRYPTER_WIDTH-1:0] data_in_p,
    input wire [`KEY_ROTATION_WIDTH-1:0] key_rotation_p,
    input wire prog_p,
    input wire data_ready_in_p,
    output reg ready_p,

    // Encrypter <-> Collector signals
    output reg [`ENCRYPTER_WIDTH-1:0] data_out_c,
    output reg data_ready_out_c,
    input wire capture_c
);

    reg [2:0] state;
    reg [`ENCRYPTER_WIDTH-1:0] keyRotated;
    reg [`ENCRYPTER_WIDTH-1:0] data_in_store;
    reg [`ENCRYPTER_WIDTH-1:0] keyOrigin;
    reg [`KEY_ROTATION_WIDTH:0] offset;

    initial begin
        state <= `IDLE;
        ready_p = 0;
        data_ready_out_c = 0;
        data_out_c = 0;
        data_in_store = 0;
        keyOrigin = 0;
        keyRotated = 0;
        offset = 0;
    end

    always @(posedge clk) begin
        if (reset) begin
            state <= `IDLE;
            ready_p = 0;
            data_ready_out_c = 0;
            data_out_c = 0;
            data_in_store = 0;
            keyOrigin = 0;
            keyRotated = 0;
            offset = 0;
        end
        
        case (state)

            `IDLE: begin
                if (prog_p) state <= `READING_KEY;
            end

            `WAITING_RDY_DATA_IN: begin
                if (data_ready_in_p) state <= `READING_DATA_ENCRYPTING;
            end

            `READING_KEY: begin
                keyOrigin = data_in_p;
                state = `WAITING_RDY_DATA_IN;
            end

            `READING_DATA_ENCRYPTING: begin
                data_in_store = data_in_p;
                offset = key_rotation_p;
                ready_p = 0;
                keyRotated = (keyOrigin << offset) | (keyOrigin >> (`ENCRYPTER_WIDTH-offset));
                #20;
                state = `SENDING_DATA;
            end

            `SENDING_DATA: begin
                if (capture_c)
                state <= `ACKNOWLEDGING_CAPTURE;
            end

        endcase
    end

    always @(negedge clk) begin
        case (state)
            `SENDING_DATA: begin
                data_out_c = data_in_store ^ keyRotated;
                data_ready_out_c = 1;
            end

            `WAITING_RDY_DATA_IN: begin
                if (~ready_p) ready_p = 1;
            end

            `ACKNOWLEDGING_CAPTURE: begin
                state <= `WAITING_RDY_DATA_IN;
                data_ready_out_c = 0;
                ready_p = 1;
            end
        endcase
    end
endmodule

Icarus-Verliog-testing/Parallelizer/parallelizer.sv
`include "./Constants/constants.vh"

`define STATE_IDLE 3'b000
`define STATE_PROGRAMMING 3'b001
`define STATE_RECEIVING_KEY 3'b010
`define STATE_PROGRAMMING_ENCRYPTERS 3'b011
`define STATE_WAITING_FOR_READY_ENCRYPTERS 3'b100
`define STATE_ENCRYPTING 3'b101

module Parallelizer (
    input wire clk,
    input wire reset,
    //QSPI
    input wire [3:0] qspi_data,
    input wire qspi_sending,
    output reg qspi_ready,
    //Program
    input wire prog,
    //To encrypters
    output reg [`ENCRYPTER_WIDTH-1:0] encrypters_data,
    output reg [`KEY_ROTATION_WIDTH-1:0] encrypters_key_rotation,
    output reg [`NUM_ENCRYPTERS-1:0] encrypters_program,
    output reg [`NUM_ENCRYPTERS-1:0] encrypters_data_ready,
    input wire [`NUM_ENCRYPTERS-1:0] encrypters_ready
    //Watchers
    // output reg [2:0] state_out,
    // output reg [`ENCRYPTER_WIDTH-1:0] key_out
    // output reg [`KEY_ROTATION_WIDTH-1:0] key_rotation_out,
    // output reg [`ENCRYPTER_QSPI_COUNT_REG-1:0] key_index_out,
    // output reg [`ENCRYPTER_WIDTH-1:0] encrypter_data_packet_out,
    // output reg [`ENCRYPTER_QSPI_COUNT_REG-1:0] encrypter_data_index_out,
    // output reg [`NUM_ENCRYPTERS_REG-1:0] encrypter_index_out
);

reg [2:0] state = `STATE_IDLE;
reg [`ENCRYPTER_QSPI_COUNT_REG-1:0] key_index;
reg [`KEY_ROTATION_WIDTH-1:0] key_rotation;

reg [`ENCRYPTER_WIDTH-1:0] encrypter_data_packet;

reg [`ENCRYPTER_QSPI_COUNT_REG-1:0] encrypter_data_index;
reg [`NUM_ENCRYPTERS_REG-1:0] encrypter_index;
integer i;

initial begin
    // assign state_out = state;
    // assign key_out = encrypter_data_packet;
    // assign key_rotation_out = key_rotation;
    // assign key_index_out = key_index;
    // assign encrypter_data_packet_out = encrypter_data_packet;
    // assign encrypter_data_index_out = encrypter_data_index;
    // assign encrypter_index_out = encrypter_index;

    qspi_ready = 1'b0;
    encrypters_program = 0;
    encrypter_data_packet = 0;
    key_index = `ENCRYPTER_QSPI_COUNT;
end

//read on positive
always @(posedge clk) begin

    if (reset) begin
        state <= `STATE_IDLE;
        qspi_ready = 1'b1;
    end

    case (state)

        `STATE_IDLE: begin 
            if (qspi_sending) begin
                state <= `STATE_ENCRYPTING;
                encrypter_index = 0;
                encrypter_data_index = `ENCRYPTER_QSPI_COUNT;
                encrypters_data_ready = 0;
                key_rotation = 0;
            end
            if (prog) begin
                state <= `STATE_PROGRAMMING;
                qspi_ready = 1'b1;
                key_index = `ENCRYPTER_QSPI_COUNT;
            end
        end

        `STATE_PROGRAMMING: if (qspi_sending) state <= `STATE_RECEIVING_KEY;

        `STATE_RECEIVING_KEY: begin 
            if (~qspi_sending) begin
                state = `STATE_IDLE;
            end else begin
                key_index = key_index - 1;
                encrypter_data_packet[key_index*4] = qspi_data[0];
                encrypter_data_packet[key_index*4+1] = qspi_data[1];
                encrypter_data_packet[key_index*4+2] = qspi_data[2];
                encrypter_data_packet[key_index*4+3] = qspi_data[3];
                if (key_index == 0) begin
                    state = `STATE_PROGRAMMING_ENCRYPTERS;
                    qspi_ready = 1'b0;
                end
            end
        end

        `STATE_WAITING_FOR_READY_ENCRYPTERS: begin
            if (& encrypters_ready) begin
                state = `STATE_IDLE;
                encrypter_index = 0;
            end
        end

        `STATE_ENCRYPTING: begin
            if (~qspi_sending) begin
                state = `STATE_IDLE;
            end else begin
                //read spi data
                encrypter_data_index = encrypter_data_index - 1;
                encrypter_data_packet[encrypter_data_index*4] = qspi_data[0];
                encrypter_data_packet[encrypter_data_index*4+1] = qspi_data[1];
                encrypter_data_packet[encrypter_data_index*4+2] = qspi_data[2];
                encrypter_data_packet[encrypter_data_index*4+3] = qspi_data[3];
            end
        end

        default:;

    endcase
end

//write on negative
always @(negedge clk) begin
    case (state)

        `STATE_IDLE: begin    
            qspi_ready = 1'b1;
            encrypters_program = 0;
        end

        `STATE_PROGRAMMING_ENCRYPTERS: begin
            encrypters_data = encrypter_data_packet;
            for (encrypter_index = 0; encrypter_index < `NUM_ENCRYPTERS; encrypter_index = encrypter_index + 1) begin
                encrypters_program[encrypter_index] = 1'b1;
            end
            state = `STATE_WAITING_FOR_READY_ENCRYPTERS;
        end

        `STATE_ENCRYPTING: begin
            //keep ecrypter data index high for only 1 posedge clock cycle
            if (encrypter_index == 0) begin
                if (encrypters_data_ready[`NUM_ENCRYPTERS-1]) encrypters_data_ready[`NUM_ENCRYPTERS-1] = 0;
            end else begin
                if (encrypters_data_ready[encrypter_index-1]) encrypters_data_ready[encrypter_index-1] = 0;
            end

            if (encrypter_data_index == 0) begin
                //when packet full, send to encrypters
                encrypter_data_index = `ENCRYPTER_QSPI_COUNT;
                
                //check if encrypter is ready for new data
                if (encrypters_ready[encrypter_index]) begin
                    //put packet on encrypter bus
                    encrypters_data = encrypter_data_packet;
                    //put key rot on encrypter bus
                    encrypters_key_rotation = key_rotation;

                    //signal data is ready
                    encrypters_data_ready[encrypter_index] = 1'b1;

                    //move to next encrypter
                    encrypter_index = encrypter_index + 1;
                    if (encrypter_index == `NUM_ENCRYPTERS) encrypter_index = 0;

                    //move to next key rotation
                    key_rotation = key_rotation + 1;
                    if (key_rotation == `ENCRYPTER_WIDTH) key_rotation = 0;

                    //ready for more data as current data has been written
                    qspi_ready = 1'b1;
                end else begin
                    //if encrypter is not ready, wait for it
                    qspi_ready = 1'b0;
                end
            end
        end

        default:;

    endcase
end

endmodule

Icarus-Verliog-testing/TopLevel/top_level.sv
`timescale 10ns / 10ns
`include "./Constants/constants.vh"
`include "./Parallelizer/parallelizer.sv"
`include "./Encrypter/encrypter.sv"
`include "./Collector/collector.sv"

`define ENCRYPT 1
`define MAX_BYTES 4*4

module TopLevel();

    // Toplevel signals
    reg clk = 0;
    reg reset = 0;

    // Toplevel <-> Parallelizer signals
    reg [3:0] qspi_data_tp = 0;
    reg qspi_sending_tp = 0;
    wire qspi_ready_tp;
    reg prog_tp = 0;

    // Parallelizer <-> Encrypter signals
    wire [`ENCRYPTER_WIDTH-1:0] encrypters_data_pe;
    wire [`KEY_ROTATION_WIDTH-1:0] encrypters_key_rotation_pe;
    wire [`NUM_ENCRYPTERS-1:0] encrypters_program_pe;
    wire [`NUM_ENCRYPTERS-1:0] encrypters_data_ready_pe;
    wire [`NUM_ENCRYPTERS-1:0] encrypters_ready_pe;

    // Encrypter <-> Collector signals
    wire [`ENCRYPTER_WIDTH-1:0] encrypters_data_ec [`NUM_ENCRYPTERS-1:0];
    wire [`NUM_ENCRYPTERS-1:0] encrypters_data_ready_ec;
    wire [`NUM_ENCRYPTERS-1:0] encrypters_capture_ec;

    // Collector <-> Toplevel signals
    wire [3:0] qspi_data_ct;
    wire qspi_sending_ct;
    reg qspi_ready_ct = 1;

    // Watchers
    // wire [2:0] state_out_p;
    wire [`ENCRYPTER_WIDTH-1:0] key_out;
    wire [`ENCRYPTER_WIDTH-1:0] encrypters_data_ec0;
    wire [`ENCRYPTER_WIDTH-1:0] encrypters_data_ec1;

    assign encrypters_data_ec0 = encrypters_data_ec[0];
    assign encrypters_data_ec1 = encrypters_data_ec[1];

    Parallelizer p_inst(
        .clk(clk),
        .reset(reset),
        .qspi_data(qspi_data_tp),
        .qspi_sending(qspi_sending_tp),
        .qspi_ready(qspi_ready_tp),
        .prog(prog_tp),
        .encrypters_data(encrypters_data_pe),
        .encrypters_key_rotation(encrypters_key_rotation_pe),
        .encrypters_program(encrypters_program_pe),
        .encrypters_data_ready(encrypters_data_ready_pe),
        .encrypters_ready(encrypters_ready_pe)
        // .state_out(state_out_p),
        // .key_out(key_out)
    );

    generate
        genvar e;
        for (e = 0; e < `NUM_ENCRYPTERS; e = e + 1) begin : encrypter_loop
            Encrypter e_inst (
                .clk(clk),
                .reset(reset),
                .data_in_p(encrypters_data_pe),
                .key_rotation_p(encrypters_key_rotation_pe),
                .prog_p(encrypters_program_pe[e]),
                .data_ready_in_p(encrypters_data_ready_pe[e]),
                .ready_p(encrypters_ready_pe[e]),
                .data_out_c(encrypters_data_ec[e]),
                .data_ready_out_c(encrypters_data_ready_ec[e]),
                .capture_c(encrypters_capture_ec[e])
            );
        end
    endgenerate

    Collector c_inst(
        .clk(clk),
        .reset(reset),
        .qspi_data(qspi_data_ct),
        .qspi_sending(qspi_sending_ct),
        .qspi_ready(qspi_ready_ct),
        .encrypters_data(encrypters_data_ec),
        .encrypters_data_ready(encrypters_data_ready_ec),
        .encrypters_capture(encrypters_capture_ec)
    );

    reg [31:0] key = 32'hB4352B93;
    integer fd_read, fd_write, i, j, bytes_sent = 0;
    reg [7:0] char_read, char_write;
    logic char_write_progress = 0;

    initial begin
        //fill spi_data_values with data from file
        if (`ENCRYPT) begin
            fd_read = $fopen("../data/unencrypted/starwarsscript.txt", "r");
        end else begin
            fd_read = $fopen("./TopLevel/encrypted_message.enc", "r");
        end

        if (fd_read == -1) begin
            $display("Error data file!");
            $finish;  // Exit simulation on error
        end

        if (`ENCRYPT) begin
            fd_write = $fopen("./TopLevel/encrypted_message.enc", "w");
        end else begin
            fd_write = $fopen("./TopLevel/decrypted_message.txt", "w");
        end
        if (fd_write == -1) begin
            $display("Error encrypted data file!");
            $finish;  // Exit simulation on error
        end
    end

    initial begin
        $dumpfile("TopLevel/top_level.vcd");
        $dumpvars(0, TopLevel);
        $display("Starting simulation");

        //set data on neg edge, read on the rising
        #2 reset = 1; #2 reset = 0;
        #2 prog_tp = 1; #2 prog_tp = 0;

        //send key
        while (!qspi_ready_tp) #2;
        #2 qspi_sending_tp = 1; #2
        for (i = `ENCRYPTER_QSPI_COUNT-1; i > -1; i = i - 1) begin
            qspi_data_tp[0] = key[i*4];
            qspi_data_tp[1] = key[i*4+1];
            qspi_data_tp[2] = key[i*4+2];
            qspi_data_tp[3] = key[i*4+3];
            #2;
            // $display("[KEY] 0x%x", qspi_data_tp);
        end
        qspi_sending_tp = 0;

        //send data
        while (!qspi_ready_tp) #2;
        #2 qspi_sending_tp = 1; #2
        while (!$feof(fd_read) && (bytes_sent <= `MAX_BYTES)) begin
            char_read = $fgetc(fd_read);
            // $display("[RAW] 0x%x", char_read);

            while (!qspi_ready_tp) #2;
            qspi_data_tp = char_read[7:4]; #2;
            // $display("[DAT] 0x%x", qspi_data_tp);

            while (!qspi_ready_tp) #2;
            qspi_data_tp = char_read[3:0]; #2;
            // $display("[DAT] 0x%x", qspi_data_tp);
            bytes_sent = bytes_sent + 1;
            // $display("Bytes sent: %d", bytes_sent);
        end
        #2 qspi_sending_tp = 0;

        while (qspi_sending_ct) #2;
        #4 $fclose(fd_read); $fclose(fd_write); $finish;
    end

    always begin
        #1 clk = ~clk;
        if (clk) begin
            if (qspi_sending_ct) begin
                if (char_write_progress == 0) begin
                    char_write_progress = 1;
                    char_write[7:4] = qspi_data_ct;
                end else begin
                    char_write_progress = 0;
                    char_write[3:0] = qspi_data_ct;
                    // $display("[ENC] 0x%x", char_write);
                    j = $fputc(char_write, fd_write);
                end
            end
        end
    end

endmodule

Icarus-Verliog-testing/TopLevel/top_level.vcd
$date
	Sun May 19 18:21:43 2024
$end
$version
	Icarus Verilog
$end
$timescale
	10ns
$end
$scope module TopLevel $end
$var wire 32 ! encrypters_data_ec0 [31:0] $end
$var wire 32 " encrypters_data_ec1 [31:0] $end
$var wire 1 # qspi_sending_ct $end
$var wire 1 $ qspi_ready_tp $end
$var wire 4 % qspi_data_ct [3:0] $end
$var wire 2 & encrypters_ready_pe [1:0] $end
$var wire 2 ' encrypters_program_pe [1:0] $end
$var wire 5 ( encrypters_key_rotation_pe [4:0] $end
$var wire 2 ) encrypters_data_ready_pe [1:0] $end
$var wire 2 * encrypters_data_ready_ec [1:0] $end
$var wire 32 + encrypters_data_pe [31:0] $end
$var wire 2 , encrypters_capture_ec [1:0] $end
$var reg 8 - char_read [7:0] $end
$var reg 8 . char_write [7:0] $end
$var reg 1 / char_write_progress $end
$var reg 1 0 clk $end
$var reg 32 1 key [31:0] $end
$var reg 1 2 prog_tp $end
$var reg 4 3 qspi_data_tp [3:0] $end
$var reg 1 4 qspi_ready_ct $end
$var reg 1 5 qspi_sending_tp $end
$var reg 1 6 reset $end
$var integer 32 7 bytes_sent [31:0] $end
$var integer 32 8 fd_read [31:0] $end
$var integer 32 9 fd_write [31:0] $end
$var integer 32 : i [31:0] $end
$var integer 32 ; j [31:0] $end
$scope begin encrypter_loop[0] $end
$var parameter 2 < e $end
$scope module e_inst $end
$var wire 1 = capture_c $end
$var wire 1 0 clk $end
$var wire 1 > data_ready_in_p $end
$var wire 1 ? prog_p $end
$var wire 1 6 reset $end
$var wire 5 @ key_rotation_p [4:0] $end
$var wire 32 A data_in_p [31:0] $end
$var reg 32 B data_in_store [31:0] $end
$var reg 32 C data_out_c [31:0] $end
$var reg 1 D data_ready_out_c $end
$var reg 32 E keyOrigin [31:0] $end
$var reg 32 F keyRotated [31:0] $end
$var reg 6 G offset [5:0] $end
$var reg 1 H ready_p $end
$var reg 3 I state [2:0] $end
$upscope $end
$upscope $end
$scope begin encrypter_loop[1] $end
$var parameter 2 J e $end
$scope module e_inst $end
$var wire 1 K capture_c $end
$var wire 1 0 clk $end
$var wire 1 L data_ready_in_p $end
$var wire 1 M prog_p $end
$var wire 1 6 reset $end
$var wire 5 N key_rotation_p [4:0] $end
$var wire 32 O data_in_p [31:0] $end
$var reg 32 P data_in_store [31:0] $end
$var reg 32 Q data_out_c [31:0] $end
$var reg 1 R data_ready_out_c $end
$var reg 32 S keyOrigin [31:0] $end
$var reg 32 T keyRotated [31:0] $end
$var reg 6 U offset [5:0] $end
$var reg 1 V ready_p $end
$var reg 3 W state [2:0] $end
$upscope $end
$upscope $end
$scope module c_inst $end
$var wire 1 0 clk $end
$var wire 2 X encrypters_data_ready [1:0] $end
$var wire 1 4 qspi_ready $end
$var wire 1 6 reset $end
$var reg 4 Y encrypter_data_index [3:0] $end
$var reg 32 Z encrypter_data_packet [31:0] $end
$var reg 2 [ encrypter_index [1:0] $end
$var reg 2 \ encrypters_capture [1:0] $end
$var reg 4 ] qspi_data [3:0] $end
$var reg 1 # qspi_sending $end
$var reg 2 ^ state [1:0] $end
$upscope $end
$scope module p_inst $end
$var wire 1 0 clk $end
$var wire 2 _ encrypters_ready [1:0] $end
$var wire 1 2 prog $end
$var wire 4 ` qspi_data [3:0] $end
$var wire 1 5 qspi_sending $end
$var wire 1 6 reset $end
$var reg 4 a encrypter_data_index [3:0] $end
$var reg 32 b encrypter_data_packet [31:0] $end
$var reg 2 c encrypter_index [1:0] $end
$var reg 32 d encrypters_data [31:0] $end
$var reg 2 e encrypters_data_ready [1:0] $end
$var reg 5 f encrypters_key_rotation [4:0] $end
$var reg 2 g encrypters_program [1:0] $end
$var reg 4 h key_index [3:0] $end
$var reg 5 i key_rotation [4:0] $end
$var reg 1 $ qspi_ready $end
$var reg 3 j state [2:0] $end
$upscope $end
$upscope $end
$enddefinitions $end
$comment Show the parameter values. $end
$dumpall
b1 J
b0 <
$end
#0
$dumpvars
b0 j
bx i
b1000 h
b0 g
bx f
bx e
bx d
bx c
b0 b
bx a
b0 `
b0 _
b0 ^
bx ]
b0 \
bx [
bx Z
bx Y
b0 X
b0 W
0V
b0 U
b0 T
b0 S
0R
b0 Q
b0 P
bx O
bx N
0M
xL
0K
b0 I
0H
b0 G
b0 F
b0 E
0D
b0 C
b0 B
bx A
bx @
0?
x>
0=
bx ;
bx :
b10000000000000000000000000000100 9
b10000000000000000000000000000011 8
b0 7
06
05
14
b0 3
02
b10110100001101010010101110010011 1
00
0/
bx .
bx -
b0 ,
bx +
b0 *
bx )
bx (
b0 '
b0 &
bx %
0$
0#
b0 "
b0 !
$end
#1
10
#2
1$
00
16
#3
b0 [
b1 ^
10
#4
00
06
#5
10
#6
00
12
#7
b1 j
10
#8
00
02
#9
10
#10
00
15
#11
b10 j
10
#12
00
b1011 3
b1011 `
b111 :
#13
b10110000000000000000000000000000 b
b111 h
10
#14
00
b100 3
b100 `
b110 :
#15
b10110100000000000000000000000000 b
b110 h
10
#16
00
b11 3
b11 `
b101 :
#17
b10110100001100000000000000000000 b
b101 h
10
#18
00
b101 3
b101 `
b100 :
#19
b10110100001101010000000000000000 b
b100 h
10
#20
00
b10 3
b10 `
b11 :
#21
b10110100001101010010000000000000 b
b11 h
10
#22
00
b1011 3
b1011 `
b10 :
#23
b10110100001101010010101100000000 b
b10 h
10
#24
00
b1001 3
b1001 `
b1 :
#25
b10110100001101010010101110010000 b
b1 h
10
#26
00
b11 3
b11 `
b0 :
#27
0$
b11 j
b10110100001101010010101110010011 b
b0 h
10
#28
1M
1?
b100 j
b11 '
b11 g
b10 c
b10110100001101010010101110010011 +
b10110100001101010010101110010011 A
b10110100001101010010101110010011 O
b10110100001101010010101110010011 d
00
05
b11111111111111111111111111111111 :
#29
b1 I
b1 W
10
#30
00
#31
b10 W
b10110100001101010010101110010011 S
b10 I
b10110100001101010010101110010011 E
10
#32
1V
b11 &
b11 _
1H
00
#33
b0 c
b0 j
10
#34
0M
0?
b0 '
b0 g
1$
00
#35
10
#36
00
#37
10
#38
00
15
#39
b101 j
0L
0>
b0 i
b0 )
b0 e
b1000 a
10
#40
00
b101 3
b101 `
b1010011 -
#41
b1010100001101010010101110010011 b
b111 a
10
#42
00
b11 3
b11 `
#43
b1010011001101010010101110010011 b
b110 a
10
#44
00
b101 3
b101 `
b1010100 -
b1 7
#45
b1010011010101010010101110010011 b
b101 a
10
#46
00
b100 3
b100 `
#47
b1010011010101000010101110010011 b
b100 a
10
#48
00
b1000001 -
b10 7
#49
b1010011010101000100101110010011 b
b11 a
10
#50
00
b1 3
b1 `
#51
b1010011010101000100000110010011 b
b10 a
10
#52
00
b101 3
b101 `
b1010010 -
b11 7
#53
b1010011010101000100000101010011 b
b1 a
10
#54
00
b10 3
b10 `
#55
b1010011010101000100000101010010 b
b0 a
10
#56
1>
b1 i
b1 c
b1 )
b1 e
b0 (
b0 @
b0 N
b0 f
b1010011010101000100000101010010 +
b1010011010101000100000101010010 A
b1010011010101000100000101010010 O
b1010011010101000100000101010010 d
b1000 a
00
b100000 -
b100 7
#57
b11 I
b100011010101000100000101010010 b
b111 a
10
#58
0>
b0 )
b0 e
00
b0 3
b0 `
#59
b100000010101000100000101010010 b
b110 a
b100 I
b10110100001101010010101110010011 F
b10 &
b10 _
0H
b1010011010101000100000101010010 B
10
#60
b1 *
b1 X
1D
b11100111011000010110101011000001 !
b11100111011000010110101011000001 C
00
b101 3
b101 `
b1010111 -
b101 7
#61
b10 ^
b101 a
b1000 Y
b11100111011000010110101011000001 Z
10
#62
1=
b1 ,
b1 \
b1110 %
b1110 ]
b111 Y
1#
b11 ^
00
b111 3
b111 `
#63
b101 I
b100000010101110100000101010010 b
b100 a
b1110xxxx .
1/
10
#64
0=
b0 ,
b0 \
b10 I
b111 %
b111 ]
b110 Y
b11 &
b11 _
1H
b0 *
b0 X
0D
00
b100 3
b100 `
b1000001 -
b110 7
#65
b11 a
b0 ;
b11100111 .
0/
10
#66
b110 %
b110 ]
b101 Y
00
b1 3
b1 `
#67
b10 a
b1100111 .
1/
10
#68
b1 %
b1 ]
b100 Y
00
b101 3
b101 `
b1010010 -
b111 7
#69
b1 a
b1100001 .
0/
10
#70
b110 %
b110 ]
b11 Y
00
b10 3
b10 `
#71
b0 a
1/
10
#72
1L
b1010 %
b1010 ]
b10 Y
b10 i
b0 c
b10 )
b10 e
b1 (
b1 @
b1 N
b1 f
b100000010101110100000101010010 +
b100000010101110100000101010010 A
b100000010101110100000101010010 O
b100000010101110100000101010010 d
b1000 a
00
b101 3
b101 `
b1010011 -
b1000 7
#73
b11 W
b1010000010101110100000101010010 b
b111 a
b1101010 .
0/
10
#74
0L
b0 )
b0 e
b1100 %
b1100 ]
b1 Y
00
b11 3
b11 `
#75
b1010011010101110100000101010010 b
b110 a
b100 W
b1101000011010100101011100100111 T
b1 &
b1 _
0V
b1 U
b100000010101110100000101010010 P
b11001010 .
1/
10
#76
b1 ^
b1 [
b1 %
b1 ]
b0 Y
b10 *
b10 X
1R
b1001000001111010001011001110101 "
b1001000001111010001011001110101 Q
00
b0 3
b0 `
b1010 -
b1001 7
#77
b10 ^
b1010011000001110100000101010010 b
b101 a
b1000 Y
b1001000001111010001011001110101 Z
b11000001 .
0/
10
#78
1K
b10 ,
b10 \
b100 %
b100 ]
b111 Y
b11 ^
00
b1010 3
b1010 `
#79
b101 W
b1010011000010100100000101010010 b
b100 a
b1000001 .
1/
10
#80
0K
b0 ,
b0 \
b10 W
b1000 %
b1000 ]
b110 Y
b11 &
b11 _
1V
b0 *
b0 X
0R
00
b0 3
b0 `
b1010 7
#81
b1010011000010100000000101010010 b
b11 a
b1001000 .
0/
10
#82
b11 %
b11 ]
b101 Y
00
b1010 3
b1010 `
#83
b1010011000010100000101001010010 b
b10 a
b111000 .
1/
10
#84
b1101 %
b1101 ]
b100 Y
00
b100 3
b100 `
b1000101 -
b1011 7
#85
b1010011000010100000101001000010 b
b1 a
b111101 .
0/
10
#86
b1 %
b1 ]
b11 Y
00
b101 3
b101 `
#87
b1010011000010100000101001000101 b
b0 a
b11101 .
1/
10
#88
1>
b110 %
b110 ]
b10 Y
b11 i
b1 c
b1 )
b1 e
b10 (
b10 @
b10 N
b10 f
b1010011000010100000101001000101 +
b1010011000010100000101001000101 A
b1010011000010100000101001000101 O
b1010011000010100000101001000101 d
b1000 a
00
b111 3
b111 `
b1110000 -
b1100 7
#89
b11 I
b1110011000010100000101001000101 b
b111 a
b10110 .
0/
10
#90
0>
b0 )
b0 e
b111 %
b111 ]
b1 Y
00
b0 3
b0 `
#91
b1110000000010100000101001000101 b
b110 a
b100 I
b11010000110101001010111001001110 F
b10 &
b10 _
0H
b10 G
b1010011000010100000101001000101 B
b1110110 .
1/
10
#92
b1 ^
b0 [
b101 %
b101 ]
b0 Y
b1 *
b1 X
1D
b10000011110111101010010000001011 !
b10000011110111101010010000001011 C
00
b110 3
b110 `
b1101001 -
b1101 7
#93
b10 ^
b1110000011010100000101001000101 b
b101 a
b1000 Y
b10000011110111101010010000001011 Z
b1110101 .
0/
10
#94
1=
b1 ,
b1 \
b1000 %
b1000 ]
b111 Y
b11 ^
00
b1001 3
b1001 `
#95
b101 I
b1110000011010010000101001000101 b
b100 a
b10000101 .
1/
10
