Icarus-Verliog-testing/Constants/constants.vh
//DEFINE CONSTANTS
// `define KEY_WIDTH 16 // width of the key. In multiples of 4.
// `define KEY_QSPI_COUNT `KEY_WIDTH/4 // number of QSPI transactions per key sent in LSB. 
// `define KEY_QSPI_COUNT_REG $clog2(`KEY_QSPI_COUNT+1) // register size required to count the current QSPI transaction of the key + 1. log2(`KEY_QSPI_COUNT+1)

`define ENCRYPTER_WIDTH 32 // width of the bus between the Paralellizer and Encrypter, and the Encrypter and Collector. In multiples of 4.
`define ENCRYPTER_WIDTH_COUNT_REG $clog2(`ENCRYPTER_WIDTH+1) // register size required to count the current bit of the encrypter bus + 1. log2(`ENCRYPTER_WIDTH+1). (Verilog doesn't like me so i need a for loop)
`define ENCRYPTER_QSPI_COUNT `ENCRYPTER_WIDTH/4 // number of QSPI transactions per Encrypter.
`define ENCRYPTER_QSPI_COUNT_REG $clog2(`ENCRYPTER_QSPI_COUNT+1) // register size required to count the current QSPI transaction of the Encrypter + 1. log2(`ENCRYPTER_QSPI_COUNT+1)

`define KEY_ROTATION_WIDTH $clog2(`ENCRYPTER_WIDTH) // width of the key rotation bus between Paralellizer and Encrypter. log2(`KEY_WIDTH)
`define KEY_ROTATION_WIDTH_COUNT_REG $clog2(`KEY_ROTATION_WIDTH+1) // register size required to count the current bit of the key rotation bus + 1. log2(`KEY_ROTATION_WIDTH+1). (Verilog doesn't like me so i need a for loop)

// `define KEY_ENCRYPTER_COUNT `KEY_WIDTH/`ENCRYPTER_WIDTH // number of Encrypters transactions per key. `KEY_WIDTH/`ENCRYPTER_WIDTH
// `define KEY_ENCRYPTER_COUNT_REG $clog2(`KEY_ENCRYPTER_COUNT+1) // register size required to count the current Encrypter transaction of the key + 1. log2(`KEY_ENCRYPTER_COUNT+1)

`define NUM_ENCRYPTERS 2 // number of Encrypters
`define NUM_ENCRYPTERS_REG $clog2(`NUM_ENCRYPTERS+1) // register size required to count the current Encrypter + 1. log2(`NUM_ENCRYPTERS+1)

Icarus-Verliog-testing/Collector/collector.sv
`include "./Constants/constants.vh"
`define IDLE 2'b00
`define WAITING 2'b01
`define SENDING 2'b10


module Collector(
    input wire clk,
    input wire reset,
    //QSPI
    
    output reg [3:0] qspi_data,
    output reg qspi_sending = 0,
    input wire qspi_ready,
    
    //To encrypters
    input wire [`ENCRYPTER_WIDTH-1:0] encrypters_data  [`NUM_ENCRYPTERS-1:0],
    input wire [`NUM_ENCRYPTERS-1:0] encrypters_data_ready,
    output reg [`NUM_ENCRYPTERS-1:0] encrypters_capture,
    //Watchers

    output reg [1:0] state_out,
    output reg [`ENCRYPTER_WIDTH-1:0] encrypter_data_packe_out,
    
    output reg [`ENCRYPTER_WIDTH_COUNT_REG-1:0] encrypter_data_subindex_out,
    output reg [`NUM_ENCRYPTERS_REG-1:0] encrypter_index_out,
    output reg [`ENCRYPTER_QSPI_COUNT_REG-1:0] encrypter_data_index_out    
); // 4-bit collector

    reg [1:0] state = `IDLE;

    reg [`ENCRYPTER_WIDTH-1:0] encrypter_data_packet;
    reg [`ENCRYPTER_WIDTH_COUNT_REG-1:0] encrypter_data_subindex;

    reg [`NUM_ENCRYPTERS_REG-1:0] encrypter_index;

    reg [`ENCRYPTER_QSPI_COUNT_REG-1:0] encrypter_data_index;

    
    assign state_out = state;
    assign encrypter_data_packe_out = encrypter_data_packet;
    assign encrypter_data_subindex_out = encrypter_data_subindex;
    assign encrypter_index_out = encrypter_index;
    assign encrypter_data_index_out = encrypter_data_index;


    

    always @(posedge reset) begin
        state <= `WAITING;
        encrypter_index <= 0;
    end  


    always @(posedge clk) begin
        if (state == `WAITING) begin
            if(encrypters_data_ready[encrypter_index]) begin
                for (encrypter_data_subindex = 0; encrypter_data_subindex < `ENCRYPTER_WIDTH; encrypter_data_subindex = encrypter_data_subindex + 1) begin
                    encrypter_data_packet[encrypter_data_subindex] = encrypters_data[encrypter_index][encrypter_data_subindex];
                end
                state <= `SENDING;
                encrypter_data_index = 0;
            end
        end
    end 

    always @(negedge clk) begin 
        if (encrypters_capture[encrypter_index]) encrypters_capture[encrypter_index] <= 0;

        if (state == `SENDING) begin  encrypters_capture[encrypter_index] <= 1;  
            if (encrypter_data_index == 0) encrypters_capture[encrypter_index] <= 1;  
                if(qspi_ready) begin
                    qspi_sending = 1;
                    qspi_data[0] = encrypter_data_packet[encrypter_data_index*4];
                    qspi_data[1] = encrypter_data_packet[encrypter_data_index*4+1]; 
                    qspi_data[2] = encrypter_data_packet[encrypter_data_index*4+2];
                    qspi_data[3] = encrypter_data_packet[encrypter_data_index*4+3];  
                    encrypter_data_index = encrypter_data_index + 1;   
                    if(encrypter_data_index == `ENCRYPTER_QSPI_COUNT) begin
                        qspi_sending = 0;
                            encrypter_index = encrypter_index + 1;
                            if (encrypter_index == `NUM_ENCRYPTERS) begin
                                encrypter_index = 0;
                            end
                        state <= `WAITING; 
                    end           
                end
            else qspi_sending = 0;   
        end     
    end 


endmodule

Icarus-Verliog-testing/Collector/collector_tb.sv
`timescale 1ns / 1ns
`include "./Constants/constants.vh"
`include "./Collector/collector.sv"


module Collector_tb;

  reg clk=1'b0;
  reg reset;

  // QSPI signals
  wire [3:0] qspi_data;
  wire qspi_sending;
  reg qspi_ready;

  // Encrypters signals
  reg [`ENCRYPTER_WIDTH-1:0] encrypters_data [0:`NUM_ENCRYPTERS-1];
  reg [`NUM_ENCRYPTERS-1:0] encrypters_data_ready;
  wire [`NUM_ENCRYPTERS-1:0] encrypters_capture;

  // Watchers signals
  wire [1:0] state_out;
  wire [`ENCRYPTER_WIDTH-1:0] encrypter_data_packe_out;
  // wire [`ENCRYPTER_WIDTH_COUNT_REG-1:0] encrypter_data_subindex;
  // wire [`NUM_ENCRYPTERS_REG-1:0] encrypter_index;
  // wire [`ENCRYPTER_QSPI_COUNT_REG-1:0] encrypter_data_index;
  
  // DUT (Device Under Test)
  Collector uut (
    .clk(clk),
    .reset(reset),
    .qspi_data(qspi_data),
    .qspi_sending(qspi_sending),
    .qspi_ready(qspi_ready),
    .encrypters_data(encrypters_data),
    .encrypters_data_ready(encrypters_data_ready),
    .encrypters_capture(encrypters_capture),
    .state_out(state_out),
    .encrypter_data_packe_out(encrypter_data_packe_out),
    .encrypter_data_subindex_out(encrypter_data_subindex_out),
    .encrypter_index_out(encrypter_index_out),
    .encrypter_data_index_out(encrypter_data_index_out)
  );

  // Clock generation
  always begin
    #5 clk = ~clk;
  end

    // Reset generation
    initial begin
      $display("Start test");

      $dumpfile("wave.vcd");
      $dumpvars(0, Collector_tb);

      // initializing to zero 
      reset = 1'b0;
      qspi_ready = 1'b1;
      encrypters_data_ready = 0;

      #10
      
      // checking reset
      reset = 1'b1;
      #20
      

      // checking if the data is ready
      encrypters_data[0] = 32'h12345678;
      encrypters_data_ready[0] = 1'b1;
      
      #100; // Add a delay here
      encrypters_data_ready[0] = 1'b0;
      encrypters_data[1] = 32'h123458;
      encrypters_data_ready[1] = 1'b1;

      #1000
      $finish; 
    end

endmodule

Icarus-Verliog-testing/Collector/wave.vcd
$date
	Tue May 07 12:29:54 2024
$end
$version
	Icarus Verilog
$end
$timescale
	1ns
$end
$scope module Collector_tb $end
$var wire 2 ! state_out [1:0] $end
$var wire 1 " qspi_sending $end
$var wire 4 # qspi_data [3:0] $end
$var wire 4 $ encrypters_capture [3:0] $end
$var wire 1 % encrypter_index_out $end
$var wire 1 & encrypter_data_subindex_out $end
$var wire 16 ' encrypter_data_packe_out [15:0] $end
$var wire 1 ( encrypter_data_index_out $end
$var reg 1 ) clk $end
$var reg 4 * encrypters_data_ready [3:0] $end
$var reg 1 + qspi_ready $end
$var reg 1 , reset $end
$scope module uut $end
$var wire 1 ) clk $end
$var wire 3 - encrypter_data_index_out [2:0] $end
$var wire 16 . encrypter_data_packe_out [15:0] $end
$var wire 5 / encrypter_data_subindex_out [4:0] $end
$var wire 3 0 encrypter_index_out [2:0] $end
$var wire 4 1 encrypters_data_ready [3:0] $end
$var wire 1 + qspi_ready $end
$var wire 1 , reset $end
$var wire 2 2 state_out [1:0] $end
$var reg 3 3 encrypter_data_index [2:0] $end
$var reg 16 4 encrypter_data_packet [15:0] $end
$var reg 5 5 encrypter_data_subindex [4:0] $end
$var reg 3 6 encrypter_index [2:0] $end
$var reg 4 7 encrypters_capture [3:0] $end
$var reg 4 8 qspi_data [3:0] $end
$var reg 1 " qspi_sending $end
$var reg 2 9 state [1:0] $end
$upscope $end
$upscope $end
$enddefinitions $end
$comment Show the parameter values. $end
$dumpall
$end
#0
$dumpvars
b0 9
bx 8
bx 7
bx 6
bx 5
bx 4
bx 3
b0 2
b0 1
bx 0
bx /
bx .
bx -
0,
1+
b0 *
0)
x(
bx '
x&
x%
bx $
bx #
0"
b0 !
$end
#5
1)
#10
0%
b0 0
b0 6
b1 !
b1 2
b1 9
0)
1,
#15
1)
#20
0)
#25
1)
#30
0)
b1 *
b1 1
#35
b10 !
b10 2
b10 9
0(
0&
b0 -
b0 3
b101011001111000 '
b101011001111000 .
b101011001111000 4
b10000 /
b10000 5
1)
#40
bx1 $
bx1 7
1(
b1 -
b1 3
b1000 #
b1000 8
1"
0)
#45
1)
#50
bx1 $
bx1 7
0(
b10 -
b10 3
b111 #
b111 8
0)
#55
1)
#60
bx1 $
bx1 7
1(
b11 -
b11 3
b110 #
b110 8
0)
#65
1)
#70
b1 !
b1 2
b1 9
bx1 $
bx1 7
1%
0(
b1 0
b1 6
0"
b100 -
b100 3
b101 #
b101 8
0)
#75
1)
#80
0)
#85
1)
#90
0)
#95
1)
#100
0)
#105
1)
#110
0)
#115
1)
#120
0)
#125
1)
#130
0)
b10 *
b10 1
#135
b10 !
b10 2
b10 9
b0 -
b0 3
b11010001011000 '
b11010001011000 .
b11010001011000 4
b10000 /
b10000 5
1)
#140
bx11 $
bx11 7
1(
b1 -
b1 3
b1000 #
b1000 8
1"
0)
#145
1)
#150
bx11 $
bx11 7
0(
b10 -
b10 3
b101 #
b101 8
0)
#155
1)
#160
bx11 $
bx11 7
1(
b11 -
b11 3
b100 #
b100 8
0)
#165
1)
#170
b1 !
b1 2
b1 9
bx11 $
bx11 7
0%
0(
b10 0
b10 6
0"
b100 -
b100 3
b11 #
b11 8
0)
