Icarus-Verliog-testing/Constants/constants.vh
//DEFINE CONSTANTS
// `define KEY_WIDTH 16 // width of the key. In multiples of 4.
// `define KEY_QSPI_COUNT `KEY_WIDTH/4 // number of QSPI transactions per key sent in LSB. 
// `define KEY_QSPI_COUNT_REG $clog2(`KEY_QSPI_COUNT+1) // register size required to count the current QSPI transaction of the key + 1. log2(`KEY_QSPI_COUNT+1)

`define ENCRYPTER_WIDTH 32 // width of the bus between the Paralellizer and Encrypter, and the Encrypter and Collector. In multiples of 4.
`define ENCRYPTER_WIDTH_COUNT_REG $clog2(`ENCRYPTER_WIDTH+1) // register size required to count the current bit of the encrypter bus + 1. log2(`ENCRYPTER_WIDTH+1). (Verilog doesn't like me so i need a for loop)
`define ENCRYPTER_QSPI_COUNT `ENCRYPTER_WIDTH/4 // number of QSPI transactions per Encrypter.
`define ENCRYPTER_QSPI_COUNT_REG $clog2(`ENCRYPTER_QSPI_COUNT+1) // register size required to count the current QSPI transaction of the Encrypter + 1. log2(`ENCRYPTER_QSPI_COUNT+1)

`define KEY_ROTATION_WIDTH $clog2(`ENCRYPTER_WIDTH) // width of the key rotation bus between Paralellizer and Encrypter. log2(`KEY_WIDTH)
`define KEY_ROTATION_WIDTH_COUNT_REG $clog2(`KEY_ROTATION_WIDTH+1) // register size required to count the current bit of the key rotation bus + 1. log2(`KEY_ROTATION_WIDTH+1). (Verilog doesn't like me so i need a for loop)

// `define KEY_ENCRYPTER_COUNT `KEY_WIDTH/`ENCRYPTER_WIDTH // number of Encrypters transactions per key. `KEY_WIDTH/`ENCRYPTER_WIDTH
// `define KEY_ENCRYPTER_COUNT_REG $clog2(`KEY_ENCRYPTER_COUNT+1) // register size required to count the current Encrypter transaction of the key + 1. log2(`KEY_ENCRYPTER_COUNT+1)

`define NUM_ENCRYPTERS 2 // number of Encrypters
`define NUM_ENCRYPTERS_REG $clog2(`NUM_ENCRYPTERS+1) // register size required to count the current Encrypter + 1. log2(`NUM_ENCRYPTERS+1)

Icarus-Verliog-testing/Parallelizer/parallelizer.sv
`include "./Constants/constants.vh"

`define STATE_IDLE 3'b000
`define STATE_PROGRAMMING 3'b001
`define STATE_RECEIVING_KEY 3'b010
`define STATE_PROGRAMMING_ENCRYPTERS 3'b011
`define STATE_WAITING_FOR_READY_ENCRYPTERS 3'b100
`define STATE_ENCRYPTING 3'b101

module Parallelizer (
    input wire clk,
    input wire reset,
    //QSPI
    input wire [3:0] qspi_data,
    input wire qspi_sending,
    output reg qspi_ready,
    //Program
    input wire prog,
    //To encrypters
    output reg [`ENCRYPTER_WIDTH-1:0] encrypters_data,
    output reg [`KEY_ROTATION_WIDTH-1:0] encrypters_key_rotation,
    output reg [`NUM_ENCRYPTERS-1:0] encrypters_program,
    output reg [`NUM_ENCRYPTERS-1:0] encrypters_data_ready,
    input wire [`NUM_ENCRYPTERS-1:0] encrypters_ready
    //Watchers
    // output reg [2:0] state_out,
    // output reg [`ENCRYPTER_WIDTH-1:0] key_out
    // output reg [`KEY_ROTATION_WIDTH-1:0] key_rotation_out,
    // output reg [`ENCRYPTER_QSPI_COUNT_REG-1:0] key_index_out,
    // output reg [`ENCRYPTER_WIDTH-1:0] encrypter_data_packet_out,
    // output reg [`ENCRYPTER_QSPI_COUNT_REG-1:0] encrypter_data_index_out,
    // output reg [`NUM_ENCRYPTERS_REG-1:0] encrypter_index_out
);

reg [2:0] state = `STATE_IDLE;
reg [`ENCRYPTER_WIDTH-1:0] key;
reg [`ENCRYPTER_QSPI_COUNT_REG-1:0] key_index;
reg [`KEY_ROTATION_WIDTH-1:0] key_rotation;

reg [`ENCRYPTER_WIDTH-1:0] encrypter_data_packet;

reg [`ENCRYPTER_QSPI_COUNT_REG-1:0] encrypter_data_index;
reg [`NUM_ENCRYPTERS_REG-1:0] encrypter_index;
integer i;

initial begin
    // assign state_out = state;
    // assign key_out = key;
    // assign key_rotation_out = key_rotation;
    // assign key_index_out = key_index;
    // assign encrypter_data_packet_out = encrypter_data_packet;
    // assign encrypter_data_index_out = encrypter_data_index;
    // assign encrypter_index_out = encrypter_index;

    qspi_ready = 1'b0;
    encrypters_program = 0;
    key = 0;
    key_index = `ENCRYPTER_QSPI_COUNT;
end

//read on positive
always @(posedge clk) begin

    if (reset) begin
        state <= `STATE_IDLE;
        qspi_ready = 1'b1;
    end

    case (state)

        `STATE_IDLE: begin 
            if (qspi_sending) begin
                state <= `STATE_ENCRYPTING;
                encrypter_index = 0;
                encrypter_data_index = `ENCRYPTER_QSPI_COUNT;
                encrypters_data_ready = 0;
                key_rotation = 0;
            end
            if (prog) begin
                state <= `STATE_PROGRAMMING;
                qspi_ready = 1'b1;
                key_index = `ENCRYPTER_QSPI_COUNT;
            end
        end

        `STATE_PROGRAMMING: if (qspi_sending) state <= `STATE_RECEIVING_KEY;

        `STATE_RECEIVING_KEY: begin 
            if (~qspi_sending) begin
                state = `STATE_IDLE;
            end else begin
                key_index = key_index - 1;
                key[key_index*4] = qspi_data[0];
                key[key_index*4+1] = qspi_data[1];
                key[key_index*4+2] = qspi_data[2];
                key[key_index*4+3] = qspi_data[3];
                if (key_index == 0) begin
                    state = `STATE_PROGRAMMING_ENCRYPTERS;
                    qspi_ready = 1'b0;
                end
            end
        end

        `STATE_WAITING_FOR_READY_ENCRYPTERS: begin
            if (& encrypters_ready) begin
                state = `STATE_IDLE;
                encrypter_index = 0;
            end
        end

        `STATE_ENCRYPTING: begin
            if (~qspi_sending) begin
                state = `STATE_IDLE;
            end else begin
                //read spi data
                encrypter_data_index = encrypter_data_index - 1;
                encrypter_data_packet[encrypter_data_index*4] = qspi_data[0];
                encrypter_data_packet[encrypter_data_index*4+1] = qspi_data[1];
                encrypter_data_packet[encrypter_data_index*4+2] = qspi_data[2];
                encrypter_data_packet[encrypter_data_index*4+3] = qspi_data[3];
            end
        end

        default:;

    endcase
end

//write on negative
always @(negedge clk) begin
    case (state)

        `STATE_IDLE: begin    
            qspi_ready = 1'b1;
            encrypters_program = 0;
        end

        `STATE_PROGRAMMING_ENCRYPTERS: begin
            encrypters_data = key;
            for (encrypter_index = 0; encrypter_index < `NUM_ENCRYPTERS; encrypter_index = encrypter_index + 1) begin
                encrypters_program[encrypter_index] = 1'b1;
            end
            state = `STATE_WAITING_FOR_READY_ENCRYPTERS;
        end

        `STATE_ENCRYPTING: begin
            //keep ecrypter data index high for only 1 posedge clock cycle
            if (encrypter_index == 0) begin
                if (encrypters_data_ready[`NUM_ENCRYPTERS-1]) encrypters_data_ready[`NUM_ENCRYPTERS-1] = 0;
            end else begin
                if (encrypters_data_ready[encrypter_index-1]) encrypters_data_ready[encrypter_index-1] = 0;
            end

            if (encrypter_data_index == 0) begin
                //when packet full, send to encrypters
                encrypter_data_index = `ENCRYPTER_QSPI_COUNT;
                
                //check if encrypter is ready for new data
                if (encrypters_ready[encrypter_index]) begin
                    //put packet on encrypter bus
                    encrypters_data = encrypter_data_packet;
                    //put key rot on encrypter bus
                    encrypters_key_rotation = key_rotation;

                    //signal data is ready
                    encrypters_data_ready[encrypter_index] = 1'b1;

                    //move to next encrypter
                    encrypter_index = encrypter_index + 1;
                    if (encrypter_index == `NUM_ENCRYPTERS) encrypter_index = 0;

                    //move to next key rotation
                    key_rotation = key_rotation + 1;
                    if (key_rotation == `ENCRYPTER_WIDTH) key_rotation = 0;

                    //ready for more data as current data has been written
                    qspi_ready = 1'b1;
                end else begin
                    //if encrypter is not ready, wait for it
                    qspi_ready = 1'b0;
                end
            end
        end

        default:;

    endcase
end

endmodule

Icarus-Verliog-testing/Parallelizer/parallelizer_tb.sv
`timescale 1ns / 1ns
`include "./Constants/constants.vh"
`include "./Parallelizer/parallelizer.sv"

module Parallelizer_tb;

    reg clk; 
    reg reset;
    //QSPI
    reg [3:0] qspi_data;
    reg qspi_sending;
    wire qspi_ready;
    //Program
    reg prog;
    //To encrypters
    wire[`ENCRYPTER_WIDTH-1:0] encrypters_data;
    wire [`KEY_ROTATION_WIDTH-1:0] encrypters_key_rotation;
    wire [`NUM_ENCRYPTERS-1:0] encrypters_program;
    wire [`NUM_ENCRYPTERS-1:0] encrypters_data_ready;
    reg [`NUM_ENCRYPTERS-1:0] encrypters_ready;
    //Watchers
    wire [2:0] state_out;
    wire [`ENCRYPTER_WIDTH-1:0] key_out;
    wire [`KEY_ROTATION_WIDTH-1:0] key_rotation_out;
    wire [`ENCRYPTER_QSPI_COUNT_REG-1:0] key_index_out;
    wire [`ENCRYPTER_WIDTH-1:0] encrypter_data_packet_out;
    wire [`ENCRYPTER_QSPI_COUNT_REG-1:0] encrypter_data_index_out;
    wire [`NUM_ENCRYPTERS_REG-1:0] encrypter_index_out;
    reg [`ENCRYPTER_WIDTH-1:0] encrypters_data_slice;

    Parallelizer uut(
        .clk(clk),
        .reset(reset),
        .qspi_data(qspi_data),
        .qspi_sending(qspi_sending),
        .qspi_ready(qspi_ready),
        .prog(prog),
        .encrypters_data(encrypters_data),
        .encrypters_key_rotation(encrypters_key_rotation),
        .encrypters_program(encrypters_program),
        .encrypters_data_ready(encrypters_data_ready),
        .encrypters_ready(encrypters_ready)
        // .state_out(state_out)
        // .key_out(key_out),
        // .key_rotation_out(key_rotation_out),
        // .key_index_out(key_index_out),
        // .encrypter_data_packet_out(encrypter_data_packet_out),
        // .encrypter_data_index_out(encrypter_data_index_out),
        // .encrypter_index_out(encrypter_index_out)
    );
    
    reg [3:0] spi_data_values[256:0];
    reg [3:0] encrypters_delays [`NUM_ENCRYPTERS-1:0];
    integer fd, i, j;

    initial begin
        //fill spi_data_values with data from file
        fd = $fopen("./Constants/qspi_data.csv", "r");
        if (fd == -1) begin
            $display("Error opening file!");
            $finish;  // Exit simulation on error
        end
        for (i = 0; i < 256; i++) begin
            j = $fscanf(fd, "%h", spi_data_values[i]);
        end
        $fclose(fd);
        $display(spi_data_values[0]);

        for (j = 0; j < `NUM_ENCRYPTERS-1; j = j + 1) begin
            encrypters_delays[j] = 0;
        end
    end

    initial begin
        $dumpfile("Parallelizer/parallelizer_tb.vcd");
        $dumpvars(0, Parallelizer_tb);
        $display("Starting parallelizer testbench");
        clk = 0;
        reset = 0;
        qspi_data = 0;
        qspi_sending = 0;
        prog = 0;
        encrypters_ready = 0;


        //expected use
        //set data on neg edge, read on the rising
        #2 reset = 1; #2 reset = 0;
        #2 prog = 1; #2 prog = 0;
        //send key
        #2 qspi_sending = 1;
        for (i = 0; i < `ENCRYPTER_QSPI_COUNT; i = i + 1) begin
            qspi_data = spi_data_values[i];
            $display("Setting qspi_data to 0x%h", spi_data_values[i]);
            #2;
        end
        qspi_sending = 0;

        #10;
        //simulate encrypters receiving key after parallelizer send it out
        for (i = 0; i < `NUM_ENCRYPTERS; i = i + 1) begin
            encrypters_ready[i] = 1;
            #1;
        end

        //start encrypting data. can only be started from idle state
        #4 qspi_sending = 1;
        for (i = `ENCRYPTER_QSPI_COUNT; i < 200; i = i + 1) begin
            qspi_data = spi_data_values[i];
            $display("Setting qspi_data to 0x%h", spi_data_values[i]);
            #2;
        end
        #2 qspi_sending = 0;
        #10
        $display("Ending parallelizer testbench");
        $finish;
    end

    always begin
        #1 clk = ~clk;
        //update slice of encrypters data to be seen on gktwave
        // encrypters_data_slice[`ENCRYPTER_WIDTH-1:0] = encrypters_data[0][`ENCRYPTER_WIDTH-1:0];
        if (clk)
            for (j = 0; j < `NUM_ENCRYPTERS-1; j = j + 1) begin
                if (encrypters_ready[j] && encrypters_data_ready[j]) begin
                    encrypters_ready[j] = 0;
                end
                if (encrypters_data_ready[j]) encrypters_delays[j] = 4;
                if (encrypters_delays[j]) begin
                    if (encrypters_delays[j] == 1) encrypters_ready[j] = 1;
                    encrypters_delays[j] = encrypters_delays[j] - 1;
                end
            end
    end

endmodule

Icarus-Verliog-testing/Parallelizer/parallelizer_tb.vcd
$date
	Sun May 19 14:31:24 2024
$end
$version
	Icarus Verilog
$end
$timescale
	1ns
$end
$scope module Parallelizer_tb $end
$var wire 1 ! qspi_ready $end
$var wire 2 " encrypters_program [1:0] $end
$var wire 5 # encrypters_key_rotation [4:0] $end
$var wire 2 $ encrypters_data_ready [1:0] $end
$var wire 32 % encrypters_data [31:0] $end
$var reg 1 & clk $end
$var reg 2 ' encrypters_ready [1:0] $end
$var reg 1 ( prog $end
$var reg 4 ) qspi_data [3:0] $end
$var reg 1 * qspi_sending $end
$var reg 1 + reset $end
$var integer 32 , fd [31:0] $end
$var integer 32 - i [31:0] $end
$var integer 32 . j [31:0] $end
$scope module uut $end
$var wire 1 & clk $end
$var wire 2 / encrypters_ready [1:0] $end
$var wire 1 ( prog $end
$var wire 4 0 qspi_data [3:0] $end
$var wire 1 * qspi_sending $end
$var wire 1 + reset $end
$var reg 4 1 encrypter_data_index [3:0] $end
$var reg 32 2 encrypter_data_packet [31:0] $end
$var reg 2 3 encrypter_index [1:0] $end
$var reg 32 4 encrypters_data [31:0] $end
$var reg 2 5 encrypters_data_ready [1:0] $end
$var reg 5 6 encrypters_key_rotation [4:0] $end
$var reg 2 7 encrypters_program [1:0] $end
$var reg 32 8 key [31:0] $end
$var reg 4 9 key_index [3:0] $end
$var reg 5 : key_rotation [4:0] $end
$var reg 1 ! qspi_ready $end
$var reg 3 ; state [2:0] $end
$upscope $end
$upscope $end
$enddefinitions $end
$comment Show the parameter values. $end
$dumpall
$end
#0
$dumpvars
b0 ;
bx :
b0 9
b0 8
b0 7
bx 6
bx 5
bx 4
bx 3
bx 2
bx 1
b0 0
b0 /
b1 .
b100000000 -
b10000000000000000000000000000011 ,
0+
0*
b0 )
0(
b0 '
0&
bx %
bx $
bx #
b0 "
0!
$end
#1
b1 .
1&
#2
0&
1+
#3
1!
b1 .
1&
#4
0&
0+
#5
b1 .
1&
#6
0&
1(
#7
b1 ;
b1 .
1&
#8
0&
0(
#9
b1 .
1&
#10
0&
b1101 )
b1101 0
b0 -
1*
#11
b10 ;
b1 .
1&
#12
0&
b1 )
b1 0
b1 -
#13
b1 9
b1 8
b1 .
1&
#14
0&
b1010 )
b1010 0
b10 -
#15
b10 9
b10100001 8
b1 .
1&
#16
0&
b11 -
#17
b11 9
b101010100001 8
b1 .
1&
#18
0&
b11 )
b11 0
b100 -
#19
b100 9
b11101010100001 8
b1 .
1&
#20
0&
b10 )
b10 0
b101 -
#21
b101 9
b100011101010100001 8
b1 .
1&
#22
0&
b1011 )
b1011 0
b110 -
#23
b110 9
b101100100011101010100001 8
b1 .
1&
#24
0&
b1 )
b1 0
b111 -
#25
b111 9
b1101100100011101010100001 8
b1 .
1&
#26
0&
0*
b1000 -
#27
b0 ;
b1 .
1&
#28
0&
#29
b1 .
1&
#30
0&
#31
b1 .
1&
#32
0&
#33
b1 .
1&
#34
0&
#35
b1 .
1&
#36
0&
b1 '
b1 /
b0 -
#37
b1 .
1&
b11 '
b11 /
b1 -
#38
0&
b10 -
#39
b1 .
1&
#40
0&
#41
b1 .
1&
#42
0&
b1100 )
b1100 0
b1000 -
1*
#43
b101 ;
b0 :
b0 $
b0 5
b0 1
b0 3
b1 .
1&
#44
0&
b1000 )
b1000 0
b1001 -
#45
b1 1
bx1000 2
b1 .
1&
#46
0&
b111 )
b111 0
b1010 -
#47
b10 1
bx01111000 2
b1 .
1&
#48
0&
b1101 )
b1101 0
b1011 -
#49
b11 1
bx110101111000 2
b1 .
1&
#50
0&
b1001 )
b1001 0
b1100 -
#51
b100 1
bx1001110101111000 2
b1 .
1&
#52
0&
b110 )
b110 0
b1101 -
#53
b101 1
bx01101001110101111000 2
b1 .
1&
#54
0&
b1001 )
b1001 0
b1110 -
#55
b110 1
bx100101101001110101111000 2
b1 .
1&
#56
0&
b10 )
b10 0
b1111 -
#57
b111 1
bx0010100101101001110101111000 2
b1 .
1&
#58
0&
b111 )
b111 0
b10000 -
#59
b1000 1
b1110010100101101001110101111000 2
b1 .
1&
#60
b1 :
b1 3
b1 $
b1 5
b0 #
b0 6
b1110010100101101001110101111000 %
b1110010100101101001110101111000 4
b0 1
0&
b1011 )
b1011 0
b10001 -
#61
b1 1
b1110010100101101001110101111011 2
b10 '
b10 /
b1 .
1&
#62
b0 $
b0 5
0&
b0 )
b0 0
b10010 -
#63
b10 1
b1110010100101101001110100001011 2
b1 .
1&
#64
0&
b110 )
b110 0
b10011 -
#65
b11 1
b1110010100101101001011000001011 2
b1 .
1&
#66
0&
b11 )
b11 0
b10100 -
#67
b100 1
b1110010100101100011011000001011 2
b11 '
b11 /
b1 .
1&
#68
0&
b111 )
b111 0
b10101 -
#69
b101 1
b1110010100101110011011000001011 2
b1 .
1&
#70
0&
b101 )
b101 0
b10110 -
#71
b110 1
b1110010010101110011011000001011 2
b1 .
1&
#72
0&
b1010 )
b1010 0
b10111 -
#73
b111 1
b1111010010101110011011000001011 2
b1 .
1&
#74
0&
b100 )
b100 0
b11000 -
#75
b1000 1
b1001010010101110011011000001011 2
b1 .
1&
#76
b10 :
b0 3
b10 $
b10 5
b1 #
b1 6
b1001010010101110011011000001011 %
b1001010010101110011011000001011 4
b0 1
0&
b10 )
b10 0
b11001 -
#77
b1 1
b1001010010101110011011000000010 2
b1 .
1&
#78
b0 $
b0 5
0&
b100 )
b100 0
b11010 -
#79
b10 1
b1001010010101110011011001000010 2
b1 .
1&
#80
0&
b110 )
b110 0
b11011 -
#81
b11 1
b1 .
1&
#82
0&
b0 )
b0 0
b11100 -
#83
b100 1
b1001010010101110000011001000010 2
b1 .
1&
#84
0&
b1110 )
b1110 0
b11101 -
#85
b101 1
b1001010010111100000011001000010 2
b1 .
1&
#86
0&
b0 )
b0 0
b11110 -
#87
b110 1
b1001010000011100000011001000010 2
b1 .
1&
#88
0&
b1110 )
b1110 0
b11111 -
#89
b111 1
b1001110000011100000011001000010 2
b1 .
1&
#90
0&
b0 )
b0 0
b100000 -
#91
b1000 1
b1110000011100000011001000010 2
b1 .
1&
#92
b11 :
b1 3
b1 $
b1 5
b10 #
b10 6
b1110000011100000011001000010 %
b1110000011100000011001000010 4
b0 1
0&
b1111 )
b1111 0
b100001 -
#93
b1 1
b1110000011100000011001001111 2
b10 '
b10 /
b1 .
1&
#94
b0 $
b0 5
0&
b101 )
b101 0
b100010 -
#95
b10 1
b1110000011100000011001011111 2
b1 .
1&
#96
0&
b0 )
b0 0
b100011 -
#97
b11 1
b1110000011100000000001011111 2
b1 .
1&
#98
0&
b101 )
b101 0
b100100 -
#99
b100 1
b1110000011100101000001011111 2
b11 '
b11 /
b1 .
1&
#100
0&
b111 )
b111 0
b100101 -
#101
b101 1
b1110000001110101000001011111 2
b1 .
1&
#102
0&
b1111 )
b1111 0
b100110 -
#103
b110 1
b1110111101110101000001011111 2
b1 .
1&
#104
0&
b11 )
b11 0
b100111 -
#105
b111 1
b11111101110101000001011111 2
b1 .
1&
#106
0&
b1101 )
b1101 0
b101000 -
#107
b1000 1
b11010011111101110101000001011111 2
b1 .
1&
#108
b100 :
b0 3
b10 $
b10 5
b11 #
b11 6
b11010011111101110101000001011111 %
b11010011111101110101000001011111 4
b0 1
0&
b110 )
b110 0
b101001 -
#109
b1 1
b11010011111101110101000001010110 2
b1 .
1&
#110
b0 $
b0 5
0&
b101 )
b101 0
b101010 -
#111
b10 1
b1 .
1&
#112
0&
b1011 )
b1011 0
b101011 -
#113
b11 1
b11010011111101110101101101010110 2
b1 .
1&
#114
0&
b101 )
b101 0
b101100 -
#115
b100 1
b1 .
1&
#116
0&
b1111 )
b1111 0
b101101 -
#117
b101 1
b11010011111111110101101101010110 2
b1 .
1&
#118
0&
b1101 )
b1101 0
b101110 -
#119
b110 1
b11010011110111110101101101010110 2
b1 .
1&
#120
0&
b1111 )
b1111 0
b101111 -
#121
b111 1
b11011111110111110101101101010110 2
b1 .
1&
#122
0&
b1010 )
b1010 0
b110000 -
#123
b1000 1
b10101111110111110101101101010110 2
b1 .
1&
#124
b101 :
b1 3
b1 $
b1 5
b100 #
b100 6
b10101111110111110101101101010110 %
b10101111110111110101101101010110 4
b0 1
0&
b1 )
b1 0
b110001 -
#125
b1 1
b10101111110111110101101101010001 2
b10 '
b10 /
b1 .
1&
#126
b0 $
b0 5
0&
b10 )
b10 0
b110010 -
#127
b10 1
b10101111110111110101101100100001 2
b1 .
1&
#128
0&
b1011 )
b1011 0
b110011 -
#129
b11 1
b1 .
1&
#130
0&
b1 )
b1 0
b110100 -
#131
b100 1
b10101111110111110001101100100001 2
b11 '
b11 /
b1 .
1&
#132
0&
b1101 )
b1101 0
b110101 -
#133
b101 1
b10101111110111010001101100100001 2
b1 .
1&
#134
0&
b0 )
b0 0
b110110 -
#135
b110 1
b10101111000011010001101100100001 2
b1 .
1&
#136
0&
b10 )
b10 0
b110111 -
#137
b111 1
b10100010000011010001101100100001 2
b1 .
1&
#138
0&
b11 )
b11 0
b111000 -
#139
b1000 1
b110010000011010001101100100001 2
b1 .
1&
#140
b110 :
b0 3
b10 $
b10 5
b101 #
b101 6
b110010000011010001101100100001 %
b110010000011010001101100100001 4
b0 1
0&
b100 )
b100 0
b111001 -
#141
b1 1
b110010000011010001101100100100 2
b1 .
1&
#142
b0 $
b0 5
0&
b111010 -
#143
b10 1
b110010000011010001101101000100 2
b1 .
1&
#144
0&
b1 )
b1 0
b111011 -
#145
b11 1
b110010000011010001000101000100 2
b1 .
1&
#146
0&
b1001 )
b1001 0
b111100 -
#147
b100 1
b110010000011011001000101000100 2
b1 .
1&
#148
0&
b111101 -
#149
b101 1
b110010000010011001000101000100 2
b1 .
1&
#150
0&
b1 )
b1 0
b111110 -
#151
b110 1
b110010000110011001000101000100 2
b1 .
1&
#152
0&
b1001 )
b1001 0
b111111 -
#153
b111 1
b111001000110011001000101000100 2
b1 .
1&
#154
0&
b1101 )
b1101 0
b1000000 -
#155
b1000 1
b11011001000110011001000101000100 2
b1 .
1&
#156
b111 :
b1 3
b1 $
b1 5
b110 #
b110 6
b11011001000110011001000101000100 %
b11011001000110011001000101000100 4
b0 1
0&
b1110 )
b1110 0
b1000001 -
#157
b1 1
b11011001000110011001000101001110 2
b10 '
b10 /
b1 .
1&
#158
b0 $
b0 5
0&
b100 )
b100 0
b1000010 -
#159
b10 1
b1 .
1&
#160
0&
b1100 )
b1100 0
b1000011 -
#161
b11 1
b11011001000110011001110001001110 2
b1 .
1&
#162
0&
b1111 )
b1111 0
b1000100 -
#163
b100 1
b11011001000110011111110001001110 2
b11 '
b11 /
b1 .
1&
#164
0&
b1101 )
b1101 0
b1000101 -
#165
b101 1
b11011001000111011111110001001110 2
b1 .
1&
#166
0&
b111 )
b111 0
b1000110 -
#167
b110 1
b11011001011111011111110001001110 2
b1 .
1&
#168
0&
b1101 )
b1101 0
b1000111 -
#169
b111 1
b11011101011111011111110001001110 2
b1 .
1&
#170
0&
b110 )
b110 0
b1001000 -
#171
b1000 1
b1101101011111011111110001001110 2
b1 .
1&
#172
b1000 :
b0 3
b10 $
b10 5
b111 #
b111 6
b1101101011111011111110001001110 %
b1101101011111011111110001001110 4
b0 1
0&
b1101 )
b1101 0
b1001001 -
#173
b1 1
b1101101011111011111110001001101 2
b1 .
1&
#174
b0 $
b0 5
0&
b1000 )
b1000 0
b1001010 -
#175
b10 1
b1101101011111011111110010001101 2
b1 .
1&
#176
0&
b1001011 -
#177
b11 1
b1101101011111011111100010001101 2
b1 .
1&
#178
0&
b1110 )
b1110 0
b1001100 -
#179
b100 1
b1101101011111011110100010001101 2
b1 .
1&
#180
0&
b1000 )
b1000 0
b1001101 -
#181
b101 1
b1101101011110001110100010001101 2
b1 .
1&
#182
0&
b0 )
b0 0
b1001110 -
#183
b110 1
b1101101000010001110100010001101 2
b1 .
1&
#184
0&
b101 )
b101 0
b1001111 -
#185
b111 1
b1100101000010001110100010001101 2
b1 .
1&
#186
0&
b0 )
b0 0
b1010000 -
#187
b1000 1
b101000010001110100010001101 2
b1 .
1&
#188
b1001 :
b1 3
b1 $
b1 5
b1000 #
b1000 6
b101000010001110100010001101 %
b101000010001110100010001101 4
b0 1
0&
b11 )
b11 0
b1010001 -
#189
b1 1
b101000010001110100010000011 2
b10 '
b10 /
b1 .
1&
#190
b0 $
b0 5
0&
b1111 )
b1111 0
b1010010 -
#191
b10 1
b101000010001110100011110011 2
b1 .
1&
#192
0&
b11 )
b11 0
b1010011 -
#193
b11 1
b101000010001110001111110011 2
b1 .
1&
#194
0&
b1001 )
b1001 0
b1010100 -
#195
b100 1
b101000010001001001111110011 2
b11 '
b11 /
b1 .
1&
#196
0&
b1111 )
b1111 0
b1010101 -
#197
b101 1
b101000011111001001111110011 2
b1 .
1&
#198
0&
b1101 )
b1101 0
b1010110 -
#199
b110 1
b101110111111001001111110011 2
b1 .
1&
#200
0&
b10 )
b10 0
b1010111 -
#201
b111 1
b10110111111001001111110011 2
b1 .
1&
#202
0&
b1110 )
b1110 0
b1011000 -
#203
b1000 1
b11100010110111111001001111110011 2
b1 .
1&
#204
b1010 :
b0 3
b10 $
b10 5
b1001 #
b1001 6
b11100010110111111001001111110011 %
b11100010110111111001001111110011 4
b0 1
0&
b1101 )
b1101 0
b1011001 -
#205
b1 1
b11100010110111111001001111111101 2
b1 .
1&
#206
b0 $
b0 5
0&
b1001 )
b1001 0
b1011010 -
#207
b10 1
b11100010110111111001001110011101 2
b1 .
1&
#208
0&
b1011011 -
#209
b11 1
b11100010110111111001100110011101 2
b1 .
1&
#210
0&
b110 )
b110 0
b1011100 -
#211
b100 1
b11100010110111110110100110011101 2
b1 .
1&
#212
0&
b1110 )
b1110 0
b1011101 -
#213
b101 1
b11100010110111100110100110011101 2
b1 .
1&
#214
0&
b11 )
b11 0
b1011110 -
#215
b110 1
b11100010001111100110100110011101 2
b1 .
1&
#216
0&
b1000 )
b1000 0
b1011111 -
#217
b111 1
b11101000001111100110100110011101 2
b1 .
1&
#218
0&
b1100 )
b1100 0
b1100000 -
#219
b1000 1
b11001000001111100110100110011101 2
b1 .
1&
#220
b1011 :
b1 3
b1 $
b1 5
b1010 #
b1010 6
b11001000001111100110100110011101 %
b11001000001111100110100110011101 4
b0 1
0&
b1110 )
b1110 0
b1100001 -
#221
b1 1
b11001000001111100110100110011110 2
b10 '
b10 /
b1 .
1&
#222
b0 $
b0 5
0&
b1111 )
b1111 0
b1100010 -
#223
b10 1
b11001000001111100110100111111110 2
b1 .
1&
#224
0&
b1100 )
b1100 0
b1100011 -
#225
b11 1
b11001000001111100110110011111110 2
b1 .
1&
#226
0&
b1101 )
b1101 0
b1100100 -
#227
b100 1
b11001000001111101101110011111110 2
b11 '
b11 /
b1 .
1&
#228
0&
b111 )
b111 0
b1100101 -
#229
b101 1
b11001000001101111101110011111110 2
b1 .
1&
#230
0&
b0 )
b0 0
b1100110 -
#231
b110 1
b11001000000001111101110011111110 2
b1 .
1&
#232
0&
b1000 )
b1000 0
b1100111 -
#233
b111 1
b1 .
1&
#234
0&
b101 )
b101 0
b1101000 -
#235
b1000 1
b1011000000001111101110011111110 2
b1 .
1&
#236
b1100 :
b0 3
b10 $
b10 5
b1011 #
b1011 6
b1011000000001111101110011111110 %
b1011000000001111101110011111110 4
b0 1
0&
b1001 )
b1001 0
b1101001 -
#237
b1 1
b1011000000001111101110011111001 2
b1 .
1&
#238
b0 $
b0 5
0&
b0 )
b0 0
b1101010 -
#239
b10 1
b1011000000001111101110000001001 2
b1 .
1&
#240
0&
b1101011 -
#241
b11 1
b1011000000001111101000000001001 2
b1 .
1&
#242
0&
b111 )
b111 0
b1101100 -
#243
b100 1
b1011000000001110111000000001001 2
b1 .
1&
#244
0&
b110 )
b110 0
b1101101 -
#245
b101 1
b1011000000001100111000000001001 2
b1 .
1&
#246
0&
b1 )
b1 0
b1101110 -
#247
b110 1
b1011000000101100111000000001001 2
b1 .
1&
#248
0&
b1000 )
b1000 0
b1101111 -
#249
b111 1
b1 .
1&
#250
0&
b10 )
b10 0
b1110000 -
#251
b1000 1
b101000000101100111000000001001 2
b1 .
1&
#252
b1101 :
b1 3
b1 $
b1 5
b1100 #
b1100 6
b101000000101100111000000001001 %
b101000000101100111000000001001 4
b0 1
0&
b1110001 -
#253
b1 1
b101000000101100111000000000010 2
b10 '
b10 /
b1 .
1&
#254
b0 $
b0 5
0&
b1010 )
b1010 0
b1110010 -
#255
b10 1
b101000000101100111000010100010 2
b1 .
1&
#256
0&
b110 )
b110 0
b1110011 -
#257
b11 1
b101000000101100111011010100010 2
b1 .
1&
#258
0&
b1110100 -
#259
b100 1
b101000000101100110011010100010 2
b11 '
b11 /
b1 .
1&
#260
0&
b111 )
b111 0
b1110101 -
#261
b101 1
b101000000101110110011010100010 2
b1 .
1&
#262
0&
b1110110 -
#263
b110 1
b101000011101110110011010100010 2
b1 .
1&
#264
0&
b1101 )
b1101 0
b1110111 -
#265
b111 1
b101101011101110110011010100010 2
b1 .
1&
#266
0&
b110 )
b110 0
b1111000 -
#267
b1000 1
b1101101011101110110011010100010 2
b1 .
1&
#268
b1110 :
b0 3
b10 $
b10 5
b1101 #
b1101 6
b1101101011101110110011010100010 %
b1101101011101110110011010100010 4
b0 1
0&
b100 )
b100 0
b1111001 -
#269
b1 1
b1101101011101110110011010100100 2
b1 .
1&
#270
b0 $
b0 5
0&
b111 )
b111 0
b1111010 -
#271
b10 1
b1101101011101110110011001110100 2
b1 .
1&
#272
0&
b1010 )
b1010 0
b1111011 -
#273
b11 1
b1101101011101110110101001110100 2
b1 .
1&
#274
0&
b1111100 -
#275
b100 1
b1101101011101111010101001110100 2
b1 .
1&
#276
0&
b10 )
b10 0
b1111101 -
#277
b101 1
b1101101011100101010101001110100 2
b1 .
1&
#278
0&
b1101 )
b1101 0
b1111110 -
#279
b110 1
b1101101110100101010101001110100 2
b1 .
1&
#280
0&
b1111111 -
#281
b111 1
b1 .
1&
