Icarus-Verliog-testing/Constants/constants.vh
//DEFINE CONSTANTS
// `define KEY_WIDTH 16 // width of the key. In multiples of 4.
// `define KEY_QSPI_COUNT `KEY_WIDTH/4 // number of QSPI transactions per key sent in LSB. 
// `define KEY_QSPI_COUNT_REG $clog2(`KEY_QSPI_COUNT+1) // register size required to count the current QSPI transaction of the key + 1. log2(`KEY_QSPI_COUNT+1)

`define ENCRYPTER_WIDTH 32 // width of the bus between the Paralellizer and Encrypter, and the Encrypter and Collector. In multiples of 4.
`define ENCRYPTER_WIDTH_COUNT_REG $clog2(`ENCRYPTER_WIDTH+1) // register size required to count the current bit of the encrypter bus + 1. log2(`ENCRYPTER_WIDTH+1). (Verilog doesn't like me so i need a for loop)
`define ENCRYPTER_QSPI_COUNT `ENCRYPTER_WIDTH/4 // number of QSPI transactions per Encrypter.
`define ENCRYPTER_QSPI_COUNT_REG $clog2(`ENCRYPTER_QSPI_COUNT+1) // register size required to count the current QSPI transaction of the Encrypter + 1. log2(`ENCRYPTER_QSPI_COUNT+1)

`define KEY_ROTATION_WIDTH $clog2(`ENCRYPTER_WIDTH) // width of the key rotation bus between Paralellizer and Encrypter. log2(`KEY_WIDTH)
`define KEY_ROTATION_WIDTH_COUNT_REG $clog2(`KEY_ROTATION_WIDTH+1) // register size required to count the current bit of the key rotation bus + 1. log2(`KEY_ROTATION_WIDTH+1). (Verilog doesn't like me so i need a for loop)

// `define KEY_ENCRYPTER_COUNT `KEY_WIDTH/`ENCRYPTER_WIDTH // number of Encrypters transactions per key. `KEY_WIDTH/`ENCRYPTER_WIDTH
// `define KEY_ENCRYPTER_COUNT_REG $clog2(`KEY_ENCRYPTER_COUNT+1) // register size required to count the current Encrypter transaction of the key + 1. log2(`KEY_ENCRYPTER_COUNT+1)

`define NUM_ENCRYPTERS 2 // number of Encrypters
`define NUM_ENCRYPTERS_REG $clog2(`NUM_ENCRYPTERS+1) // register size required to count the current Encrypter + 1. log2(`NUM_ENCRYPTERS+1)

Icarus-Verliog-testing/Encrypter/encrypter.sv
`include "./Constants/constants.vh"

`define IDLE 3'b000
`define READING_KEY 3'b001
`define WAITING_RDY_DATA_IN 3'b010
`define READING_DATA_ENCRYPTING 3'b011
`define SENDING_DATA 3'b100
`define ACKNOWLEDGING_CAPTURE 3'b101

module Encrypter (
    input wire clk,
    input wire reset,

    // Parallelizer <-> Encrypter signals
    input wire [`ENCRYPTER_WIDTH-1:0] data_in_p,
    input wire [`KEY_ROTATION_WIDTH-1:0] key_rotation_p,
    input wire prog_p,
    input wire data_ready_in_p,
    output reg ready_p,

    // Encrypter <-> Collector signals
    output reg [`ENCRYPTER_WIDTH-1:0] data_out_c,
    output reg data_ready_out_c,
    input wire capture_c
);

    reg [2:0] state;
    reg [`ENCRYPTER_WIDTH-1:0] keyRotated;
    reg [`ENCRYPTER_WIDTH-1:0] data_in_store;
    reg [`ENCRYPTER_WIDTH-1:0] keyOrigin;
    reg [`KEY_ROTATION_WIDTH:0] offset;

    initial begin
        state <= `IDLE;
        ready_p = 0;
        data_ready_out_c = 0;
        data_out_c = 0;
        data_in_store = 0;
        keyOrigin = 0;
        keyRotated = 0;
        offset = 0;
    end

    always @(posedge clk) begin
        if (reset) begin
            state <= `IDLE;
            ready_p = 0;
            data_ready_out_c = 0;
            data_out_c = 0;
            data_in_store = 0;
            keyOrigin = 0;
            keyRotated = 0;
            offset = 0;
        end
        
        case (state)

            `IDLE: begin
                if (prog_p) state <= `READING_KEY;
            end

            `WAITING_RDY_DATA_IN: begin
                if (data_ready_in_p) state <= `READING_DATA_ENCRYPTING;
            end

            `READING_KEY: begin
                keyOrigin = data_in_p;
                state = `WAITING_RDY_DATA_IN;
            end

            `READING_DATA_ENCRYPTING: begin
                data_in_store = data_in_p;
                offset = key_rotation_p;
                ready_p = 0;
                keyRotated = (keyOrigin << offset) | (keyOrigin >> (`ENCRYPTER_WIDTH-offset));
                // #20;
                state = `SENDING_DATA;
            end

            `SENDING_DATA: begin
                if (capture_c)
                state <= `ACKNOWLEDGING_CAPTURE;
            end

        endcase
    end

    always @(negedge clk) begin
        case (state)
            `SENDING_DATA: begin
                data_out_c = data_in_store ^ keyRotated;
                data_ready_out_c = 1;
            end

            `WAITING_RDY_DATA_IN: begin
                if (~ready_p) ready_p = 1;
            end

            `ACKNOWLEDGING_CAPTURE: begin
                state <= `WAITING_RDY_DATA_IN;
                data_ready_out_c = 0;
                ready_p = 1;
            end
        endcase
    end
endmodule


module EncrypterADV (
    input wire clk,
    input wire reset,

    // Parallelizer <-> Encrypter signals
    input wire [`ENCRYPTER_WIDTH-1:0] data_in_p,
    input wire [`KEY_ROTATION_WIDTH-1:0] key_rotation_p,
    input wire prog_p,
    input wire data_ready_in_p,
    output reg ready_p,

    // Encrypter <-> Collector signals
    output reg [`ENCRYPTER_WIDTH-1:0] data_out_c,
    output reg data_ready_out_c,
    input wire capture_c,
    output reg [31:0] keyS
);

    reg [2:0] state;
    reg [`ENCRYPTER_WIDTH-1:0] keyRotated;
    reg [64-1:0] keySquared;
    reg [`ENCRYPTER_WIDTH-1:0] keyMod;
    reg [`ENCRYPTER_WIDTH-1:0] data_in_store;
    reg [`ENCRYPTER_WIDTH-1:0] keyOrigin;
    reg [`KEY_ROTATION_WIDTH:0] offset;
    reg [`KEY_ROTATION_WIDTH:0] xorOffset;

    initial begin
        state <= `IDLE;
        ready_p = 0;
        data_ready_out_c = 0;
        data_out_c = 0;
        data_in_store = 0;
        keyRotated = 0;
        keyOrigin = 0;
        keySquared = 0;
        keyMod = 0;
        offset = 0;
    end

    always @(posedge clk) begin
        if (reset) begin
            state <= `IDLE;
            ready_p = 0;
            data_ready_out_c = 0;
            data_out_c = 0;
            data_in_store = 0;
            keyRotated = 0;
            keyOrigin = 0;
            keySquared = 0;
            keyMod = 0;
            offset = 0;
        end
        
        case (state)

            `IDLE: begin
                if (prog_p) state <= `READING_KEY;
            end

            `WAITING_RDY_DATA_IN: begin
                if (data_ready_in_p) state <= `READING_DATA_ENCRYPTING;
            end

            `READING_KEY: begin
                keyOrigin = data_in_p;
                state = `WAITING_RDY_DATA_IN;
            end

            `READING_DATA_ENCRYPTING: begin
                data_in_store = data_in_p;
                offset = key_rotation_p;
                ready_p = 0;
                xorOffset = (keyOrigin & 5'b11111)^offset;
                keyRotated = (keyOrigin << xorOffset) | (keyOrigin >> (`ENCRYPTER_WIDTH-xorOffset));
                keySquared = keyRotated*keyRotated;
                
                keyMod = keySquared%4294967311;
                
                #20;
                state = `SENDING_DATA;
            end

            `SENDING_DATA: begin
                if (capture_c)
                state <= `ACKNOWLEDGING_CAPTURE;
            end

        endcase
    end

    always @(negedge clk) begin
        case (state)
            `SENDING_DATA: begin
                keyS = data_in_store;
                data_out_c = data_in_store ^ keyMod;
                data_ready_out_c = 1;
            end

            `WAITING_RDY_DATA_IN: begin
                if (~ready_p) ready_p = 1;
            end

            `ACKNOWLEDGING_CAPTURE: begin
                state <= `WAITING_RDY_DATA_IN;
                data_ready_out_c = 0;
                ready_p = 1;
            end
        endcase
    end
endmodule

Icarus-Verliog-testing/Encrypter/encrypterADV_tb.sv
`timescale 1ns/1ps

`include "./Constants/constants.vh"
`include "./Encrypter/encrypter.sv"

module EncrypterADV_tb;

    reg clk;
    reg reset;

    reg [`ENCRYPTER_WIDTH-1:0] data_in_p;
    reg [`KEY_ROTATION_WIDTH-1:0] key_rotation_p;
    reg prog_p;
    reg data_ready_in_p;
    wire ready_p;

    wire [`ENCRYPTER_WIDTH-1:0] data_out_c;
    wire data_ready_out_c;
    reg capture_c;

EncrypterADV DUT(
    .clk(clk),
    .reset(reset),

    .data_in_p(data_in_p),
    .key_rotation_p(key_rotation_p),
    .prog_p(prog_p),
    .data_ready_in_p(data_ready_in_p),
    .ready_p(ready_p),

    .data_out_c(data_out_c),
    .data_ready_out_c(data_ready_out_c),
    .capture_c(capture_c)
);

initial begin
    //clock generation
    clk = 1;
    forever #5 clk = ~clk;
end

initial begin
    //initialization
    reset = 1;#10;
    reset = 0;
end

initial begin
    
    #20;
    data_in_p = 32'b10110100001101010010101110010011; #10;
    prog_p = 1;#10;

end

initial begin
    //monitoring
    $dumpfile("Encrypter/encrypterADVtb.vcd");
    $dumpvars(1, EncrypterADV_tb);

    //$monitor("data_out: %b\tdataRdyIn: %d\tcap: %d\trdyIn: %d\tdataRdyOut: %d\tkeyRotated: %b\toffset: %d",dataOut,dataRdyIn,cap,rdyIn,dataRdyOut,keyRotated,rot_offset);
    #170;$finish;
end

always @(posedge data_ready_out_c) begin
    #10 capture_c = 0;
    #10 capture_c = 1;
end

always @(posedge ready_p) begin
    #5 
    data_in_p = 32'h1F537C8A;
    key_rotation_p = 5'b00000; #5;
    data_ready_in_p = 1;
end

always @(negedge ready_p) begin
    #10 data_ready_in_p = 0;
end

endmodule

Icarus-Verliog-testing/Encrypter/encrypterADVtb.vcd
$date
	Sun May 19 17:43:28 2024
$end
$version
	Icarus Verilog
$end
$timescale
	1ps
$end
$scope module EncrypterADV_tb $end
$var wire 1 ! ready_p $end
$var wire 1 " data_ready_out_c $end
$var wire 32 # data_out_c [31:0] $end
$var reg 1 $ capture_c $end
$var reg 1 % clk $end
$var reg 32 & data_in_p [31:0] $end
$var reg 1 ' data_ready_in_p $end
$var reg 5 ( key_rotation_p [4:0] $end
$var reg 1 ) prog_p $end
$var reg 1 * reset $end
$upscope $end
$enddefinitions $end
#0
$dumpvars
1*
x)
bx (
x'
bx &
1%
x$
b0 #
0"
0!
$end
#5000
0%
#10000
1%
0*
#15000
0%
#20000
1%
b10110100001101010010101110010011 &
#25000
0%
#30000
1%
1)
#35000
0%
#40000
1%
#45000
1!
0%
#50000
b0 (
b11111010100110111110010001010 &
1%
#55000
1'
0%
#60000
1%
#65000
0%
#70000
0!
1%
#75000
0%
#80000
1%
0'
#85000
0%
#90000
1%
#95000
1"
b101111100101011010011001101010 #
0%
#100000
1%
#105000
0%
0$
#110000
1%
#115000
0%
1$
#120000
1%
#125000
1!
0"
0%
#130000
1%
#135000
1'
0%
#140000
1%
#145000
0%
#150000
0!
1%
#155000
0%
#160000
1%
0'
