Icarus-Verliog-testing/Constants/constants.vh
//DEFINE CONSTANTS
// `define KEY_WIDTH 16 // width of the key. In multiples of 4.
// `define KEY_QSPI_COUNT `KEY_WIDTH/4 // number of QSPI transactions per key sent in LSB. 
// `define KEY_QSPI_COUNT_REG $clog2(`KEY_QSPI_COUNT+1) // register size required to count the current QSPI transaction of the key + 1. log2(`KEY_QSPI_COUNT+1)

`define ENCRYPTER_WIDTH 32 // width of the bus between the Paralellizer and Encrypter, and the Encrypter and Collector. In multiples of 4.
`define ENCRYPTER_WIDTH_COUNT_REG $clog2(`ENCRYPTER_WIDTH+1) // register size required to count the current bit of the encrypter bus + 1. log2(`ENCRYPTER_WIDTH+1). (Verilog doesn't like me so i need a for loop)
`define ENCRYPTER_QSPI_COUNT `ENCRYPTER_WIDTH/4 // number of QSPI transactions per Encrypter.
`define ENCRYPTER_QSPI_COUNT_REG $clog2(`ENCRYPTER_QSPI_COUNT+1) // register size required to count the current QSPI transaction of the Encrypter + 1. log2(`ENCRYPTER_QSPI_COUNT+1)

`define KEY_ROTATION_WIDTH $clog2(`ENCRYPTER_WIDTH) // width of the key rotation bus between Paralellizer and Encrypter. log2(`KEY_WIDTH)
`define KEY_ROTATION_WIDTH_COUNT_REG $clog2(`KEY_ROTATION_WIDTH+1) // register size required to count the current bit of the key rotation bus + 1. log2(`KEY_ROTATION_WIDTH+1). (Verilog doesn't like me so i need a for loop)

// `define KEY_ENCRYPTER_COUNT `KEY_WIDTH/`ENCRYPTER_WIDTH // number of Encrypters transactions per key. `KEY_WIDTH/`ENCRYPTER_WIDTH
// `define KEY_ENCRYPTER_COUNT_REG $clog2(`KEY_ENCRYPTER_COUNT+1) // register size required to count the current Encrypter transaction of the key + 1. log2(`KEY_ENCRYPTER_COUNT+1)

`define NUM_ENCRYPTERS 2 // number of Encrypters
`define NUM_ENCRYPTERS_REG $clog2(`NUM_ENCRYPTERS+1) // register size required to count the current Encrypter + 1. log2(`NUM_ENCRYPTERS+1)

Icarus-Verliog-testing/Encrypter/encrypter.sv
`include "./Constants/constants.vh"

`define IDLE 3'b000
`define WAITING_RDY_DATA_IN 3'b001
`define READING_KEY 3'b010
`define READING_DATA 3'b011
`define ENCRYPTING 3'b100
`define WAITING_RDY_DATA_OUT 3'b101
`define SENDING_DATA 3'b110


module Encrypter (
    input wire clk,
    input wire reset,

    input wire [`ENCRYPTER_WIDTH-1:0] dataIn,
    input wire [`KEY_ROTATION_WIDTH-1:0] rot_offset,
    input wire rdyIn,
    input wire rdyOut,
    input wire prog,
    input wire error,

    output reg [`ENCRYPTER_WIDTH-1:0] dataOut,
    output reg reqIn,
    output reg reqOut,

    output reg [2:0] state,
    output reg [`KEY_WIDTH-1:0] key,
    output reg [`ENCRYPTER_WIDTH-1:0] data_in
);
    
    reg [`KEY_WIDTH-1:0] keyTemp;
    reg [`KEY_ROTATION_WIDTH:0] offset;

    initial begin
        state <= `IDLE;
        reqIn = 1;
        reqOut = 0;
        dataOut = 0;
        data_in = 0;
        key = 0;
        offset = 0;
    end

    always @(posedge reset) begin
        state <= `IDLE;
        reqIn = 1;
        reqOut = 0;
        dataOut = 0;
        data_in = 0;
        key = 0;
        offset = 0;
    end

    always @(posedge prog) begin
        if (state == `WAITING_RDY_DATA_OUT) begin
            state <= `SENDING_DATA;
        end
        state <= `WAITING_RDY_DATA_IN;
    end

    always @(posedge rdyIn) begin
        case (state)
            `IDLE: state <= `READING_KEY;
            `WAITING_RDY_DATA_IN: state <= `READING_DATA;
        endcase 
    end

    always @(posedge rdyOut) begin
        if (state == `WAITING_RDY_DATA_OUT) begin
            state <= `SENDING_DATA;
        end
    end

    // always @(posedge error) begin
    //     state = encryption;
    // end

    always @(posedge clk) begin
        case (state)
            `IDLE: begin
                reqIn = 1;
            end

            `READING_KEY: begin
                reqIn <= 0;
                keyTemp <= dataIn;
                state <= `WAITING_RDY_DATA_IN;
                reqIn <= 1;
            end

            `READING_DATA: begin
                reqIn = 0;
                data_in = dataIn;
                offset = rot_offset;
                state = `ENCRYPTING;
            end

            `ENCRYPTING: begin
                key = (keyTemp << offset) | (keyTemp >> (`KEY_WIDTH-offset));
                dataOut = data_in ^ key;
                state = `WAITING_RDY_DATA_OUT;
                reqOut = 1;
            end

            `SENDING_DATA: begin
                reqOut = 0;
                state = `WAITING_RDY_DATA_IN;
            end
        endcase
    end
endmodule

Icarus-Verliog-testing/Encrypter/encrypter_tb.sv
`timescale 1ns/1ps

`include "./Constants/constants.vh"
`include "./Encrypter/encrypter.sv"

module Encrypter_tb;

    reg clk;
    reg reset;

    reg [`ENCRYPTER_WIDTH-1:0] dataIn;
    reg [`KEY_ROTATION_WIDTH-1:0] rot_offset;
    reg rdyIn;
    reg rdyOut;
    reg prog;
    reg error;

    wire [`ENCRYPTER_WIDTH-1:0] dataOut;
    wire reqIn;
    wire reqOut;
    wire [2:0] state;
    wire [`KEY_WIDTH-1:0] key;
    wire [`ENCRYPTER_WIDTH-1:0] data_in;

Encrypter DUT(
    .clk(clk),
    .reset(reset),
    .dataIn(dataIn),
    .rot_offset(rot_offset),
    .rdyIn(rdyIn),
    .rdyOut(rdyOut),
    .prog(prog),
    .error(error),
    .dataOut(dataOut),
    .reqIn(reqIn),
    .reqOut(reqOut),
    .state(state),
    .key(key),
    .data_in(data_in)
);

initial begin
    //clock generation
    clk = 1;
    forever #5 clk = ~clk;
end

initial begin
    //initialization
    reset = 1;#10;
    reset = 0;
    dataIn = 0;
    rot_offset = 0;
    rdyIn = 0;
    rdyOut = 0;
    prog = 0;
    error = 0;
end

initial begin
    
    #20;
    dataIn = 16'b1100110011100011; #10;

    rdyIn = 1;#100;
    rdyIn = 0;#10;
    prog = 1;#10;

    dataIn = 16'b1111000011110000;
    rot_offset = 4'b0111; #10;

    rdyIn = 1;#100;
    rdyIn = 0;#10;

    dataIn = 16'b1111000011110000;
    rot_offset = 4'b0011; #10;

    rdyIn = 1;#100;
    rdyIn = 0;#10;

end

initial begin
    //monitoring
    $dumpfile("Encrypter/encrypter_tb.vcd");
    $dumpvars(1, Encrypter_tb);

    $monitor("data_out: %b\trdyIn: %d\trdyOut: %d\treqIn: %d\treqOut: %d\tkey: %b\toffset: %d",dataOut,rdyIn,rdyOut,reqIn,reqOut,key,rot_offset);
    #500;$finish;
end

always @(posedge reqOut) begin
    #1 rdyOut = 1;
end

always @(negedge reqOut) begin
    #1 rdyOut = 0;
end

endmodule

Icarus-Verliog-testing/Encrypter/encrypter_tb.vcd
$date
	Mon May  6 12:10:17 2024
$end
$version
	Icarus Verilog
$end
$timescale
	1ps
$end
$scope module Encrypter_tb $end
$var wire 3 ! state [2:0] $end
$var wire 1 " reqOut $end
$var wire 1 # reqIn $end
$var wire 16 $ key [15:0] $end
$var wire 16 % data_in [15:0] $end
$var wire 16 & dataOut [15:0] $end
$var reg 1 ' clk $end
$var reg 16 ( dataIn [15:0] $end
$var reg 1 ) error $end
$var reg 1 * prog $end
$var reg 1 + rdyIn $end
$var reg 1 , rdyOut $end
$var reg 1 - reset $end
$var reg 4 . rot_offset [3:0] $end
$upscope $end
$enddefinitions $end
#0
$dumpvars
bx .
1-
x,
x+
x*
x)
bx (
1'
b0 &
b0 %
b0 $
1#
0"
b0 !
$end
#5000
0'
#10000
1'
0)
0*
0,
0+
b0 .
b0 (
0-
#15000
0'
#20000
1'
b1100110011100011 (
#25000
0'
#30000
b10 !
1'
1+
#35000
0'
#40000
b1 !
1#
1'
#45000
0'
#50000
1'
#55000
0'
#60000
1'
#65000
0'
#70000
1'
#75000
0'
#80000
1'
#85000
0'
#90000
1'
#95000
0'
#100000
1'
#105000
0'
#110000
1'
#115000
0'
#120000
1'
#125000
0'
#130000
1'
0+
#135000
0'
#140000
1'
1*
#145000
0'
#150000
1'
b111 .
b1111000011110000 (
#155000
0'
#160000
b11 !
1'
1+
#165000
0'
#170000
b100 !
b1111000011110000 %
0#
1'
#175000
0'
#180000
1"
b101 !
b1000000100010110 &
b111000111100110 $
1'
#181000
b110 !
1,
#185000
0'
#190000
b1 !
0"
1'
#191000
0,
#195000
0'
#200000
1'
#205000
0'
#210000
1'
#215000
0'
#220000
1'
#225000
0'
#230000
1'
#235000
0'
#240000
1'
#245000
0'
#250000
1'
#255000
0'
#260000
1'
0+
#265000
0'
#270000
1'
b11 .
#275000
0'
#280000
b11 !
1'
1+
#285000
0'
#290000
b100 !
1'
#295000
0'
#300000
1"
b101 !
b1001011111101110 &
b110011100011110 $
1'
#301000
b110 !
1,
#305000
0'
#310000
b1 !
0"
1'
#311000
0,
#315000
0'
#320000
1'
#325000
0'
#330000
1'
#335000
0'
#340000
1'
#345000
0'
#350000
1'
#355000
0'
#360000
1'
#365000
0'
#370000
1'
#375000
0'
#380000
1'
0+
