Icarus-Verliog-testing/Constants/constants.vh
//DEFINE CONSTANTS
// `define KEY_WIDTH 16 // width of the key. In multiples of 4.
// `define KEY_QSPI_COUNT `KEY_WIDTH/4 // number of QSPI transactions per key sent in LSB. 
// `define KEY_QSPI_COUNT_REG $clog2(`KEY_QSPI_COUNT+1) // register size required to count the current QSPI transaction of the key + 1. log2(`KEY_QSPI_COUNT+1)

`define ENCRYPTER_WIDTH 32 // width of the bus between the Paralellizer and Encrypter, and the Encrypter and Collector. In multiples of 4.
`define ENCRYPTER_WIDTH_COUNT_REG $clog2(`ENCRYPTER_WIDTH+1) // register size required to count the current bit of the encrypter bus + 1. log2(`ENCRYPTER_WIDTH+1). (Verilog doesn't like me so i need a for loop)
`define ENCRYPTER_QSPI_COUNT `ENCRYPTER_WIDTH/4 // number of QSPI transactions per Encrypter.
`define ENCRYPTER_QSPI_COUNT_REG $clog2(`ENCRYPTER_QSPI_COUNT+1) // register size required to count the current QSPI transaction of the Encrypter + 1. log2(`ENCRYPTER_QSPI_COUNT+1)

`define KEY_ROTATION_WIDTH $clog2(`ENCRYPTER_WIDTH) // width of the key rotation bus between Paralellizer and Encrypter. log2(`KEY_WIDTH)
`define KEY_ROTATION_WIDTH_COUNT_REG $clog2(`KEY_ROTATION_WIDTH+1) // register size required to count the current bit of the key rotation bus + 1. log2(`KEY_ROTATION_WIDTH+1). (Verilog doesn't like me so i need a for loop)

// `define KEY_ENCRYPTER_COUNT `KEY_WIDTH/`ENCRYPTER_WIDTH // number of Encrypters transactions per key. `KEY_WIDTH/`ENCRYPTER_WIDTH
// `define KEY_ENCRYPTER_COUNT_REG $clog2(`KEY_ENCRYPTER_COUNT+1) // register size required to count the current Encrypter transaction of the key + 1. log2(`KEY_ENCRYPTER_COUNT+1)

`define NUM_ENCRYPTERS 2 // number of Encrypters
`define NUM_ENCRYPTERS_REG $clog2(`NUM_ENCRYPTERS+1) // register size required to count the current Encrypter + 1. log2(`NUM_ENCRYPTERS+1)

Icarus-Verliog-testing/Encrypter/encrypter.sv
`include "./Constants/constants.vh"

`define IDLE 3'b000
`define READING_KEY 3'b001
`define WAITING_RDY_DATA_IN 3'b010
`define READING_DATA 3'b011
`define ENCRYPTING 3'b100
`define SENDING_DATA 3'b101

module Encrypter (
    input wire clk,
    input wire reset,

    input wire [`ENCRYPTER_WIDTH-1:0] dataIn,
    input wire [`KEY_ROTATION_WIDTH-1:0] rot_offset,
    input wire rdyIn,
    input wire cap,
    input wire prog,

    output reg [`ENCRYPTER_WIDTH-1:0] dataOut,
    output reg reqIn,
    output reg reqOut,

    output reg [2:0] state,
    output reg [`KEY_WIDTH-1:0] key,
    output reg [`ENCRYPTER_WIDTH-1:0] data_in
);

    reg [`ENCRYPTER_WIDTH-1:0] data_out;
    reg [`KEY_WIDTH-1:0] keyTemp;
    reg [`KEY_ROTATION_WIDTH:0] offset;

    initial begin
        state <= `IDLE;
        reqIn = 0;
        reqOut = 0;
        dataOut = 0;
        data_in = 0;
        key = 0;
        offset = 0;
    end

    always @(posedge reset) begin
        state <= `IDLE;
        reqIn = 0;
        reqOut = 0;
        dataOut = 0;
        data_in = 0;
        key = 0;
        offset = 0;
    end

    always @(posedge prog) begin
        state <= `READING_KEY;
    end

    always @(posedge rdyIn) begin
        state <= `READING_DATA;
    end

    always @(posedge cap) begin
        state <= `WAITING_RDY_DATA_IN;
        reqOut = 0;
        reqIn = 1;
    end

    always @(posedge clk) begin
        case (state)
            `READING_KEY: begin
                keyTemp = dataIn;
                state = `WAITING_RDY_DATA_IN;
                reqIn = 1;
            end

            `READING_DATA: begin
                data_in = dataIn;
                offset = rot_offset;
                state = `ENCRYPTING;
                reqIn = 0;
            end

            `ENCRYPTING: begin
                key = (keyTemp << offset) | (keyTemp >> (`KEY_WIDTH-offset));
                data_out = data_in ^ key;
                state = `SENDING_DATA;
            end
        endcase
    end

    always @(negedge clk) begin
        case (state)
            `SENDING_DATA: begin
                dataOut = data_out;
                reqOut = 1;
            end
        endcase
    end
endmodule

Icarus-Verliog-testing/Encrypter/encrypter_tb.sv
`timescale 1ns/1ps

`include "./Constants/constants.vh"
`include "./Encrypter/encrypter.sv"

module Encrypter_tb;

    reg clk;
    reg reset;

    reg [`ENCRYPTER_WIDTH-1:0] dataIn;
    reg [`KEY_ROTATION_WIDTH-1:0] rot_offset;
    reg rdyIn;
    reg cap;
    reg prog;

    wire [`ENCRYPTER_WIDTH-1:0] dataOut;
    wire reqIn;
    wire reqOut;
    wire [2:0] state;
    wire [`KEY_WIDTH-1:0] key;
    wire [`ENCRYPTER_WIDTH-1:0] data_in;

Encrypter DUT(
    .clk(clk),
    .reset(reset),
    .dataIn(dataIn),
    .rot_offset(rot_offset),
    .rdyIn(rdyIn),
    .cap(cap),
    .prog(prog),
    .dataOut(dataOut),
    .reqIn(reqIn),
    .reqOut(reqOut),
    .state(state),
    .key(key),
    .data_in(data_in)
);

initial begin
    //clock generation
    clk = 1;
    forever #5 clk = ~clk;
end

initial begin
    //initialization
    reset = 1;#10;
    reset = 0;
end

initial begin
    
    #20;
    dataIn = 16'b1100110011100011; #10;
    prog = 1;#10;

end

initial begin
    //monitoring
    $dumpfile("Encrypter/encrypter_tb.vcd");
    $dumpvars(1, Encrypter_tb);

    $monitor("data_out: %b\trdyIn: %d\tcap: %d\treqIn: %d\treqOut: %d\tkey: %b\toffset: %d",dataOut,rdyIn,cap,reqIn,reqOut,key,rot_offset);
    #170;$finish;
end

always @(posedge reqOut) begin
    #10 cap = 0;
    #10 cap = 1;
end

always @(posedge reqIn) begin
    #5 
    dataIn = 16'b1111000011110000;
    rot_offset = 4'b0111; #5;
    rdyIn = 1;
end

always @(negedge reqIn) begin
    #10 rdyIn = 0;
end

endmodule

Icarus-Verliog-testing/Encrypter/encrypter_tb.vcd
$date
	Tue May  7 11:59:21 2024
$end
$version
	Icarus Verilog
$end
$timescale
	1ps
$end
$scope module Encrypter_tb $end
$var wire 3 ! state [2:0] $end
$var wire 1 " reqOut $end
$var wire 1 # reqIn $end
$var wire 16 $ key [15:0] $end
$var wire 16 % data_in [15:0] $end
$var wire 16 & dataOut [15:0] $end
$var reg 1 ' cap $end
$var reg 1 ( clk $end
$var reg 16 ) dataIn [15:0] $end
$var reg 1 * prog $end
$var reg 1 + rdyIn $end
$var reg 1 , reset $end
$var reg 4 - rot_offset [3:0] $end
$upscope $end
$enddefinitions $end
#0
$dumpvars
bx -
1,
x+
x*
bx )
1(
x'
b0 &
b0 %
b0 $
0#
0"
b0 !
$end
#5000
0(
#10000
1(
0,
#15000
0(
#20000
1(
b1100110011100011 )
#25000
0(
#30000
b1 !
1(
1*
#35000
0(
#40000
1#
b10 !
1(
#45000
b111 -
b1111000011110000 )
0(
#50000
b11 !
1+
1(
#55000
0(
#60000
0#
b100 !
b1111000011110000 %
1(
#65000
0(
#70000
b101 !
b111000111100110 $
1(
0+
#75000
1"
b1000000100010110 &
0(
#80000
1(
#85000
0(
0'
#90000
1(
#95000
b10 !
1#
1"
0(
1'
#100000
1(
#105000
b11 !
1+
0(
0'
#110000
0#
b100 !
1(
#115000
b10 !
1#
0"
0(
1'
#120000
1(
0+
#125000
b11 !
1+
0(
#130000
0#
b100 !
1(
#135000
0(
#140000
b101 !
1(
0+
#145000
1"
0(
#150000
1(
#155000
0(
0'
#160000
1(
#165000
b10 !
1#
1"
0(
1'
