Icarus-Verliog-testing/Constants/constants.vh
//DEFINE CONSTANTS
// `define KEY_WIDTH 16 // width of the key. In multiples of 4.
// `define KEY_QSPI_COUNT `KEY_WIDTH/4 // number of QSPI transactions per key sent in LSB. 
// `define KEY_QSPI_COUNT_REG $clog2(`KEY_QSPI_COUNT+1) // register size required to count the current QSPI transaction of the key + 1. log2(`KEY_QSPI_COUNT+1)

`define ENCRYPTER_WIDTH 32 // width of the bus between the Paralellizer and Encrypter, and the Encrypter and Collector. In multiples of 4.
`define ENCRYPTER_WIDTH_COUNT_REG $clog2(`ENCRYPTER_WIDTH+1) // register size required to count the current bit of the encrypter bus + 1. log2(`ENCRYPTER_WIDTH+1). (Verilog doesn't like me so i need a for loop)
`define ENCRYPTER_QSPI_COUNT `ENCRYPTER_WIDTH/4 // number of QSPI transactions per Encrypter.
`define ENCRYPTER_QSPI_COUNT_REG $clog2(`ENCRYPTER_QSPI_COUNT+1) // register size required to count the current QSPI transaction of the Encrypter + 1. log2(`ENCRYPTER_QSPI_COUNT+1)

`define KEY_ROTATION_WIDTH $clog2(`ENCRYPTER_WIDTH) // width of the key rotation bus between Paralellizer and Encrypter. log2(`KEY_WIDTH)
`define KEY_ROTATION_WIDTH_COUNT_REG $clog2(`KEY_ROTATION_WIDTH+1) // register size required to count the current bit of the key rotation bus + 1. log2(`KEY_ROTATION_WIDTH+1). (Verilog doesn't like me so i need a for loop)

// `define KEY_ENCRYPTER_COUNT `KEY_WIDTH/`ENCRYPTER_WIDTH // number of Encrypters transactions per key. `KEY_WIDTH/`ENCRYPTER_WIDTH
// `define KEY_ENCRYPTER_COUNT_REG $clog2(`KEY_ENCRYPTER_COUNT+1) // register size required to count the current Encrypter transaction of the key + 1. log2(`KEY_ENCRYPTER_COUNT+1)

`define NUM_ENCRYPTERS 2 // number of Encrypters
`define NUM_ENCRYPTERS_REG $clog2(`NUM_ENCRYPTERS+1) // register size required to count the current Encrypter + 1. log2(`NUM_ENCRYPTERS+1)

Icarus-Verliog-testing/Encrypter/encrypter.sv
`include "./Constants/constants.vh"

`define IDLE 3'b000
`define READING_KEY 3'b001
`define WAITING_RDY_DATA_IN 3'b010
`define READING_DATA_ENCRYPTING 3'b011
`define SENDING_DATA 3'b100

module Encrypter (
    input wire clk,
    input wire reset,

    input wire [`ENCRYPTER_WIDTH-1:0] dataIn,
    input wire [`KEY_ROTATION_WIDTH-1:0] rot_offset,
    input wire dataRdyIn,
    input wire cap,
    input wire prog,

    output reg [`ENCRYPTER_WIDTH-1:0] dataOut,
    output reg rdyIn,
    output reg dataRdyOut,

    output reg [2:0] state,
    output reg [`KEY_WIDTH-1:0] keyRotated,
    output reg [`ENCRYPTER_WIDTH-1:0] data_in
);

    reg [`KEY_WIDTH-1:0] keyOrigin;
    reg [`KEY_ROTATION_WIDTH:0] offset;

    initial begin
        state <= `IDLE;
        rdyIn = 0;
        dataRdyOut = 0;
        dataOut = 0;
        data_in = 0;
        keyOrigin = 0;
        keyRotated = 0;
        offset = 0;
    end

    always @(posedge reset) begin
        state <= `IDLE;
        rdyIn = 0;
        dataRdyOut = 0;
        dataOut = 0;
        data_in = 0;
        keyOrigin = 0;
        keyRotated = 0;
        offset = 0;
    end

    always @(posedge prog) begin
        state <= `READING_KEY;
    end

    always @(posedge dataRdyIn) begin
        state <= `READING_DATA_ENCRYPTING;
    end

    always @(posedge cap) begin
        state <= `WAITING_RDY_DATA_IN;
        dataRdyOut = 0;
        rdyIn = 1;
    end

    always @(posedge clk) begin
        case (state)
            `READING_KEY: begin
                keyOrigin = dataIn;
                state = `WAITING_RDY_DATA_IN;
                rdyIn = 1;
            end

            `READING_DATA_ENCRYPTING: begin
                data_in = dataIn;
                offset = rot_offset;
                rdyIn = 0;
                keyRotated = (keyOrigin << offset) | (keyOrigin >> (`KEY_WIDTH-offset));
                dataOut = data_in ^ keyRotated;
                state = `SENDING_DATA;
            end
        endcase
    end

    always @(negedge clk) begin
        case (state)
            `SENDING_DATA: begin
                dataRdyOut = 1;
            end
        endcase
    end
endmodule

Icarus-Verliog-testing/Encrypter/encrypter_tb.sv
`timescale 1ns/1ps

`include "./Constants/constants.vh"
`include "./Encrypter/encrypter.sv"

module Encrypter_tb;

    reg clk;
    reg reset;

    reg [`ENCRYPTER_WIDTH-1:0] dataIn;
    reg [`KEY_ROTATION_WIDTH-1:0] rot_offset;
    reg dataRdyIn;
    reg cap;
    reg prog;

    wire [`ENCRYPTER_WIDTH-1:0] dataOut;
    wire rdyIn;
    wire dataRdyOut;
    wire [2:0] state;
    wire [`KEY_WIDTH-1:0] keyRotated;
    wire [`ENCRYPTER_WIDTH-1:0] data_in;

Encrypter DUT(
    .clk(clk),
    .reset(reset),
    .dataIn(dataIn),
    .rot_offset(rot_offset),
    .dataRdyIn(dataRdyIn),
    .cap(cap),
    .prog(prog),
    .dataOut(dataOut),
    .rdyIn(rdyIn),
    .dataRdyOut(dataRdyOut),
    .state(state),
    .keyRotated(keyRotated),
    .data_in(data_in)
);

initial begin
    //clock generation
    clk = 1;
    forever #5 clk = ~clk;
end

initial begin
    //initialization
    reset = 1;#10;
    reset = 0;
end

initial begin
    
    #20;
    dataIn = 16'b1100110011100011; #10;
    prog = 1;#10;

end

initial begin
    //monitoring
    $dumpfile("Encrypter/encrypter_tb.vcd");
    $dumpvars(1, Encrypter_tb);

    $monitor("data_out: %b\tdataRdyIn: %d\tcap: %d\trdyIn: %d\tdataRdyOut: %d\tkeyRotated: %b\toffset: %d",dataOut,dataRdyIn,cap,rdyIn,dataRdyOut,keyRotated,rot_offset);
    #170;$finish;
end

always @(posedge dataRdyOut) begin
    #10 cap = 0;
    #10 cap = 1;
end

always @(posedge rdyIn) begin
    #5 
    dataIn = 16'b1111000011110000;
    rot_offset = 4'b0111; #5;
    dataRdyIn = 1;
end

always @(negedge rdyIn) begin
    #10 dataRdyIn = 0;
end

endmodule

Icarus-Verliog-testing/Encrypter/encrypter_tb.vcd
$date
	Tue May  7 12:37:38 2024
$end
$version
	Icarus Verilog
$end
$timescale
	1ps
$end
$scope module Encrypter_tb $end
$var wire 3 ! state [2:0] $end
$var wire 1 " rdyIn $end
$var wire 16 # keyRotated [15:0] $end
$var wire 16 $ data_in [15:0] $end
$var wire 1 % dataRdyOut $end
$var wire 16 & dataOut [15:0] $end
$var reg 1 ' cap $end
$var reg 1 ( clk $end
$var reg 16 ) dataIn [15:0] $end
$var reg 1 * dataRdyIn $end
$var reg 1 + prog $end
$var reg 1 , reset $end
$var reg 4 - rot_offset [3:0] $end
$upscope $end
$enddefinitions $end
#0
$dumpvars
bx -
1,
x+
x*
bx )
1(
x'
b0 &
0%
b0 $
b0 #
0"
b0 !
$end
#5000
0(
#10000
1(
0,
#15000
0(
#20000
1(
b1100110011100011 )
#25000
0(
#30000
b1 !
1(
1+
#35000
0(
#40000
1"
b10 !
1(
#45000
b111 -
b1111000011110000 )
0(
#50000
b11 !
1*
1(
#55000
0(
#60000
b100 !
b1000000100010110 &
b111000111100110 #
0"
b1111000011110000 $
1(
#65000
1%
0(
#70000
1(
0*
#75000
0(
0'
#80000
1(
#85000
b10 !
1"
1%
0(
1'
#90000
1(
#95000
b11 !
1*
0(
0'
#100000
b100 !
0"
1(
#105000
b10 !
1"
1%
0(
1'
#110000
1(
0*
#115000
b11 !
1*
0(
0'
#120000
b100 !
0"
1(
#125000
b10 !
1"
1%
0(
1'
#130000
1(
0*
#135000
b11 !
1*
0(
0'
#140000
b100 !
0"
1(
#145000
b10 !
1"
1%
0(
1'
#150000
1(
0*
#155000
b11 !
1*
0(
0'
#160000
b100 !
0"
1(
#165000
b10 !
1"
1%
0(
1'
#170000
1(
0*
